Workbook

Sheet Допущения
A1: Допущения модели. Меняйте значения в колонках C–E (жёлтые): все листы пересчитаются. ФАКТ = есть источник, ОЦЕНКА = допущение аналитика.
A2: id | B2: Допущение | C2: Осторожный | D2: Базовый | E2: Оптимистичный | F2: Ед. | G2: Источник / тип | H2: Уверенность
B3: ОБЩИЕ: КОММЕРЦИЯ НА OZON
A4: aov | B4: Средний чек заказа на Ozon (детские вещи) | C4: 1300 | D4: 1600 | E4: 2000 | F4: ₽ | G4: Владелец (1 600 ₽). Края диапазона: оценка | H4: средняя
A5: ds_margin | B5: Чистая маржа дропшиппинга FBS на заказ (после комиссии, логистики, возвратов, налога) | C5: 0.08 | D5: 0.12 | E5: 0.18 | F5: % от чека | G5: ОЦЕНКА. Комиссии Ozon 2026 на одежду и детские товары 43–55% (Коммерсантъ 8401352, RB.ru, Selsup). Прежний анализ брал 15%. Нужна выгрузка владельца | H5: низкая
A6: cr_ozon | B6: Конверсия внешнего клика в заказ на Ozon | C6: 0.02 | D6: 0.035 | E6: 0.05 | F6: % | G6: ОЦЕНКА: публичной статистики нет. Прежний анализ брал 5% | H6: низкая
A7: ozon_mult | B7: «Эффект Ozon»: множитель к заказам от внешнего трафика (органика) | C7: 1 | D7: 1.15 | E7: 1.5 | F7: x | G7: ОЦЕНКА: Ozon официально не подтверждает влияние внешнего трафика на ранжирование | H7: низкая
A8: rpm | B8: Доход РСЯ на 1 000 визитов сайта | C8: 40 | D8: 80 | E8: 150 | F8: ₽ | G8: Нет данных по нише; Habr: десятки центов за 1 000 показов. ОЦЕНКА | H8: низкая
A9: tg_cps | B9: Стоимость платного подписчика Telegram (посевы, ниша дети и родители) | C9: 300 | D9: 180 | E9: 100 | F9: ₽ | G9: Обзор по тематикам: «дети и родители» 120–600 ₽ (нативные посевы); TG Ads, детская психология: 32–105 ₽ (Habr) | H9: средняя
A10: tg_cpm | B10: CPM рекламного поста в своём канале | C10: 300 | D10: 500 | E10: 700 | F10: ₽ | G10: ОЦЕНКА. Канал 50k: 3–10 тыс. ₽ за пост (Точка, Tele-scope); мем-каналы CPM 150–200, IT 1 000–2 000 | H10: средняя
A11: tg_view | B11: Доля подписчиков, видящих пост | C11: 0.22 | D11: 0.28 | E11: 0.35 | F11: % | G11: ОЦЕНКА (типичный ERR для каналов 10–60k) | H11: средняя
A12: tg_ads_pm | B12: Рекламных постов в месяц в своём канале | C12: 4 | D12: 8 | E12: 12 | F12: шт | G12: ОЦЕНКА; больше постов снижают охват | H12: средняя
A13: tg_org | B13: Доля подписчиков, пришедших бесплатно (из клипов, SEO) | C13: 0.2 | D13: 0.4 | E13: 0.6 | F13: % | G13: ОЦЕНКА | H13: низкая
A14: tax_serv | B14: Налог с выручки услуг/обучения (УСН доходы) | C14: 0.06 | D14: 0.06 | E14: 0.06 | F14: % | G14: ОЦЕНКА; режим уточнить у владельца | H14: средняя
B15: КОНТЕНТ-ЯДРО
A16: core_full | B16: Полный эскалатор: команда и гонорары в месяц | C16: 480000 | D16: 420000 | E16: 360000 | F16: ₽/мес | G16: ОЦЕНКА: продюсер-редактор, монтаж, SEO-автор, SMM, гонорары профессорам и рецензентам. Прежний анализ: 300–500 тыс. | H16: средняя
A17: core_lite | B17: Урезанное ядро (без подкастов и сетки блогов) | C17: 220000 | D17: 180000 | E17: 150000 | F17: ₽/мес | G17: ОЦЕНКА: 1 редактор-продюсер, монтаж на сдельной, рецензент | H17: средняя
A18: capex_full | B18: Старт полного эскалатора (сайт, дизайн, техника) | C18: 600000 | D18: 400000 | E18: 300000 | F18: ₽ | G18: ОЦЕНКА; свой продакшн снижает | H18: средняя
A19: capex_lite | B19: Старт урезанного ядра | C19: 250000 | D19: 150000 | E19: 100000 | F19: ₽ | G19: ОЦЕНКА | H19: средняя
B20: A. ПОЛНЫЙ ЭСКАЛАТОР → ДРОПШИППИНГ OZON
A21: A_visits | B21: Визиты сайта в месяц на 36-м месяце | C21: 60000 | D21: 150000 | E21: 400000 | F21: визитов | G21: Прежний анализ 60/200/500 тыс.; база снижена из-за нейроответов (инфо-сайты −30%, Kokoc через ppc.world; −15…−60%, Timeweb) | H21: низкая
A22: A_subs | B22: Подписчики Telegram на 36-м месяце | C22: 10000 | D22: 25000 | E22: 60000 | F22: подп. | G22: Прежний 15/40/100 тыс. снижен: каждый подписчик стоит денег (см. tg_cps) | H22: низкая
A23: A_clips | B23: Просмотры клипов в месяц на 36-м месяце | C23: 2000000 | D23: 6000000 | E23: 15000000 | F23: просм. | G23: Прежний анализ; ОЦЕНКА | H23: низкая
A24: A_ctr_site | B24: Доля визитов медстатей с кликом на Ozon | C24: 0.005 | D24: 0.012 | E24: 0.025 | F24: % | G24: ОЦЕНКА: информационный медицинский интент, товар не в фокусе | H24: низкая
A25: A_click_sub | B25: Кликов на Ozon на подписчика в месяц | C25: 0.15 | D25: 0.3 | E25: 0.6 | F25: клик | G25: ОЦЕНКА | H25: низкая
A26: A_ctr_clip | B26: Кликов на Ozon на 1 просмотр клипа | C26: 0.0001 | D26: 0.0003 | E26: 0.0005 | F26: % | G26: ОЦЕНКА: клипы VK/Rutube дают мало переходов | H26: низкая
A27: A_start | B27: Месяц начала трафика | C27: 3 | D27: 3 | E27: 2 | F27: мес | G27: ОЦЕНКА | H27: средняя
A28: A_k | B28: Форма кривой роста (>1 медленный старт) | C28: 1.5 | D28: 1.3 | E28: 1.1 | G28: ОЦЕНКА | H28: средняя
B29: D. ПЛАТНЫЕ КУРСЫ И КЛУБ ДЛЯ РОДИТЕЛЕЙ (поверх A)
A30: D_start | B30: Месяц первого запуска | C30: 12 | D30: 9 | E30: 7 | F30: мес | G30: ОЦЕНКА | H30: средняя
A31: D_price | B31: Цена курса | C31: 1900 | D31: 2900 | E31: 3900 | F31: ₽ | G31: ОЦЕНКА; на рынке много бесплатного (Stepik, бесплатные курсы первой помощи) | H31: низкая
A32: D_launch | B32: Запусков курса в год | C32: 2 | D32: 3 | E32: 4 | F32: шт | G32: ОЦЕНКА | H32: средняя
A33: D_conv | B33: Конверсия тёплой аудитории в покупку за запуск | C33: 0.004 | D33: 0.01 | E33: 0.018 | F33: % | G33: ОЦЕНКА (инфобиз: 0,5–2% от базы) | H33: низкая
A34: D_warm | B34: Доп. тёплая база (email, VK) к подписчикам TG | C34: 0.5 | D34: 0.8 | E34: 1 | F34: x | G34: ОЦЕНКА | H34: низкая
A35: D_club_price | B35: Подписка клуба | C35: 290 | D35: 390 | E35: 490 | F35: ₽/мес | G35: ОЦЕНКА | H35: средняя
A36: D_club_pen | B36: Доля тёплой базы в клубе | C36: 0.003 | D36: 0.008 | E36: 0.015 | F36: % | G36: ОЦЕНКА | H36: низкая
A37: D_fees | B37: Платформа и эквайринг | C37: 0.12 | D37: 0.1 | E37: 0.08 | F37: % выручки | G37: ОЦЕНКА | H37: средняя
A38: D_mkt | B38: Реклама запусков | C38: 0.25 | D38: 0.2 | E38: 0.15 | F38: % выручки курса | G38: ОЦЕНКА | H38: низкая
A39: D_team | B39: Куратор и поддержка | C39: 120000 | D39: 100000 | E39: 80000 | F39: ₽/мес | G39: ОЦЕНКА | H39: средняя
A40: D_capex | B40: Производство 2 курсов | C40: 1200000 | D40: 800000 | E40: 600000 | F40: ₽ | G40: ОЦЕНКА | H40: средняя
B41: B. PRIVATE LABEL: СВОЙ ДЕТСКИЙ ТЕКСТИЛЬ НА OZON
A42: B_start | B42: Месяц первых продаж | C42: 5 | D42: 4 | E42: 3 | F42: мес | G42: ОЦЕНКА: лекала, образцы, декларация ТР ТС, маркировка | H42: средняя
A43: B_sku | B43: Число SKU (модель×цвет) к 36-му месяцу | C43: 15 | D43: 30 | E43: 50 | F43: SKU | G43: ОЦЕНКА | H43: средняя
A44: B_upm | B44: Продаж на SKU в месяц в зрелости | C44: 40 | D44: 90 | E44: 160 | F44: шт | G44: ОЦЕНКА; проверить по своим 30 тыс. карточек | H44: низкая
A45: B_price | B45: Цена продажи | C45: 1700 | D45: 1900 | E45: 2200 | F45: ₽ | G45: ОЦЕНКА (слипы, спальники, муслин) | H45: средняя
A46: B_cogs | B46: Себестоимость пошива | C46: 0.3 | D46: 0.26 | E46: 0.23 | F46: % цены | G46: Иваново: 300–1 500 ₽/ед., тираж от 100 на модель (Uniseller) | H46: средняя
A47: B_comm | B47: Комиссия Ozon | C47: 0.5 | D47: 0.45 | E47: 0.4 | F47: % цены | G47: ФАКТ 2026: одежда 43–55%, детские ~47–50% (Коммерсантъ, RB.ru, Selsup, Sellerblog) | H47: средняя
A48: B_log | B48: Логистика и обработка FBS на ед. | C48: 90 | D48: 70 | E48: 55 | F48: ₽ | G48: ОЦЕНКА: Ozon снизил логистику в обмен на рост комиссий (Oborot); +10 ₽ за отправление с 29.09.2026 (Selsup) | H48: средняя
A49: B_drr | B49: Реклама внутри Ozon (ДРР) | C49: 0.12 | D49: 0.09 | E49: 0.06 | F49: % выручки | G49: ОЦЕНКА | H49: средняя
A50: B_ret | B50: Возвраты, брак, уценка | C50: 0.06 | D50: 0.04 | E50: 0.02 | F50: % выручки | G50: ОЦЕНКА | H50: средняя
A51: B_mark | B51: Маркировка «Честный знак» и упаковка на ед. | C51: 30 | D51: 25 | E51: 20 | F51: ₽ | G51: Маркировка детской одежды обязательна с 01.03.2025 (честныйзнак.рф); сумма ОЦЕНКА | H51: средняя
A52: B_tax | B52: Налоги | C52: 0.07 | D52: 0.06 | E52: 0.04 | F52: % выручки | G52: ОЦЕНКА; режим и НДС уточнить у бухгалтера | H52: низкая
A53: B_inv | B53: Запас на складе | C53: 3 | D53: 2.5 | E53: 2 | F53: мес продаж | G53: ОЦЕНКА | H53: средняя
... A55: B_capex | B55: Старт: лекала, образцы, декларации, фото | C55: 600000 | D55: 400000 | E55: 300000 | F55: ₽ | G55: ОЦЕНКА | H55: средняя
A56: B_k | B56: Форма кривой роста | C56: 1.2 | D56: 1 | E56: 0.9 | G56: ОЦЕНКА | H56: средняя
B57: C. ОБУЧЕНИЕ ПРОФЕССИОНАЛОВ (ДПО/НМО с лицензией НГУ + первая помощь детям для педагогов)
A58: C_start | B58: Месяц первых продаж (договор с НГУ, утверждение программ) | C58: 10 | D58: 7 | E58: 5 | F58: мес | G58: ОЦЕНКА | H58: низкая
A59: C_share | B59: Доля владельца в выручке (остальное НГУ как лицензиату) | C59: 0.35 | D59: 0.5 | E59: 0.6 | F59: % | G59: ОЦЕНКА: условия НГУ неизвестны | H59: низкая
A60: C_pro_price | B60: Средний чек курса для медсестёр и педиатров | C60: 3500 | D60: 4500 | E60: 6000 | F60: ₽ | G60: Рынок: 144 ч для медсестёр 29 900 ₽ (kedu.ru); курсы для врачей 39–55 тыс. (checkroi). Короткие 18–36 ч: ОЦЕНКА | H60: средняя
A61: C_pro_n | B61: Продаж медработникам в месяц на 36-м мес. | C61: 60 | D61: 200 | E61: 500 | F61: шт | G61: ОЦЕНКА. Врачей ~558 тыс. (Минздрав, 2025); средний медперсонал ~1,3–1,5 млн (оценка) | H61: низкая
A62: C_ped_price | B62: Средний чек «Первая помощь детям» для педагогов и воспитателей | C62: 900 | D62: 1200 | E62: 1600 | F62: ₽ | G62: Нет данных; рынок массовый и дешёвый. ОЦЕНКА | H62: низкая
A63: C_ped_n | B63: Продаж педагогам в месяц на 36-м мес. (B2B через сады и школы) | C63: 200 | D63: 600 | E63: 1500 | F63: шт | G63: ОЦЕНКА. Обучение первой помощи педагогов обязательно (ст. 41 273-ФЗ) [ЮРИСТ] | H63: низкая
A64: C_cac | B64: Маркетинг и продажи | C64: 0.35 | D64: 0.25 | E64: 0.15 | F64: % валовой выручки | G64: ОЦЕНКА | H64: низкая
A65: C_team | B65: Методист и менеджер B2B | C65: 200000 | D65: 170000 | E65: 150000 | F65: ₽/мес | G65: ОЦЕНКА | H65: средняя
A66: C_capex | B66: Производство 4–6 программ (видео, тесты) | C66: 1500000 | D66: 1000000 | E66: 700000 | F66: ₽ | G66: ОЦЕНКА; свой продакшн | H66: средняя
A67: C_k | B67: Форма кривой роста | C67: 1.3 | D67: 1.2 | E67: 1 | G67: ОЦЕНКА | H67: средняя
B68: E. ПРОДАЖИ ОРГАНИЗАЦИЯМ (лицензия видеотеки + продакшн экспертного контента)
A69: E_lic_start | B69: Месяц первого лицензиата | C69: 9 | D69: 6 | E69: 5 | F69: мес | G69: ОЦЕНКА: цикл сделки 4–9 мес. | H69: низкая
A70: E_lic_n | B70: Лицензиатов на 36-м мес. (телемед, страховые, аптечные сети, работодатели) | C70: 1 | D70: 3 | E70: 6 | F70: шт | G70: ОЦЕНКА | H70: низкая
A71: E_lic_price | B71: Лицензия видеотеки в год на клиента | C71: 600000 | D71: 1200000 | E71: 2000000 | F71: ₽/год | G71: ОЦЕНКА; публичных прайсов нет | H71: низкая
A72: E_ag_start | B72: Месяц первого клиента продакшна | C72: 4 | D72: 3 | E72: 2 | F72: мес | G72: ОЦЕНКА | H72: средняя
A73: E_ag_n | B73: Клиентов продакшна (клиники, бренды без «веществ») на 36-м мес. | C73: 1 | D73: 2 | E73: 4 | F73: шт | G73: ОЦЕНКА | H73: средняя
A74: E_ag_fee | B74: Абонентская плата продакшна | C74: 100000 | D74: 150000 | E74: 200000 | F74: ₽/мес | G74: ОЦЕНКА | H74: средняя
A75: E_ag_margin | B75: Маржа продакшна | C75: 0.3 | D75: 0.4 | E75: 0.45 | F75: % | G75: ОЦЕНКА | H75: средняя
A76: E_sales | B76: Менеджер по B2B | C76: 130000 | D76: 110000 | E76: 90000 | F76: ₽/мес | G76: ОЦЕНКА | H76: средняя
A77: E_capex | B77: Демо-ролики, презентация, договоры | C77: 200000 | D77: 150000 | E77: 100000 | F77: ₽ | G77: ОЦЕНКА | H77: средняя
B78: F. МИНИМУМ: SEO-ПОДБОРКИ И TELEGRAM-КАНАЛ ПОД OZON
A79: F_visits | B79: Визиты коммерческих подборок в месяц на 36-м мес. | C79: 25000 | D79: 60000 | E79: 120000 | F79: визитов | G79: ОЦЕНКА: коммерческий интент, меньше Нейро | H79: низкая
A80: F_ctr | B80: Доля визитов с кликом на Ozon | C80: 0.08 | D80: 0.12 | E80: 0.18 | F80: % | G80: ОЦЕНКА (подборки и обзоры) | H80: средняя
A81: F_subs | B81: Подписчики канала находок на 36-м мес. | C81: 4000 | D81: 12000 | E81: 30000 | F81: подп. | G81: ОЦЕНКА | H81: низкая
A82: F_click_sub | B82: Кликов на подписчика в месяц | C82: 0.8 | D82: 1.2 | E82: 2 | F82: клик | G82: ОЦЕНКА | H82: низкая
A83: F_org | B83: Доля бесплатных подписчиков канала | C83: 0.2 | D83: 0.3 | E83: 0.4 | F83: % | G83: ОЦЕНКА | H83: низкая
A84: F_team | B84: Команда F отдельно | C84: 130000 | D84: 110000 | E84: 90000 | F84: ₽/мес | G84: ОЦЕНКА: 1 редактор + LLM + точечная проверка врачом | H84: средняя
A85: F_incr | B85: Прирост затрат F поверх ядра (в комбинации R) | C85: 70000 | D85: 50000 | E85: 40000 | F85: ₽/мес | G85: ОЦЕНКА | H85: средняя
A86: F_capex | B86: Старт F | C86: 150000 | D86: 100000 | E86: 70000 | F86: ₽ | G86: ОЦЕНКА | H86: средняя
A87: F_k | B87: Форма кривой роста | C87: 1.3 | D87: 1.2 | E87: 1 | G87: ОЦЕНКА | H87: средняя

Sheet Сводка
A1: Сводка по моделям и сценариям (₽). Пересчитывается из листов моделей. 99 = не достигнуто за 36 мес.
A2: Модель | B2: Сценарий | C2: Выручка год 1 | D2: Выручка год 2 | E2: Выручка год 3 | F2: Опер. прибыль год 3 | G2: Опер. прибыль, мес. 36 | H2: Макс. глубина минуса | I2: Накоплено за 36 мес | J2: Мес. устойчивой опер. прибыли | K2: Мес. окупаемости | L2: CAPEX+оборотка 36 мес
A3: A. Эскалатор → дропшиппинг | B3: Осторожный | C3: =A_дропшиппинг!AM10 -> 37421.799 | D3: =A_дропшиппинг!AN10 -> 214436.15 | E3: =A_дропшиппинг!AO10 -> 481526.54 | F3: =A_дропшиппинг!AO17 -> -6847586.6 | G3: =A_дропшиппинг!AL17 -> -576058.35 | H3: =MIN(0,MIN(A_дропшиппинг!C20:AL20)) -> -20184999 | I3: =A_дропшиппинг!AL20 -> -20184999 | J3: =MIN(A_дропшиппинг!C21:AL21) -> 99 | K3: =MIN(A_дропшиппинг!C22:AL22) -> 99 | L3: =A_дропшиппинг!AP18 -> 600000
A4: A. Эскалатор → дропшиппинг | B4: Базовый | C4: =A_дропшиппинг!AM30 -> 707307.05 | D4: =A_дропшиппинг!AN30 -> 3380003.3 | E4: =A_дропшиппинг!AO30 -> 6839270.1 | F4: =A_дропшиппинг!AO37 -> -5019487.7 | G4: =A_дропшиппинг!AL37 -> -398675.88 | H4: =MIN(0,MIN(A_дропшиппинг!C40:AL40)) -> -16396795 | I4: =A_дропшиппинг!AL40 -> -16396795 | J4: =MIN(A_дропшиппинг!C41:AL41) -> 99 | K4: =MIN(A_дропшиппинг!C42:AL42) -> 99 | L4: =A_дропшиппинг!AP38 -> 400000
A5: A. Эскалатор → дропшиппинг | B5: Оптимистичный | C5: =A_дропшиппинг!AM50 -> 12898301 | D5: =A_дропшиппинг!AN50 -> 45022667 | E5: =A_дропшиппинг!AO50 -> 79851626 | F5: =A_дропшиппинг!AO57 -> 11412540 | G5: =A_дропшиппинг!AL57 -> 1234996.1 | H5: =MIN(0,MIN(A_дропшиппинг!C60:AL60)) -> -2728050.9 | I5: =A_дропшиппинг!AL60 -> 12935721 | J5: =MIN(A_дропшиппинг!C61:AL61) -> 12 | K5: =MIN(A_дропшиппинг!C62:AL62) -> 22 | L5: =A_дропшиппинг!AP58 -> 300000
A6: D. Эскалатор + курсы/клуб (A+D) | B6: Осторожный | C6: =D_курсы_родителям!AM9 -> 5112.2215 | D6: =D_курсы_родителям!AN9 -> 132166.9 | E6: =D_курсы_родителям!AO9 -> 296787.03 | F6: =D_курсы_родителям!AO13 -> -8088206.8 | G6: =D_курсы_родителям!AL13 -> -674527.35 | H6: =MIN(0,MIN(D_курсы_родителям!C16:AL16)) -> -24213396 | I6: =D_курсы_родителям!AL16 -> -24213396 | J6: =MIN(D_курсы_родителям!C17:AL17) -> 99 | K6: =MIN(D_курсы_родителям!C18:AL18) -> 99 | L6: =D_курсы_родителям!AP14 -> 1800000
A7: D. Эскалатор + курсы/клуб (A+D) | B7: Базовый | C7: =D_курсы_родителям!AM25 -> 308915.81 | D7: =D_курсы_родителям!AN25 -> 2206477.7 | E7: =D_курсы_родителям!AO25 -> 4464699 | F7: =D_курсы_родителям!AO29 -> -3093423.5 | G7: =D_курсы_родителям!AL29 -> -171939.88 | H7: =MIN(0,MIN(D_курсы_родителям!C32:AL32)) -> -15209519 | I7: =D_курсы_родителям!AL32 -> -15209519 | J7: =MIN(D_курсы_родителям!C33:AL33) -> 99 | K7: =MIN(D_курсы_родителям!C34:AL34) -> 99 | L7: =D_курсы_родителям!AP30 -> 1200000
A8: D. Эскалатор + курсы/клуб (A+D) | B8: Оптимистичный | C8: =D_курсы_родителям!AM41 -> 4677746.3 | D8: =D_курсы_родителям!AN41 -> 20702011 | E8: =D_курсы_родителям!AO41 -> 36716823 | F8: =D_курсы_родителям!AO45 -> 37837916 | G8: =D_курсы_родителям!AL45 -> 3907196.1 | H8: =MIN(0,MIN(D_курсы_родителям!C48:AL48)) -> -2911327.5 | I8: =D_курсы_родителям!AL48 -> 56170683 | J8: =MIN(D_курсы_родителям!C49:AL49) -> 7 | K8: =MIN(D_курсы_родителям!C50:AL50) -> 13 | L8: =D_курсы_родителям!AP46 -> 900000
A9: B. Свой бренд текстиля | B9: Осторожный | C9: =B_свой_бренд!AM6 -> 800910.83 | D9: =B_свой_бренд!AN6 -> 4766768.5 | E9: =B_свой_бренд!AO6 -> 9780998.6 | F9: =B_свой_бренд!AO13 -> -4299473.4 | G9: =B_свой_бренд!AL13 -> -383000 | H9: =MIN(0,MIN(B_свой_бренд!C16:AL16)) -> -12728870 | I9: =B_свой_бренд!AL16 -> -12728870 | J9: =MIN(B_свой_бренд!C17:AL17) -> 99 | K9: =MIN(B_свой_бренд!C18:AL18) -> 99 | L9: =B_свой_бренд!AP14 -> 1518000
A10: B. Свой бренд текстиля | B10: Базовый | C10: =B_свой_бренд!AM22 -> 6995454.5 | D10: =B_свой_бренд!AN22 -> 28914545 | E10: =B_свой_бренд!AO22 -> 51300000 | F10: =B_свой_бренд!AO29 -> -75000 | G10: =B_свой_бренд!AL29 -> 36500 | H10: =MIN(0,MIN(B_свой_бренд!C32:AL32)) -> -7294000 | I10: =B_свой_бренд!AL32 -> -7294000 | J10: =MIN(B_свой_бренд!C33:AL33) -> 32 | K10: =MIN(B_свой_бренд!C34:AL34) -> 99 | L10: =B_свой_бренд!AP30 -> 3734500
A11: B. Свой бренд текстиля | B11: Оптимистичный | C11: =B_свой_бренд!AM38 -> 33685821 | D11: =B_свой_бренд!AN38 -> 1.0995849e+08 | E11: =B_свой_бренд!AO38 -> 1.8006735e+08 | F11: =B_свой_бренд!AO45 -> 36718179 | G11: =B_свой_бренд!AL45 -> 3620000 | H11: =MIN(0,MIN(B_свой_бренд!C48:AL48)) -> -1227454.5 | I11: =B_свой_бренд!AL48 -> 55016291 | J11: =MIN(B_свой_бренд!C49:AL49) -> 4 | K11: =MIN(B_свой_бренд!C50:AL50) -> 10 | L11: =B_свой_бренд!AP46 -> 8396000
A12: C. Обучение профи (НГУ) | B12: Осторожный | C12: =C_обучение_профи!AM8 -> 14357.571 | D12: =C_обучение_профи!AN8 -> 432418.7 | E12: =C_обучение_профи!AO8 -> 1224331 | F12: =C_обучение_профи!AO12 -> -2473459.9 | G12: =C_обучение_профи!AL12 -> -208190 | H12: =MIN(0,MIN(C_обучение_профи!C15:AL15)) -> -8600266.4 | I12: =C_обучение_профи!AL15 -> -8600266.4 | J12: =MIN(C_обучение_профи!C16:AL16) -> 99 | K12: =MIN(C_обучение_профи!C17:AL17) -> 99 | L12: =C_обучение_профи!AP13 -> 1500000
A13: C. Обучение профи (НГУ) | B13: Базовый | C13: =C_обучение_профи!AM23 -> 380135.78 | D13: =C_обучение_профи!AN23 -> 3431133.7 | E13: =C_обучение_профи!AO23 -> 7641135.8 | F13: =C_обучение_профи!AO27 -> 1322099.8 | G13: =C_обучение_профи!AL27 -> 186400 | H13: =MIN(0,MIN(C_обучение_профи!C30:AL30)) -> -3266386.5 | I13: =C_обучение_профи!AL30 -> -1910941.7 | J13: =MIN(C_обучение_профи!C31:AL31) -> 23 | K13: =MIN(C_обучение_профи!C32:AL32) -> 99 | L13: =C_обучение_профи!AP28 -> 1000000
A14: C. Обучение профи (НГУ) | B14: Оптимистичный | C14: =C_обучение_профи!AM38 -> 3645000 | D14: =C_обучение_профи!AN38 -> 17617500 | E14: =C_обучение_профи!AO38 -> 32197500 | F14: =C_обучение_профи!AO42 -> 20416275 | G14: =C_обучение_профи!AL42 -> 2085600 | H14: =MIN(0,MIN(C_обучение_профи!C45:AL45)) -> -1240412.5 | I14: =C_обучение_профи!AL45 -> 30937400 | J14: =MIN(C_обучение_профи!C46:AL46) -> 7 | K14: =MIN(C_обучение_профи!C47:AL47) -> 12 | L14: =C_обучение_профи!AP43 -> 700000
A15: E. B2B: лицензия + продакшн | B15: Осторожный | C15: =E_B2B!AM7 -> 900000 | D15: =E_B2B!AN7 -> 1350000 | E15: =E_B2B!AO7 -> 1800000 | F15: =E_B2B!AO11 -> -3348000 | G15: =E_B2B!AL11 -> -279000 | H15: =MIN(0,MIN(E_B2B!C14:AL14)) -> -11423000 | I15: =E_B2B!AL14 -> -11423000 | J15: =MIN(E_B2B!C15:AL15) -> 99 | K15: =MIN(E_B2B!C16:AL16) -> 99 | L15: =E_B2B!AP12 -> 450000
A16: E. B2B: лицензия + продакшн | B16: Базовый | C16: =E_B2B!AM21 -> 1700000 | D16: =E_B2B!AN21 -> 4150000 | E16: =E_B2B!AO21 -> 6600000 | F16: =E_B2B!AO25 -> 564000 | G16: =E_B2B!AL25 -> 94000 | H16: =MIN(0,MIN(E_B2B!C28:AL28)) -> -4081000 | I16: =E_B2B!AL28 -> -3517000 | J16: =MIN(E_B2B!C29:AL29) -> 31 | K16: =MIN(E_B2B!C30:AL30) -> 99 | L16: =E_B2B!AP26 -> 300000
A17: E. B2B: лицензия + продакшн | B17: Оптимистичный | C17: =E_B2B!AM35 -> 3966666.7 | D17: =E_B2B!AN35 -> 11500000 | E17: =E_B2B!AO35 -> 19000000 | F17: =E_B2B!AO39 -> 10030000 | G17: =E_B2B!AL39 -> 1012000 | H17: =MIN(0,MIN(E_B2B!C42:AL42)) -> -1176000 | I17: =E_B2B!AL42 -> 13858667 | J17: =MIN(E_B2B!C43:AL43) -> 10 | K17: =MIN(E_B2B!C44:AL44) -> 16 | L17: =E_B2B!AP40 -> 200000
A18: F. Минимум: подборки + TG | B18: Осторожный | C18: =F_минимум!AM9 -> 158854 | D18: =F_минимум!AN9 -> 663934.09 | E18: =F_минимум!AO9 -> 1302563.9 | F18: =F_минимум!AO13 -> -1849963.1 | G18: =F_минимум!AL13 -> -153687.3 | H18: =MIN(0,MIN(F_минимум!C16:AL16)) -> -5604251.8 | I18: =F_минимум!AL16 -> -5604251.8 | J18: =MIN(F_минимум!C17:AL17) -> 99 | K18: =MIN(F_минимум!C18:AL18) -> 99 | L18: =F_минимум!AP14 -> 150000
A19: F. Минимум: подборки + TG | B19: Базовый | C19: =F_минимум!AM25 -> 1909703.8 | D19: =F_минимум!AN25 -> 7300042 | E19: =F_минимум!AO25 -> 13618861 | F19: =F_минимум!AO29 -> -237169.07 | G19: =F_минимум!AL29 -> 10034.058 | H19: =MIN(0,MIN(F_минимум!C32:AL32)) -> -2768294.1 | I19: =F_минимум!AL32 -> -2753793.5 | J19: =MIN(F_минимум!C33:AL33) -> 35 | K19: =MIN(F_минимум!C34:AL34) -> 99 | L19: =F_минимум!AP30 -> 100000
A20: F. Минимум: подборки + TG | B20: Оптимистичный | C20: =F_минимум!AM41 -> 23081143 | D20: =F_минимум!AN41 -> 73440000 | E20: =F_минимум!AO41 -> 1.2379886e+08 | F20: =F_минимум!AO45 -> 20768709 | G20: =F_минимум!AL45 -> 2079771.4 | H20: =MIN(0,MIN(F_минимум!C48:AL48)) -> -252468.57 | I20: =F_минимум!AL48 -> 34871600 | J20: =MIN(F_минимум!C49:AL49) -> 4 | K20: =MIN(F_минимум!C50:AL50) -> 6 | L20: =F_минимум!AP46 -> 70000
A21: R. Комбо: ядро-лайт + C + E + F | B21: Осторожный | C21: =R_комбо!AM8 -> 927065.89 | D21: =R_комбо!AN8 -> 1835533.4 | E21: =R_комбо!AO8 -> 3128536.1 | F21: =R_комбо!AO12 -> -6951423 | G21: =R_комбо!AL12 -> -580877.3 | H21: =MIN(0,MIN(R_комбо!C15:AL15)) -> -23467518 | I21: =R_комбо!AL15 -> -23467518 | J21: =MIN(R_комбо!C16:AL16) -> 99 | K21: =MIN(R_комбо!C17:AL17) -> 99 | L21: =R_комбо!AP13 -> 2100000
A22: R. Комбо: ядро-лайт + C + E + F | B22: Базовый | C22: =R_комбо!AM23 -> 2309300.2 | D22: =R_комбо!AN23 -> 8457138.7 | E22: =R_комбо!AO23 -> 15875399 | F22: =R_комбо!AO27 -> 2368930.7 | G22: =R_комбо!AL27 -> 350434.06 | H22: =MIN(0,MIN(R_комбо!C30:AL30)) -> -8431658.3 | I22: =R_комбо!AL30 -> -6021735.2 | J22: =MIN(R_комбо!C31:AL31) -> 23 | K22: =MIN(R_комбо!C32:AL32) -> 99 | L22: =R_комбо!AP28 -> 1400000
A23: R. Комбо: ядро-лайт + C + E + F | B23: Оптимистичный | C23: =R_комбо!AM38 -> 11766272 | D23: =R_комбо!AN38 -> 42336700 | E23: =R_комбо!AO38 -> 73481294 | F23: =R_комбо!AO42 -> 51814984 | G23: =R_комбо!AL42 -> 5227371.4 | H23: =MIN(0,MIN(R_комбо!C45:AL45)) -> -2069223.2 | I23: =R_комбо!AL45 -> 81467667 | J23: =MIN(R_комбо!C46:AL46) -> 6 | K23: =MIN(R_комбо!C47:AL47) -> 10 | L23: =R_комбо!AP43 -> 970000

Sheet A_дропшиппинг
A1: A. Полный эскалатор → трафик на свои карточки Ozon (дропшиппинг FBS)
A2: Реклама в TG продаётся только при ≥10 тыс. подписчиков (порог реестра РКН, 303-ФЗ: канал нужно зарегистрировать).
A4: Сценарий: Осторожный | B4: Месяц → | C4: 1 | D4: 2 | E4: 3 | F4: 4 | G4: 5 | H4: 6 | I4: 7 | J4: 8 | K4: 9 | L4: 10 | M4: 11 | N4: 12 | O4: 13 | P4: 14 | Q4: 15 | R4: 16 | S4: 17 | T4: 18 | U4: 19 | V4: 20 | W4: 21 | X4: 22 | Y4: 23 | Z4: 24 | AA4: 25 | AB4: 26 | AC4: 27 | AD4: 28 | AE4: 29 | AF4: 30 | AG4: 31 | AH4: 32 | AI4: 33 | AJ4: 34 | AK4: 35 | AL4: 36 | AM4: Год 1 | AN4: Год 2 | AO4: Год 3 | AP4: Итого 36 мес
A5: visits | B5: Визиты сайта | C5: =Допущения!$C$21*IF(C$4<Допущения!$C$27,0,((C$4-Допущения!$C$27+1)/(36-Допущения!$C$27+1))^Допущения!$C$28) -> 0 | D5: =Допущения!$C$21*IF(D$4<Допущения!$C$27,0,((D$4-Допущения!$C$27+1)/(36-Допущения!$C$27+1))^Допущения!$C$28) -> 0 | E5: =Допущения!$C$21*IF(E$4<Допущения!$C$27,0,((E$4-Допущения!$C$27+1)/(36-Допущения!$C$27+1))^Допущения!$C$28) -> 302.64456 | F5: =Допущения!$C$21*IF(F$4<Допущения!$C$27,0,((F$4-Допущения!$C$27+1)/(36-Допущения!$C$27+1))^Допущения!$C$28) -> 856.00809 | G5: =Допущения!$C$21*IF(G$4<Допущения!$C$27,0,((G$4-Допущения!$C$27+1)/(36-Допущения!$C$27+1))^Допущения!$C$28) -> 1572.5873 | H5: =Допущения!$C$21*IF(H$4<Допущения!$C$27,0,((H$4-Допущения!$C$27+1)/(36-Допущения!$C$27+1))^Допущения!$C$28) -> 2421.1565 | I5: =Допущения!$C$21*IF(I$4<Допущения!$C$27,0,((I$4-Допущения!$C$27+1)/(36-Допущения!$C$27+1))^Допущения!$C$28) -> 3383.6691 | J5: =Допущения!$C$21*IF(J$4<Допущения!$C$27,0,((J$4-Допущения!$C$27+1)/(36-Допущения!$C$27+1))^Допущения!$C$28) -> 4447.9485 | ... AL5: =Допущения!$C$21*IF(AL$4<Допущения!$C$27,0,((AL$4-Допущения!$C$27+1)/(36-Допущения!$C$27+1))^Допущения!$C$28) -> 60000 | AM5: =SUM(C5:N5) -> 43178.999 | AN5: =SUM(O5:Z5) -> 247426.33 | AO5: =SUM(AA5:AL5) -> 555607.55 | AP5: =SUM(C5:AL5) -> 846212.88
A6: subs | B6: Подписчики Telegram (на конец мес.) | C6: =Допущения!$C$22*IF(C$4<Допущения!$C$27,0,((C$4-Допущения!$C$27+1)/(36-Допущения!$C$27+1))^Допущения!$C$28) -> 0 | D6: =Допущения!$C$22*IF(D$4<Допущения!$C$27,0,((D$4-Допущения!$C$27+1)/(36-Допущения!$C$27+1))^Допущения!$C$28) -> 0 | E6: =Допущения!$C$22*IF(E$4<Допущения!$C$27,0,((E$4-Допущения!$C$27+1)/(36-Допущения!$C$27+1))^Допущения!$C$28) -> 50.44076 | F6: =Допущения!$C$22*IF(F$4<Допущения!$C$27,0,((F$4-Допущения!$C$27+1)/(36-Допущения!$C$27+1))^Допущения!$C$28) -> 142.66801 | G6: =Допущения!$C$22*IF(G$4<Допущения!$C$27,0,((G$4-Допущения!$C$27+1)/(36-Допущения!$C$27+1))^Допущения!$C$28) -> 262.09788 | H6: =Допущения!$C$22*IF(H$4<Допущения!$C$27,0,((H$4-Допущения!$C$27+1)/(36-Допущения!$C$27+1))^Допущения!$C$28) -> 403.52608 | I6: =Допущения!$C$22*IF(I$4<Допущения!$C$27,0,((I$4-Допущения!$C$27+1)/(36-Допущения!$C$27+1))^Допущения!$C$28) -> 563.94484 | J6: =Допущения!$C$22*IF(J$4<Допущения!$C$27,0,((J$4-Допущения!$C$27+1)/(36-Допущения!$C$27+1))^Допущения!$C$28) -> 741.32475 | ... AL6: =Допущения!$C$22*IF(AL$4<Допущения!$C$27,0,((AL$4-Допущения!$C$27+1)/(36-Допущения!$C$27+1))^Допущения!$C$28) -> 10000 | AM6: =N6 -> 1595.0769 | AN6: =Z6 -> 5204.939 | AO6: =AL6 -> 10000
A7: clips | B7: Просмотры клипов | C7: =Допущения!$C$23*IF(C$4<Допущения!$C$27,0,((C$4-Допущения!$C$27+1)/(36-Допущения!$C$27+1))^Допущения!$C$28) -> 0 | D7: =Допущения!$C$23*IF(D$4<Допущения!$C$27,0,((D$4-Допущения!$C$27+1)/(36-Допущения!$C$27+1))^Допущения!$C$28) -> 0 | E7: =Допущения!$C$23*IF(E$4<Допущения!$C$27,0,((E$4-Допущения!$C$27+1)/(36-Допущения!$C$27+1))^Допущения!$C$28) -> 10088.152 | F7: =Допущения!$C$23*IF(F$4<Допущения!$C$27,0,((F$4-Допущения!$C$27+1)/(36-Допущения!$C$27+1))^Допущения!$C$28) -> 28533.603 | G7: =Допущения!$C$23*IF(G$4<Допущения!$C$27,0,((G$4-Допущения!$C$27+1)/(36-Допущения!$C$27+1))^Допущения!$C$28) -> 52419.576 | H7: =Допущения!$C$23*IF(H$4<Допущения!$C$27,0,((H$4-Допущения!$C$27+1)/(36-Допущения!$C$27+1))^Допущения!$C$28) -> 80705.217 | I7: =Допущения!$C$23*IF(I$4<Допущения!$C$27,0,((I$4-Допущения!$C$27+1)/(36-Допущения!$C$27+1))^Допущения!$C$28) -> 112788.97 | J7: =Допущения!$C$23*IF(J$4<Допущения!$C$27,0,((J$4-Допущения!$C$27+1)/(36-Допущения!$C$27+1))^Допущения!$C$28) -> 148264.95 | ... AL7: =Допущения!$C$23*IF(AL$4<Допущения!$C$27,0,((AL$4-Допущения!$C$27+1)/(36-Допущения!$C$27+1))^Допущения!$C$28) -> 2000000 | AM7: =SUM(C7:N7) -> 1439300 | AN7: =SUM(O7:Z7) -> 8247544.3 | AO7: =SUM(AA7:AL7) -> 18520252 | AP7: =SUM(C7:AL7) -> 28207096
A8: clicks | B8: Клики на Ozon | C8: =C5*Допущения!$C$24+C6*Допущения!$C$25+C7*Допущения!$C$26 -> 0 | D8: =D5*Допущения!$C$24+D6*Допущения!$C$25+D7*Допущения!$C$26 -> 0 | E8: =E5*Допущения!$C$24+E6*Допущения!$C$25+E7*Допущения!$C$26 -> 10.088152 | F8: =F5*Допущения!$C$24+F6*Допущения!$C$25+F7*Допущения!$C$26 -> 28.533603 | G8: =G5*Допущения!$C$24+G6*Допущения!$C$25+G7*Допущения!$C$26 -> 52.419576 | H8: =H5*Допущения!$C$24+H6*Допущения!$C$25+H7*Допущения!$C$26 -> 80.705217 | I8: =I5*Допущения!$C$24+I6*Допущения!$C$25+I7*Допущения!$C$26 -> 112.78897 | J8: =J5*Допущения!$C$24+J6*Допущения!$C$25+J7*Допущения!$C$26 -> 148.26495 | ... AL8: =AL5*Допущения!$C$24+AL6*Допущения!$C$25+AL7*Допущения!$C$26 -> 2000 | AM8: =SUM(C8:N8) -> 1439.3 | AN8: =SUM(O8:Z8) -> 8247.5443 | AO8: =SUM(AA8:AL8) -> 18520.252 | AP8: =SUM(C8:AL8) -> 28207.096
A9: orders | B9: Заказы (с «эффектом Ozon») | C9: =C8*Допущения!$C$6*Допущения!$C$7 -> 0 | D9: =D8*Допущения!$C$6*Допущения!$C$7 -> 0 | E9: =E8*Допущения!$C$6*Допущения!$C$7 -> 0.20176304 | F9: =F8*Допущения!$C$6*Допущения!$C$7 -> 0.57067206 | G9: =G8*Допущения!$C$6*Допущения!$C$7 -> 1.0483915 | H9: =H8*Допущения!$C$6*Допущения!$C$7 -> 1.6141043 | I9: =I8*Допущения!$C$6*Допущения!$C$7 -> 2.2557794 | J9: =J8*Допущения!$C$6*Допущения!$C$7 -> 2.965299 | ... AL9: =AL8*Допущения!$C$6*Допущения!$C$7 -> 40 | AM9: =SUM(C9:N9) -> 28.785999 | AN9: =SUM(O9:Z9) -> 164.95089 | AO9: =SUM(AA9:AL9) -> 370.40503 | AP9: =SUM(C9:AL9) -> 564.14192
A10: rev | B10: Оборот на Ozon, ₽ | C10: =C9*Допущения!$C$4 -> 0 | D10: =D9*Допущения!$C$4 -> 0 | E10: =E9*Допущения!$C$4 -> 262.29195 | F10: =F9*Допущения!$C$4 -> 741.87368 | G10: =G9*Допущения!$C$4 -> 1362.909 | H10: =H9*Допущения!$C$4 -> 2098.3356 | I10: =I9*Допущения!$C$4 -> 2932.5132 | J10: =J9*Допущения!$C$4 -> 3854.8887 | ... AL10: =AL9*Допущения!$C$4 -> 52000 | AM10: =SUM(C10:N10) -> 37421.799 | AN10: =SUM(O10:Z10) -> 214436.15 | AO10: =SUM(AA10:AL10) -> 481526.54 | AP10: =SUM(C10:AL10) -> 733384.49
A11: c_comm | B11: Маржа дропшиппинга | C11: =C10*Допущения!$C$5 -> 0 | D11: =D10*Допущения!$C$5 -> 0 | E11: =E10*Допущения!$C$5 -> 20.983356 | F11: =F10*Допущения!$C$5 -> 59.349894 | G11: =G10*Допущения!$C$5 -> 109.03272 | H11: =H10*Допущения!$C$5 -> 167.86685 | I11: =I10*Допущения!$C$5 -> 234.60106 | J11: =J10*Допущения!$C$5 -> 308.3911 | ... AL11: =AL10*Допущения!$C$5 -> 4160 | AM11: =SUM(C11:N11) -> 2993.7439 | AN11: =SUM(O11:Z11) -> 17154.892 | AO11: =SUM(AA11:AL11) -> 38522.123 | AP11: =SUM(C11:AL11) -> 58670.759
A12: c_rsya | B12: РСЯ на сайте | C12: =C5/1000*Допущения!$C$8 -> 0 | D12: =D5/1000*Допущения!$C$8 -> 0 | E12: =E5/1000*Допущения!$C$8 -> 12.105782 | F12: =F5/1000*Допущения!$C$8 -> 34.240324 | G12: =G5/1000*Допущения!$C$8 -> 62.903491 | H12: =H5/1000*Допущения!$C$8 -> 96.84626 | I12: =I5/1000*Допущения!$C$8 -> 135.34676 | J12: =J5/1000*Допущения!$C$8 -> 177.91794 | ... AL12: =AL5/1000*Допущения!$C$8 -> 2400 | AM12: =SUM(C12:N12) -> 1727.16 | AN12: =SUM(O12:Z12) -> 9897.0531 | AO12: =SUM(AA12:AL12) -> 22224.302 | AP12: =SUM(C12:AL12) -> 33848.515
A13: c_tg | B13: Реклама в своём Telegram (за вычетом налога) | C13: =IF(C6>=10000,C6*Допущения!$C$11*Допущения!$C$10/1000*Допущения!$C$12*(1-Допущения!$C$14),0) -> 0 | D13: =IF(D6>=10000,D6*Допущения!$C$11*Допущения!$C$10/1000*Допущения!$C$12*(1-Допущения!$C$14),0) -> 0 | E13: =IF(E6>=10000,E6*Допущения!$C$11*Допущения!$C$10/1000*Допущения!$C$12*(1-Допущения!$C$14),0) -> 0 | F13: =IF(F6>=10000,F6*Допущения!$C$11*Допущения!$C$10/1000*Допущения!$C$12*(1-Допущения!$C$14),0) -> 0 | G13: =IF(G6>=10000,G6*Допущения!$C$11*Допущения!$C$10/1000*Допущения!$C$12*(1-Допущения!$C$14),0) -> 0 | H13: =IF(H6>=10000,H6*Допущения!$C$11*Допущения!$C$10/1000*Допущения!$C$12*(1-Допущения!$C$14),0) -> 0 | I13: =IF(I6>=10000,I6*Допущения!$C$11*Допущения!$C$10/1000*Допущения!$C$12*(1-Допущения!$C$14),0) -> 0 | J13: =IF(J6>=10000,J6*Допущения!$C$11*Допущения!$C$10/1000*Допущения!$C$12*(1-Допущения!$C$14),0) -> 0 | ... AL13: =IF(AL6>=10000,AL6*Допущения!$C$11*Допущения!$C$10/1000*Допущения!$C$12*(1-Допущения!$C$14),0) -> 2481.6 | AM13: =SUM(C13:N13) -> 0 | AN13: =SUM(O13:Z13) -> 0 | AO13: =SUM(AA13:AL13) -> 2481.6 | AP13: =SUM(C13:AL13) -> 2481.6
A14: contrib | B14: Маржинальный доход | C14: =C11+C12+C13 -> 0 | D14: =D11+D12+D13 -> 0 | E14: =E11+E12+E13 -> 33.089139 | F14: =F11+F12+F13 -> 93.590218 | G14: =G11+G12+G13 -> 171.93621 | H14: =H11+H12+H13 -> 264.71311 | I14: =I11+I12+I13 -> 369.94782 | J14: =J11+J12+J13 -> 486.30904 | ... AL14: =AL11+AL12+AL13 -> 9041.6 | AM14: =SUM(C14:N14) -> 4720.9039 | AN14: =SUM(O14:Z14) -> 27051.945 | AO14: =SUM(AA14:AL14) -> 63228.025 | AP14: =SUM(C14:AL14) -> 95000.874
A15: acq | B15: Покупка подписчиков Telegram | C15: =MAX(0,C6-0)*(1-Допущения!$C$13)*Допущения!$C$9 -> 0 | D15: =MAX(0,D6-C6)*(1-Допущения!$C$13)*Допущения!$C$9 -> 0 | E15: =MAX(0,E6-D6)*(1-Допущения!$C$13)*Допущения!$C$9 -> 12105.782 | F15: =MAX(0,F6-E6)*(1-Допущения!$C$13)*Допущения!$C$9 -> 22134.541 | G15: =MAX(0,G6-F6)*(1-Допущения!$C$13)*Допущения!$C$9 -> 28663.167 | H15: =MAX(0,H6-G6)*(1-Допущения!$C$13)*Допущения!$C$9 -> 33942.769 | I15: =MAX(0,I6-H6)*(1-Допущения!$C$13)*Допущения!$C$9 -> 38500.503 | J15: =MAX(0,J6-I6)*(1-Допущения!$C$13)*Допущения!$C$9 -> 42571.177 | K15: =MAX(0,K6-J6)*(1-Допущения!$C$13)*Допущения!$C$9 -> 46284.289 | ... AL15: =MAX(0,AL6-AK6)*(1-Допущения!$C$13)*Допущения!$C$9 -> 105099.95 | AM15: =SUM(C15:N15) -> 382818.45 | AN15: =SUM(O15:Z15) -> 866366.91 | AO15: =SUM(AA15:AL15) -> 1150814.6 | AP15: =SUM(C15:AL15) -> 2400000
A16: fixed | B16: Постоянные расходы (команда) | C16: =Допущения!$C$16 -> 480000 | D16: =Допущения!$C$16 -> 480000 | E16: =Допущения!$C$16 -> 480000 | F16: =Допущения!$C$16 -> 480000 | G16: =Допущения!$C$16 -> 480000 | H16: =Допущения!$C$16 -> 480000 | I16: =Допущения!$C$16 -> 480000 | J16: =Допущения!$C$16 -> 480000 | ... AL16: =Допущения!$C$16 -> 480000 | AM16: =SUM(C16:N16) -> 5760000 | AN16: =SUM(O16:Z16) -> 5760000 | AO16: =SUM(AA16:AL16) -> 5760000 | AP16: =SUM(C16:AL16) -> 17280000
A17: op | B17: Операционная прибыль (маржинальный доход − постоянные − привлечение) | C17: =C14-C16-C15 -> -480000 | D17: =D14-D16-D15 -> -480000 | E17: =E14-E16-E15 -> -492072.69 | F17: =F14-F16-F15 -> -502040.95 | G17: =G14-G16-G15 -> -508491.23 | H17: =H14-H16-H15 -> -513678.06 | I17: =I14-I16-I15 -> -518130.56 | J17: =J14-J16-J15 -> -522084.87 | ... AL17: =AL14-AL16-AL15 -> -576058.35 | AM17: =SUM(C17:N17) -> -6138097.6 | AN17: =SUM(O17:Z17) -> -6599315 | AO17: =SUM(AA17:AL17) -> -6847586.6 | AP17: =SUM(C17:AL17) -> -19584999
A18: capex | B18: CAPEX и вложения в оборотку | C18: =IF(C$4=1,Допущения!$C$18,0) -> 600000 | D18: =IF(D$4=1,Допущения!$C$18,0) -> 0 | E18: =IF(E$4=1,Допущения!$C$18,0) -> 0 | F18: =IF(F$4=1,Допущения!$C$18,0) -> 0 | G18: =IF(G$4=1,Допущения!$C$18,0) -> 0 | H18: =IF(H$4=1,Допущения!$C$18,0) -> 0 | I18: =IF(I$4=1,Допущения!$C$18,0) -> 0 | J18: =IF(J$4=1,Допущения!$C$18,0) -> 0 | ... AL18: =IF(AL$4=1,Допущения!$C$18,0) -> 0 | AM18: =SUM(C18:N18) -> 600000 | AN18: =SUM(O18:Z18) -> 0 | AO18: =SUM(AA18:AL18) -> 0 | AP18: =SUM(C18:AL18) -> 600000
A19: cf | B19: Денежный поток | C19: =C17-C18 -> -1080000 | D19: =D17-D18 -> -480000 | E19: =E17-E18 -> -492072.69 | F19: =F17-F18 -> -502040.95 | G19: =G17-G18 -> -508491.23 | H19: =H17-H18 -> -513678.06 | I19: =I17-I18 -> -518130.56 | J19: =J17-J18 -> -522084.87 | ... AL19: =AL17-AL18 -> -576058.35 | AM19: =SUM(C19:N19) -> -6738097.6 | AN19: =SUM(O19:Z19) -> -6599315 | AO19: =SUM(AA19:AL19) -> -6847586.6 | AP19: =SUM(C19:AL19) -> -20184999
A20: cum | B20: Накопленный денежный поток | C20: =0+C19 -> -1080000 | D20: =C20+D19 -> -1560000 | E20: =D20+E19 -> -2052072.7 | F20: =E20+F19 -> -2554113.6 | G20: =F20+G19 -> -3062604.9 | H20: =G20+H19 -> -3576282.9 | I20: =H20+I19 -> -4094413.5 | J20: =I20+J19 -> -4616498.4 | K20: =J20+K19 -> -5142169.8 | ... AL20: =AK20+AL19 -> -20184999 | AM20: =N20 -> -6738097.6 | AN20: =Z20 -> -13337413 | AO20: =AL20 -> -20184999
A21: be_flag | B21: служебно: месяц устойчивой опер. прибыли | C21: =IF(AND(C17>0,COUNTIF(C17:AL17,"<=0")=0),C$4,99) -> 99 | D21: =IF(AND(D17>0,COUNTIF(D17:AL17,"<=0")=0),D$4,99) -> 99 | E21: =IF(AND(E17>0,COUNTIF(E17:AL17,"<=0")=0),E$4,99) -> 99 | F21: =IF(AND(F17>0,COUNTIF(F17:AL17,"<=0")=0),F$4,99) -> 99 | G21: =IF(AND(G17>0,COUNTIF(G17:AL17,"<=0")=0),G$4,99) -> 99 | H21: =IF(AND(H17>0,COUNTIF(H17:AL17,"<=0")=0),H$4,99) -> 99 | I21: =IF(AND(I17>0,COUNTIF(I17:AL17,"<=0")=0),I$4,99) -> 99 | J21: =IF(AND(J17>0,COUNTIF(J17:AL17,"<=0")=0),J$4,99) -> 99 | K21: =IF(AND(K17>0,COUNTIF(K17:AL17,"<=0")=0),K$4,99) -> 99 | L21: =IF(AND(L17>0,COUNTIF(L17:AL17,"<=0")=0),L$4,99) -> 99 | M21: =IF(AND(M17>0,COUNTIF(M17:AL17,"<=0")=0),M$4,99) -> 99 | N21: =IF(AND(N17>0,COUNTIF(N17:AL17,"<=0")=0),N$4,99) -> 99 | O21: =IF(AND(O17>0,COUNTIF(O17:AL17,"<=0")=0),O$4,99) -> 99 | P21: =IF(AND(P17>0,COUNTIF(P17:AL17,"<=0")=0),P$4,99) -> 99 | Q21: =IF(AND(Q17>0,COUNTIF(Q17:AL17,"<=0")=0),Q$4,99) -> 99 | R21: =IF(AND(R17>0,COUNTIF(R17:AL17,"<=0")=0),R$4,99) -> 99 | S21: =IF(AND(S17>0,COUNTIF(S17:AL17,"<=0")=0),S$4,99) -> 99 | T21: =IF(AND(T17>0,COUNTIF(T17:AL17,"<=0")=0),T$4,99) -> 99 | U21: =IF(AND(U17>0,COUNTIF(U17:AL17,"<=0")=0),U$4,99) -> 99 | V21: =IF(AND(V17>0,COUNTIF(V17:AL17,"<=0")=0),V$4,99) -> 99 | W21: =IF(AND(W17>0,COUNTIF(W17:AL17,"<=0")=0),W$4,99) -> 99 | X21: =IF(AND(X17>0,COUNTIF(X17:AL17,"<=0")=0),X$4,99) -> 99 | Y21: =IF(AND(Y17>0,COUNTIF(Y17:AL17,"<=0")=0),Y$4,99) -> 99 | Z21: =IF(AND(Z17>0,COUNTIF(Z17:AL17,"<=0")=0),Z$4,99) -> 99 | AA21: =IF(AND(AA17>0,COUNTIF(AA17:AL17,"<=0")=0),AA$4,99) -> 99 | AB21: =IF(AND(AB17>0,COUNTIF(AB17:AL17,"<=0")=0),AB$4,99) -> 99 | AC21: =IF(AND(AC17>0,COUNTIF(AC17:AL17,"<=0")=0),AC$4,99) -> 99 | AD21: =IF(AND(AD17>0,COUNTIF(AD17:AL17,"<=0")=0),AD$4,99) -> 99 | AE21: =IF(AND(AE17>0,COUNTIF(AE17:AL17,"<=0")=0),AE$4,99) -> 99 | AF21: =IF(AND(AF17>0,COUNTIF(AF17:AL17,"<=0")=0),AF$4,99) -> 99 | AG21: =IF(AND(AG17>0,COUNTIF(AG17:AL17,"<=0")=0),AG$4,99) -> 99 | AH21: =IF(AND(AH17>0,COUNTIF(AH17:AL17,"<=0")=0),AH$4,99) -> 99 | AI21: =IF(AND(AI17>0,COUNTIF(AI17:AL17,"<=0")=0),AI$4,99) -> 99 | AJ21: =IF(AND(AJ17>0,COUNTIF(AJ17:AL17,"<=0")=0),AJ$4,99) -> 99 | AK21: =IF(AND(AK17>0,COUNTIF(AK17:AL17,"<=0")=0),AK$4,99) -> 99 | AL21: =IF(AND(AL17>0,COUNTIF(AL17:AL17,"<=0")=0),AL$4,99) -> 99
A22: pb_flag | B22: служебно: месяц окупаемости | C22: =IF(AND(C20>=0,COUNTIF(C20:AL20,"<0")=0),C$4,99) -> 99 | D22: =IF(AND(D20>=0,COUNTIF(D20:AL20,"<0")=0),D$4,99) -> 99 | E22: =IF(AND(E20>=0,COUNTIF(E20:AL20,"<0")=0),E$4,99) -> 99 | F22: =IF(AND(F20>=0,COUNTIF(F20:AL20,"<0")=0),F$4,99) -> 99 | G22: =IF(AND(G20>=0,COUNTIF(G20:AL20,"<0")=0),G$4,99) -> 99 | H22: =IF(AND(H20>=0,COUNTIF(H20:AL20,"<0")=0),H$4,99) -> 99 | I22: =IF(AND(I20>=0,COUNTIF(I20:AL20,"<0")=0),I$4,99) -> 99 | J22: =IF(AND(J20>=0,COUNTIF(J20:AL20,"<0")=0),J$4,99) -> 99 | K22: =IF(AND(K20>=0,COUNTIF(K20:AL20,"<0")=0),K$4,99) -> 99 | L22: =IF(AND(L20>=0,COUNTIF(L20:AL20,"<0")=0),L$4,99) -> 99 | M22: =IF(AND(M20>=0,COUNTIF(M20:AL20,"<0")=0),M$4,99) -> 99 | N22: =IF(AND(N20>=0,COUNTIF(N20:AL20,"<0")=0),N$4,99) -> 99 | O22: =IF(AND(O20>=0,COUNTIF(O20:AL20,"<0")=0),O$4,99) -> 99 | P22: =IF(AND(P20>=0,COUNTIF(P20:AL20,"<0")=0),P$4,99) -> 99 | Q22: =IF(AND(Q20>=0,COUNTIF(Q20:AL20,"<0")=0),Q$4,99) -> 99 | R22: =IF(AND(R20>=0,COUNTIF(R20:AL20,"<0")=0),R$4,99) -> 99 | S22: =IF(AND(S20>=0,COUNTIF(S20:AL20,"<0")=0),S$4,99) -> 99 | T22: =IF(AND(T20>=0,COUNTIF(T20:AL20,"<0")=0),T$4,99) -> 99 | U22: =IF(AND(U20>=0,COUNTIF(U20:AL20,"<0")=0),U$4,99) -> 99 | V22: =IF(AND(V20>=0,COUNTIF(V20:AL20,"<0")=0),V$4,99) -> 99 | W22: =IF(AND(W20>=0,COUNTIF(W20:AL20,"<0")=0),W$4,99) -> 99 | X22: =IF(AND(X20>=0,COUNTIF(X20:AL20,"<0")=0),X$4,99) -> 99 | Y22: =IF(AND(Y20>=0,COUNTIF(Y20:AL20,"<0")=0),Y$4,99) -> 99 | Z22: =IF(AND(Z20>=0,COUNTIF(Z20:AL20,"<0")=0),Z$4,99) -> 99 | AA22: =IF(AND(AA20>=0,COUNTIF(AA20:AL20,"<0")=0),AA$4,99) -> 99 | AB22: =IF(AND(AB20>=0,COUNTIF(AB20:AL20,"<0")=0),AB$4,99) -> 99 | AC22: =IF(AND(AC20>=0,COUNTIF(AC20:AL20,"<0")=0),AC$4,99) -> 99 | AD22: =IF(AND(AD20>=0,COUNTIF(AD20:AL20,"<0")=0),AD$4,99) -> 99 | AE22: =IF(AND(AE20>=0,COUNTIF(AE20:AL20,"<0")=0),AE$4,99) -> 99 | AF22: =IF(AND(AF20>=0,COUNTIF(AF20:AL20,"<0")=0),AF$4,99) -> 99 | AG22: =IF(AND(AG20>=0,COUNTIF(AG20:AL20,"<0")=0),AG$4,99) -> 99 | AH22: =IF(AND(AH20>=0,COUNTIF(AH20:AL20,"<0")=0),AH$4,99) -> 99 | AI22: =IF(AND(AI20>=0,COUNTIF(AI20:AL20,"<0")=0),AI$4,99) -> 99 | AJ22: =IF(AND(AJ20>=0,COUNTIF(AJ20:AL20,"<0")=0),AJ$4,99) -> 99 | AK22: =IF(AND(AK20>=0,COUNTIF(AK20:AL20,"<0")=0),AK$4,99) -> 99 | AL22: =IF(AND(AL20>=0,COUNTIF(AL20:AL20,"<0")=0),AL$4,99) -> 99
A24: Сценарий: Базовый | B24: Месяц → | C24: 1 | D24: 2 | E24: 3 | F24: 4 | G24: 5 | H24: 6 | I24: 7 | J24: 8 | K24: 9 | L24: 10 | M24: 11 | N24: 12 | O24: 13 | P24: 14 | Q24: 15 | R24: 16 | S24: 17 | T24: 18 | U24: 19 | V24: 20 | W24: 21 | X24: 22 | Y24: 23 | Z24: 24 | AA24: 25 | AB24: 26 | AC24: 27 | AD24: 28 | AE24: 29 | AF24: 30 | AG24: 31 | AH24: 32 | AI24: 33 | AJ24: 34 | AK24: 35 | AL24: 36 | AM24: Год 1 | AN24: Год 2 | AO24: Год 3 | AP24: Итого 36 мес
A25: visits | B25: Визиты сайта | C25: =Допущения!$D$21*IF(C$24<Допущения!$D$27,0,((C$24-Допущения!$D$27+1)/(36-Допущения!$D$27+1))^Допущения!$D$28) -> 0 | D25: =Допущения!$D$21*IF(D$24<Допущения!$D$27,0,((D$24-Допущения!$D$27+1)/(36-Допущения!$D$27+1))^Допущения!$D$28) -> 0 | E25: =Допущения!$D$21*IF(E$24<Допущения!$D$27,0,((E$24-Допущения!$D$27+1)/(36-Допущения!$D$27+1))^Допущения!$D$28) -> 1531.6822 | F25: =Допущения!$D$21*IF(F$24<Допущения!$D$27,0,((F$24-Допущения!$D$27+1)/(36-Допущения!$D$27+1))^Допущения!$D$28) -> 3771.444 | G25: =Допущения!$D$21*IF(G$24<Допущения!$D$27,0,((G$24-Допущения!$D$27+1)/(36-Допущения!$D$27+1))^Допущения!$D$28) -> 6388.9031 | H25: =Допущения!$D$21*IF(H$24<Допущения!$D$27,0,((H$24-Допущения!$D$27+1)/(36-Допущения!$D$27+1))^Допущения!$D$28) -> 9286.3844 | I25: =Допущения!$D$21*IF(I$24<Допущения!$D$27,0,((I$24-Допущения!$D$27+1)/(36-Допущения!$D$27+1))^Допущения!$D$28) -> 12411.654 | J25: =Допущения!$D$21*IF(J$24<Допущения!$D$27,0,((J$24-Допущения!$D$27+1)/(36-Допущения!$D$27+1))^Допущения!$D$28) -> 15731.325 | ... AL25: =Допущения!$D$21*IF(AL$24<Допущения!$D$27,0,((AL$24-Допущения!$D$27+1)/(36-Допущения!$D$27+1))^Допущения!$D$28) -> 150000 | AM25: =SUM(C25:N25) -> 148419.31 | AN25: =SUM(O25:Z25) -> 709250.31 | AO25: =SUM(AA25:AL25) -> 1435133.1 | AP25: =SUM(C25:AL25) -> 2292802.7
A26: subs | B26: Подписчики Telegram (на конец мес.) | C26: =Допущения!$D$22*IF(C$24<Допущения!$D$27,0,((C$24-Допущения!$D$27+1)/(36-Допущения!$D$27+1))^Допущения!$D$28) -> 0 | D26: =Допущения!$D$22*IF(D$24<Допущения!$D$27,0,((D$24-Допущения!$D$27+1)/(36-Допущения!$D$27+1))^Допущения!$D$28) -> 0 | E26: =Допущения!$D$22*IF(E$24<Допущения!$D$27,0,((E$24-Допущения!$D$27+1)/(36-Допущения!$D$27+1))^Допущения!$D$28) -> 255.28037 | F26: =Допущения!$D$22*IF(F$24<Допущения!$D$27,0,((F$24-Допущения!$D$27+1)/(36-Допущения!$D$27+1))^Допущения!$D$28) -> 628.574 | G26: =Допущения!$D$22*IF(G$24<Допущения!$D$27,0,((G$24-Допущения!$D$27+1)/(36-Допущения!$D$27+1))^Допущения!$D$28) -> 1064.8172 | H26: =Допущения!$D$22*IF(H$24<Допущения!$D$27,0,((H$24-Допущения!$D$27+1)/(36-Допущения!$D$27+1))^Допущения!$D$28) -> 1547.7307 | I26: =Допущения!$D$22*IF(I$24<Допущения!$D$27,0,((I$24-Допущения!$D$27+1)/(36-Допущения!$D$27+1))^Допущения!$D$28) -> 2068.6091 | J26: =Допущения!$D$22*IF(J$24<Допущения!$D$27,0,((J$24-Допущения!$D$27+1)/(36-Допущения!$D$27+1))^Допущения!$D$28) -> 2621.8874 | ... AL26: =Допущения!$D$22*IF(AL$24<Допущения!$D$27,0,((AL$24-Допущения!$D$27+1)/(36-Допущения!$D$27+1))^Допущения!$D$28) -> 25000 | AM26: =N26 -> 5093.513 | AN26: =Z26 -> 14196.03 | AO26: =AL26 -> 25000
A27: clips | B27: Просмотры клипов | C27: =Допущения!$D$23*IF(C$24<Допущения!$D$27,0,((C$24-Допущения!$D$27+1)/(36-Допущения!$D$27+1))^Допущения!$D$28) -> 0 | D27: =Допущения!$D$23*IF(D$24<Допущения!$D$27,0,((D$24-Допущения!$D$27+1)/(36-Допущения!$D$27+1))^Допущения!$D$28) -> 0 | E27: =Допущения!$D$23*IF(E$24<Допущения!$D$27,0,((E$24-Допущения!$D$27+1)/(36-Допущения!$D$27+1))^Допущения!$D$28) -> 61267.288 | F27: =Допущения!$D$23*IF(F$24<Допущения!$D$27,0,((F$24-Допущения!$D$27+1)/(36-Допущения!$D$27+1))^Допущения!$D$28) -> 150857.76 | G27: =Допущения!$D$23*IF(G$24<Допущения!$D$27,0,((G$24-Допущения!$D$27+1)/(36-Допущения!$D$27+1))^Допущения!$D$28) -> 255556.12 | H27: =Допущения!$D$23*IF(H$24<Допущения!$D$27,0,((H$24-Допущения!$D$27+1)/(36-Допущения!$D$27+1))^Допущения!$D$28) -> 371455.37 | I27: =Допущения!$D$23*IF(I$24<Допущения!$D$27,0,((I$24-Допущения!$D$27+1)/(36-Допущения!$D$27+1))^Допущения!$D$28) -> 496466.17 | J27: =Допущения!$D$23*IF(J$24<Допущения!$D$27,0,((J$24-Допущения!$D$27+1)/(36-Допущения!$D$27+1))^Допущения!$D$28) -> 629252.98 | ... AL27: =Допущения!$D$23*IF(AL$24<Допущения!$D$27,0,((AL$24-Допущения!$D$27+1)/(36-Допущения!$D$27+1))^Допущения!$D$28) -> 6000000 | AM27: =SUM(C27:N27) -> 5936772.3 | AN27: =SUM(O27:Z27) -> 28370012 | AO27: =SUM(AA27:AL27) -> 57405322 | AP27: =SUM(C27:AL27) -> 91712107
A28: clicks | B28: Клики на Ozon | C28: =C25*Допущения!$D$24+C26*Допущения!$D$25+C27*Допущения!$D$26 -> 0 | D28: =D25*Допущения!$D$24+D26*Допущения!$D$25+D27*Допущения!$D$26 -> 0 | E28: =E25*Допущения!$D$24+E26*Допущения!$D$25+E27*Допущения!$D$26 -> 113.34448 | F28: =F25*Допущения!$D$24+F26*Допущения!$D$25+F27*Допущения!$D$26 -> 279.08685 | G28: =G25*Допущения!$D$24+G26*Допущения!$D$25+G27*Допущения!$D$26 -> 472.77883 | H28: =H25*Допущения!$D$24+H26*Допущения!$D$25+H27*Допущения!$D$26 -> 687.19244 | I28: =I25*Допущения!$D$24+I26*Допущения!$D$25+I27*Допущения!$D$26 -> 918.46242 | J28: =J25*Допущения!$D$24+J26*Допущения!$D$25+J27*Допущения!$D$26 -> 1164.118 | ... AL28: =AL25*Допущения!$D$24+AL26*Допущения!$D$25+AL27*Допущения!$D$26 -> 11100 | AM28: =SUM(C28:N28) -> 10983.029 | AN28: =SUM(O28:Z28) -> 52484.523 | AO28: =SUM(AA28:AL28) -> 106199.85 | AP28: =SUM(C28:AL28) -> 169667.4
A29: orders | B29: Заказы (с «эффектом Ozon») | C29: =C28*Допущения!$D$6*Допущения!$D$7 -> 0 | D29: =D28*Допущения!$D$6*Допущения!$D$7 -> 0 | E29: =E28*Допущения!$D$6*Допущения!$D$7 -> 4.5621154 | F29: =F28*Допущения!$D$6*Допущения!$D$7 -> 11.233246 | G29: =G28*Допущения!$D$6*Допущения!$D$7 -> 19.029348 | H29: =H28*Допущения!$D$6*Допущения!$D$7 -> 27.659496 | I29: =I28*Допущения!$D$6*Допущения!$D$7 -> 36.968112 | J29: =J28*Допущения!$D$6*Допущения!$D$7 -> 46.85575 | ... AL29: =AL28*Допущения!$D$6*Допущения!$D$7 -> 446.775 | AM29: =SUM(C29:N29) -> 442.06691 | AN29: =SUM(O29:Z29) -> 2112.502 | AO29: =SUM(AA29:AL29) -> 4274.5438 | AP29: =SUM(C29:AL29) -> 6829.1128
A30: rev | B30: Оборот на Ozon, ₽ | C30: =C29*Допущения!$D$4 -> 0 | D30: =D29*Допущения!$D$4 -> 0 | E30: =E29*Допущения!$D$4 -> 7299.3847 | F30: =F29*Допущения!$D$4 -> 17973.193 | G30: =G29*Допущения!$D$4 -> 30446.956 | H30: =H29*Допущения!$D$4 -> 44255.193 | I30: =I29*Допущения!$D$4 -> 59148.98 | J30: =J29*Допущения!$D$4 -> 74969.201 | ... AL30: =AL29*Допущения!$D$4 -> 714840 | AM30: =SUM(C30:N30) -> 707307.05 | AN30: =SUM(O30:Z30) -> 3380003.3 | AO30: =SUM(AA30:AL30) -> 6839270.1 | AP30: =SUM(C30:AL30) -> 10926580
A31: c_comm | B31: Маржа дропшиппинга | C31: =C30*Допущения!$D$5 -> 0 | D31: =D30*Допущения!$D$5 -> 0 | E31: =E30*Допущения!$D$5 -> 875.92617 | F31: =F30*Допущения!$D$5 -> 2156.7832 | G31: =G30*Допущения!$D$5 -> 3653.6348 | H31: =H30*Допущения!$D$5 -> 5310.6232 | I31: =I30*Допущения!$D$5 -> 7097.8776 | J31: =J30*Допущения!$D$5 -> 8996.3041 | ... AL31: =AL30*Допущения!$D$5 -> 85780.8 | AM31: =SUM(C31:N31) -> 84876.846 | AN31: =SUM(O31:Z31) -> 405600.39 | AO31: =SUM(AA31:AL31) -> 820712.41 | AP31: =SUM(C31:AL31) -> 1311189.7
A32: c_rsya | B32: РСЯ на сайте | C32: =C25/1000*Допущения!$D$8 -> 0 | D32: =D25/1000*Допущения!$D$8 -> 0 | E32: =E25/1000*Допущения!$D$8 -> 122.53458 | F32: =F25/1000*Допущения!$D$8 -> 301.71552 | G32: =G25/1000*Допущения!$D$8 -> 511.11224 | H32: =H25/1000*Допущения!$D$8 -> 742.91075 | I32: =I25/1000*Допущения!$D$8 -> 992.93235 | J32: =J25/1000*Допущения!$D$8 -> 1258.506 | ... AL32: =AL25/1000*Допущения!$D$8 -> 12000 | AM32: =SUM(C32:N32) -> 11873.545 | AN32: =SUM(O32:Z32) -> 56740.024 | AO32: =SUM(AA32:AL32) -> 114810.64 | AP32: =SUM(C32:AL32) -> 183424.21
A33: c_tg | B33: Реклама в своём Telegram (за вычетом налога) | C33: =IF(C26>=10000,C26*Допущения!$D$11*Допущения!$D$10/1000*Допущения!$D$12*(1-Допущения!$D$14),0) -> 0 | D33: =IF(D26>=10000,D26*Допущения!$D$11*Допущения!$D$10/1000*Допущения!$D$12*(1-Допущения!$D$14),0) -> 0 | E33: =IF(E26>=10000,E26*Допущения!$D$11*Допущения!$D$10/1000*Допущения!$D$12*(1-Допущения!$D$14),0) -> 0 | F33: =IF(F26>=10000,F26*Допущения!$D$11*Допущения!$D$10/1000*Допущения!$D$12*(1-Допущения!$D$14),0) -> 0 | G33: =IF(G26>=10000,G26*Допущения!$D$11*Допущения!$D$10/1000*Допущения!$D$12*(1-Допущения!$D$14),0) -> 0 | H33: =IF(H26>=10000,H26*Допущения!$D$11*Допущения!$D$10/1000*Допущения!$D$12*(1-Допущения!$D$14),0) -> 0 | I33: =IF(I26>=10000,I26*Допущения!$D$11*Допущения!$D$10/1000*Допущения!$D$12*(1-Допущения!$D$14),0) -> 0 | J33: =IF(J26>=10000,J26*Допущения!$D$11*Допущения!$D$10/1000*Допущения!$D$12*(1-Допущения!$D$14),0) -> 0 | ... AL33: =IF(AL26>=10000,AL26*Допущения!$D$11*Допущения!$D$10/1000*Допущения!$D$12*(1-Допущения!$D$14),0) -> 26320 | AM33: =SUM(C33:N33) -> 0 | AN33: =SUM(O33:Z33) -> 76773.174 | AO33: =SUM(AA33:AL33) -> 251818.01 | AP33: =SUM(C33:AL33) -> 328591.19
A34: contrib | B34: Маржинальный доход | C34: =C31+C32+C33 -> 0 | D34: =D31+D32+D33 -> 0 | E34: =E31+E32+E33 -> 998.46074 | F34: =F31+F32+F33 -> 2458.4987 | G34: =G31+G32+G33 -> 4164.747 | H34: =H31+H32+H33 -> 6053.534 | I34: =I31+I32+I33 -> 8090.8099 | J34: =J31+J32+J33 -> 10254.81 | ... AL34: =AL31+AL32+AL33 -> 124100.8 | AM34: =SUM(C34:N34) -> 96750.391 | AN34: =SUM(O34:Z34) -> 539113.59 | AO34: =SUM(AA34:AL34) -> 1187341.1 | AP34: =SUM(C34:AL34) -> 1823205.1
A35: acq | B35: Покупка подписчиков Telegram | C35: =MAX(0,C26-0)*(1-Допущения!$D$13)*Допущения!$D$9 -> 0 | D35: =MAX(0,D26-C26)*(1-Допущения!$D$13)*Допущения!$D$9 -> 0 | E35: =MAX(0,E26-D26)*(1-Допущения!$D$13)*Допущения!$D$9 -> 27570.28 | F35: =MAX(0,F26-E26)*(1-Допущения!$D$13)*Допущения!$D$9 -> 40315.712 | G35: =MAX(0,G26-F26)*(1-Допущения!$D$13)*Допущения!$D$9 -> 47114.263 | H35: =MAX(0,H26-G26)*(1-Допущения!$D$13)*Допущения!$D$9 -> 52154.664 | I35: =MAX(0,I26-H26)*(1-Допущения!$D$13)*Допущения!$D$9 -> 56254.86 | J35: =MAX(0,J26-I26)*(1-Допущения!$D$13)*Допущения!$D$9 -> 59754.064 | K35: =MAX(0,K26-J26)*(1-Допущения!$D$13)*Допущения!$D$9 -> 62830.202 | ... AL35: =MAX(0,AL26-AK26)*(1-Допущения!$D$13)*Допущения!$D$9 -> 102776.68 | AM35: =SUM(C35:N35) -> 550099.4 | AN35: =SUM(O35:Z35) -> 983071.81 | AO35: =SUM(AA35:AL35) -> 1166828.8 | AP35: =SUM(C35:AL35) -> 2700000
A36: fixed | B36: Постоянные расходы (команда) | C36: =Допущения!$D$16 -> 420000 | D36: =Допущения!$D$16 -> 420000 | E36: =Допущения!$D$16 -> 420000 | F36: =Допущения!$D$16 -> 420000 | G36: =Допущения!$D$16 -> 420000 | H36: =Допущения!$D$16 -> 420000 | I36: =Допущения!$D$16 -> 420000 | J36: =Допущения!$D$16 -> 420000 | ... AL36: =Допущения!$D$16 -> 420000 | AM36: =SUM(C36:N36) -> 5040000 | AN36: =SUM(O36:Z36) -> 5040000 | AO36: =SUM(AA36:AL36) -> 5040000 | AP36: =SUM(C36:AL36) -> 15120000
A37: op | B37: Операционная прибыль (маржинальный доход − постоянные − привлечение) | C37: =C34-C36-C35 -> -420000 | D37: =D34-D36-D35 -> -420000 | E37: =E34-E36-E35 -> -446571.82 | F37: =F34-F36-F35 -> -457857.21 | G37: =G34-G36-G35 -> -462949.52 | H37: =H34-H36-H35 -> -466101.13 | I37: =I34-I36-I35 -> -468164.05 | J37: =J34-J36-J35 -> -469499.25 | ... AL37: =AL34-AL36-AL35 -> -398675.88 | AM37: =SUM(C37:N37) -> -5493349 | AN37: =SUM(O37:Z37) -> -5483958.2 | AO37: =SUM(AA37:AL37) -> -5019487.7 | AP37: =SUM(C37:AL37) -> -15996795
A38: capex | B38: CAPEX и вложения в оборотку | C38: =IF(C$24=1,Допущения!$D$18,0) -> 400000 | D38: =IF(D$24=1,Допущения!$D$18,0) -> 0 | E38: =IF(E$24=1,Допущения!$D$18,0) -> 0 | F38: =IF(F$24=1,Допущения!$D$18,0) -> 0 | G38: =IF(G$24=1,Допущения!$D$18,0) -> 0 | H38: =IF(H$24=1,Допущения!$D$18,0) -> 0 | I38: =IF(I$24=1,Допущения!$D$18,0) -> 0 | J38: =IF(J$24=1,Допущения!$D$18,0) -> 0 | ... AL38: =IF(AL$24=1,Допущения!$D$18,0) -> 0 | AM38: =SUM(C38:N38) -> 400000 | AN38: =SUM(O38:Z38) -> 0 | AO38: =SUM(AA38:AL38) -> 0 | AP38: =SUM(C38:AL38) -> 400000
A39: cf | B39: Денежный поток | C39: =C37-C38 -> -820000 | D39: =D37-D38 -> -420000 | E39: =E37-E38 -> -446571.82 | F39: =F37-F38 -> -457857.21 | G39: =G37-G38 -> -462949.52 | H39: =H37-H38 -> -466101.13 | I39: =I37-I38 -> -468164.05 | J39: =J37-J38 -> -469499.25 | ... AL39: =AL37-AL38 -> -398675.88 | AM39: =SUM(C39:N39) -> -5893349 | AN39: =SUM(O39:Z39) -> -5483958.2 | AO39: =SUM(AA39:AL39) -> -5019487.7 | AP39: =SUM(C39:AL39) -> -16396795
A40: cum | B40: Накопленный денежный поток | C40: =0+C39 -> -820000 | D40: =C40+D39 -> -1240000 | E40: =D40+E39 -> -1686571.8 | F40: =E40+F39 -> -2144429 | G40: =F40+G39 -> -2607378.5 | H40: =G40+H39 -> -3073479.7 | I40: =H40+I39 -> -3541643.7 | J40: =I40+J39 -> -4011143 | K40: =J40+K39 -> -4481443 | ... AL40: =AK40+AL39 -> -16396795 | AM40: =N40 -> -5893349 | AN40: =Z40 -> -11377307 | AO40: =AL40 -> -16396795
A41: be_flag | B41: служебно: месяц устойчивой опер. прибыли | C41: =IF(AND(C37>0,COUNTIF(C37:AL37,"<=0")=0),C$24,99) -> 99 | D41: =IF(AND(D37>0,COUNTIF(D37:AL37,"<=0")=0),D$24,99) -> 99 | E41: =IF(AND(E37>0,COUNTIF(E37:AL37,"<=0")=0),E$24,99) -> 99 | F41: =IF(AND(F37>0,COUNTIF(F37:AL37,"<=0")=0),F$24,99) -> 99 | G41: =IF(AND(G37>0,COUNTIF(G37:AL37,"<=0")=0),G$24,99) -> 99 | H41: =IF(AND(H37>0,COUNTIF(H37:AL37,"<=0")=0),H$24,99) -> 99 | I41: =IF(AND(I37>0,COUNTIF(I37:AL37,"<=0")=0),I$24,99) -> 99 | J41: =IF(AND(J37>0,COUNTIF(J37:AL37,"<=0")=0),J$24,99) -> 99 | K41: =IF(AND(K37>0,COUNTIF(K37:AL37,"<=0")=0),K$24,99) -> 99 | L41: =IF(AND(L37>0,COUNTIF(L37:AL37,"<=0")=0),L$24,99) -> 99 | M41: =IF(AND(M37>0,COUNTIF(M37:AL37,"<=0")=0),M$24,99) -> 99 | N41: =IF(AND(N37>0,COUNTIF(N37:AL37,"<=0")=0),N$24,99) -> 99 | O41: =IF(AND(O37>0,COUNTIF(O37:AL37,"<=0")=0),O$24,99) -> 99 | P41: =IF(AND(P37>0,COUNTIF(P37:AL37,"<=0")=0),P$24,99) -> 99 | Q41: =IF(AND(Q37>0,COUNTIF(Q37:AL37,"<=0")=0),Q$24,99) -> 99 | R41: =IF(AND(R37>0,COUNTIF(R37:AL37,"<=0")=0),R$24,99) -> 99 | S41: =IF(AND(S37>0,COUNTIF(S37:AL37,"<=0")=0),S$24,99) -> 99 | T41: =IF(AND(T37>0,COUNTIF(T37:AL37,"<=0")=0),T$24,99) -> 99 | U41: =IF(AND(U37>0,COUNTIF(U37:AL37,"<=0")=0),U$24,99) -> 99 | V41: =IF(AND(V37>0,COUNTIF(V37:AL37,"<=0")=0),V$24,99) -> 99 | W41: =IF(AND(W37>0,COUNTIF(W37:AL37,"<=0")=0),W$24,99) -> 99 | X41: =IF(AND(X37>0,COUNTIF(X37:AL37,"<=0")=0),X$24,99) -> 99 | Y41: =IF(AND(Y37>0,COUNTIF(Y37:AL37,"<=0")=0),Y$24,99) -> 99 | Z41: =IF(AND(Z37>0,COUNTIF(Z37:AL37,"<=0")=0),Z$24,99) -> 99 | AA41: =IF(AND(AA37>0,COUNTIF(AA37:AL37,"<=0")=0),AA$24,99) -> 99 | AB41: =IF(AND(AB37>0,COUNTIF(AB37:AL37,"<=0")=0),AB$24,99) -> 99 | AC41: =IF(AND(AC37>0,COUNTIF(AC37:AL37,"<=0")=0),AC$24,99) -> 99 | AD41: =IF(AND(AD37>0,COUNTIF(AD37:AL37,"<=0")=0),AD$24,99) -> 99 | AE41: =IF(AND(AE37>0,COUNTIF(AE37:AL37,"<=0")=0),AE$24,99) -> 99 | AF41: =IF(AND(AF37>0,COUNTIF(AF37:AL37,"<=0")=0),AF$24,99) -> 99 | AG41: =IF(AND(AG37>0,COUNTIF(AG37:AL37,"<=0")=0),AG$24,99) -> 99 | AH41: =IF(AND(AH37>0,COUNTIF(AH37:AL37,"<=0")=0),AH$24,99) -> 99 | AI41: =IF(AND(AI37>0,COUNTIF(AI37:AL37,"<=0")=0),AI$24,99) -> 99 | AJ41: =IF(AND(AJ37>0,COUNTIF(AJ37:AL37,"<=0")=0),AJ$24,99) -> 99 | AK41: =IF(AND(AK37>0,COUNTIF(AK37:AL37,"<=0")=0),AK$24,99) -> 99 | AL41: =IF(AND(AL37>0,COUNTIF(AL37:AL37,"<=0")=0),AL$24,99) -> 99
A42: pb_flag | B42: служебно: месяц окупаемости | C42: =IF(AND(C40>=0,COUNTIF(C40:AL40,"<0")=0),C$24,99) -> 99 | D42: =IF(AND(D40>=0,COUNTIF(D40:AL40,"<0")=0),D$24,99) -> 99 | E42: =IF(AND(E40>=0,COUNTIF(E40:AL40,"<0")=0),E$24,99) -> 99 | F42: =IF(AND(F40>=0,COUNTIF(F40:AL40,"<0")=0),F$24,99) -> 99 | G42: =IF(AND(G40>=0,COUNTIF(G40:AL40,"<0")=0),G$24,99) -> 99 | H42: =IF(AND(H40>=0,COUNTIF(H40:AL40,"<0")=0),H$24,99) -> 99 | I42: =IF(AND(I40>=0,COUNTIF(I40:AL40,"<0")=0),I$24,99) -> 99 | J42: =IF(AND(J40>=0,COUNTIF(J40:AL40,"<0")=0),J$24,99) -> 99 | K42: =IF(AND(K40>=0,COUNTIF(K40:AL40,"<0")=0),K$24,99) -> 99 | L42: =IF(AND(L40>=0,COUNTIF(L40:AL40,"<0")=0),L$24,99) -> 99 | M42: =IF(AND(M40>=0,COUNTIF(M40:AL40,"<0")=0),M$24,99) -> 99 | N42: =IF(AND(N40>=0,COUNTIF(N40:AL40,"<0")=0),N$24,99) -> 99 | O42: =IF(AND(O40>=0,COUNTIF(O40:AL40,"<0")=0),O$24,99) -> 99 | P42: =IF(AND(P40>=0,COUNTIF(P40:AL40,"<0")=0),P$24,99) -> 99 | Q42: =IF(AND(Q40>=0,COUNTIF(Q40:AL40,"<0")=0),Q$24,99) -> 99 | R42: =IF(AND(R40>=0,COUNTIF(R40:AL40,"<0")=0),R$24,99) -> 99 | S42: =IF(AND(S40>=0,COUNTIF(S40:AL40,"<0")=0),S$24,99) -> 99 | T42: =IF(AND(T40>=0,COUNTIF(T40:AL40,"<0")=0),T$24,99) -> 99 | U42: =IF(AND(U40>=0,COUNTIF(U40:AL40,"<0")=0),U$24,99) -> 99 | V42: =IF(AND(V40>=0,COUNTIF(V40:AL40,"<0")=0),V$24,99) -> 99 | W42: =IF(AND(W40>=0,COUNTIF(W40:AL40,"<0")=0),W$24,99) -> 99 | X42: =IF(AND(X40>=0,COUNTIF(X40:AL40,"<0")=0),X$24,99) -> 99 | Y42: =IF(AND(Y40>=0,COUNTIF(Y40:AL40,"<0")=0),Y$24,99) -> 99 | Z42: =IF(AND(Z40>=0,COUNTIF(Z40:AL40,"<0")=0),Z$24,99) -> 99 | AA42: =IF(AND(AA40>=0,COUNTIF(AA40:AL40,"<0")=0),AA$24,99) -> 99 | AB42: =IF(AND(AB40>=0,COUNTIF(AB40:AL40,"<0")=0),AB$24,99) -> 99 | AC42: =IF(AND(AC40>=0,COUNTIF(AC40:AL40,"<0")=0),AC$24,99) -> 99 | AD42: =IF(AND(AD40>=0,COUNTIF(AD40:AL40,"<0")=0),AD$24,99) -> 99 | AE42: =IF(AND(AE40>=0,COUNTIF(AE40:AL40,"<0")=0),AE$24,99) -> 99 | AF42: =IF(AND(AF40>=0,COUNTIF(AF40:AL40,"<0")=0),AF$24,99) -> 99 | AG42: =IF(AND(AG40>=0,COUNTIF(AG40:AL40,"<0")=0),AG$24,99) -> 99 | AH42: =IF(AND(AH40>=0,COUNTIF(AH40:AL40,"<0")=0),AH$24,99) -> 99 | AI42: =IF(AND(AI40>=0,COUNTIF(AI40:AL40,"<0")=0),AI$24,99) -> 99 | AJ42: =IF(AND(AJ40>=0,COUNTIF(AJ40:AL40,"<0")=0),AJ$24,99) -> 99 | AK42: =IF(AND(AK40>=0,COUNTIF(AK40:AL40,"<0")=0),AK$24,99) -> 99 | AL42: =IF(AND(AL40>=0,COUNTIF(AL40:AL40,"<0")=0),AL$24,99) -> 99
A44: Сценарий: Оптимистичный | B44: Месяц → | C44: 1 | D44: 2 | E44: 3 | F44: 4 | G44: 5 | H44: 6 | I44: 7 | J44: 8 | K44: 9 | L44: 10 | M44: 11 | N44: 12 | O44: 13 | P44: 14 | Q44: 15 | R44: 16 | S44: 17 | T44: 18 | U44: 19 | V44: 20 | W44: 21 | X44: 22 | Y44: 23 | Z44: 24 | AA44: 25 | AB44: 26 | AC44: 27 | AD44: 28 | AE44: 29 | AF44: 30 | AG44: 31 | AH44: 32 | AI44: 33 | AJ44: 34 | AK44: 35 | AL44: 36 | AM44: Год 1 | AN44: Год 2 | AO44: Год 3 | AP44: Итого 36 мес
A45: visits | B45: Визиты сайта | C45: =Допущения!$E$21*IF(C$44<Допущения!$E$27,0,((C$44-Допущения!$E$27+1)/(36-Допущения!$E$27+1))^Допущения!$E$28) -> 0 | D45: =Допущения!$E$21*IF(D$44<Допущения!$E$27,0,((D$44-Допущения!$E$27+1)/(36-Допущения!$E$27+1))^Допущения!$E$28) -> 8009.1263 | E45: =Допущения!$E$21*IF(E$44<Допущения!$E$27,0,((E$44-Допущения!$E$27+1)/(36-Допущения!$E$27+1))^Допущения!$E$28) -> 17167.938 | F45: =Допущения!$E$21*IF(F$44<Допущения!$E$27,0,((F$44-Допущения!$E$27+1)/(36-Допущения!$E$27+1))^Допущения!$E$28) -> 26817.514 | G45: =Допущения!$E$21*IF(G$44<Допущения!$E$27,0,((G$44-Допущения!$E$27+1)/(36-Допущения!$E$27+1))^Допущения!$E$28) -> 36800.281 | H45: =Допущения!$E$21*IF(H$44<Допущения!$E$27,0,((H$44-Допущения!$E$27+1)/(36-Допущения!$E$27+1))^Допущения!$E$28) -> 47038.357 | I45: =Допущения!$E$21*IF(I$44<Допущения!$E$27,0,((I$44-Допущения!$E$27+1)/(36-Допущения!$E$27+1))^Допущения!$E$28) -> 57484.601 | J45: =Допущения!$E$21*IF(J$44<Допущения!$E$27,0,((J$44-Допущения!$E$27+1)/(36-Допущения!$E$27+1))^Допущения!$E$28) -> 68107.194 | ... AL45: =Допущения!$E$21*IF(AL$44<Допущения!$E$27,0,((AL$44-Допущения!$E$27+1)/(36-Допущения!$E$27+1))^Допущения!$E$28) -> 400000 | AM45: =SUM(C45:N45) -> 642905.99 | AN45: =SUM(O45:Z45) -> 2244120.5 | AO45: =SUM(AA45:AL45) -> 3980143.4 | AP45: =SUM(C45:AL45) -> 6867169.8
A46: subs | B46: Подписчики Telegram (на конец мес.) | C46: =Допущения!$E$22*IF(C$44<Допущения!$E$27,0,((C$44-Допущения!$E$27+1)/(36-Допущения!$E$27+1))^Допущения!$E$28) -> 0 | D46: =Допущения!$E$22*IF(D$44<Допущения!$E$27,0,((D$44-Допущения!$E$27+1)/(36-Допущения!$E$27+1))^Допущения!$E$28) -> 1201.3689 | E46: =Допущения!$E$22*IF(E$44<Допущения!$E$27,0,((E$44-Допущения!$E$27+1)/(36-Допущения!$E$27+1))^Допущения!$E$28) -> 2575.1907 | F46: =Допущения!$E$22*IF(F$44<Допущения!$E$27,0,((F$44-Допущения!$E$27+1)/(36-Допущения!$E$27+1))^Допущения!$E$28) -> 4022.6272 | G46: =Допущения!$E$22*IF(G$44<Допущения!$E$27,0,((G$44-Допущения!$E$27+1)/(36-Допущения!$E$27+1))^Допущения!$E$28) -> 5520.0421 | H46: =Допущения!$E$22*IF(H$44<Допущения!$E$27,0,((H$44-Допущения!$E$27+1)/(36-Допущения!$E$27+1))^Допущения!$E$28) -> 7055.7536 | I46: =Допущения!$E$22*IF(I$44<Допущения!$E$27,0,((I$44-Допущения!$E$27+1)/(36-Допущения!$E$27+1))^Допущения!$E$28) -> 8622.6901 | J46: =Допущения!$E$22*IF(J$44<Допущения!$E$27,0,((J$44-Допущения!$E$27+1)/(36-Допущения!$E$27+1))^Допущения!$E$28) -> 10216.079 | ... AL46: =Допущения!$E$22*IF(AL$44<Допущения!$E$27,0,((AL$44-Допущения!$E$27+1)/(36-Допущения!$E$27+1))^Допущения!$E$28) -> 60000 | AM46: =N46 -> 16796.096 | AN46: =Z46 -> 37807.418 | AO46: =AL46 -> 60000
A47: clips | B47: Просмотры клипов | C47: =Допущения!$E$23*IF(C$44<Допущения!$E$27,0,((C$44-Допущения!$E$27+1)/(36-Допущения!$E$27+1))^Допущения!$E$28) -> 0 | D47: =Допущения!$E$23*IF(D$44<Допущения!$E$27,0,((D$44-Допущения!$E$27+1)/(36-Допущения!$E$27+1))^Допущения!$E$28) -> 300342.24 | E47: =Допущения!$E$23*IF(E$44<Допущения!$E$27,0,((E$44-Допущения!$E$27+1)/(36-Допущения!$E$27+1))^Допущения!$E$28) -> 643797.68 | F47: =Допущения!$E$23*IF(F$44<Допущения!$E$27,0,((F$44-Допущения!$E$27+1)/(36-Допущения!$E$27+1))^Допущения!$E$28) -> 1005656.8 | G47: =Допущения!$E$23*IF(G$44<Допущения!$E$27,0,((G$44-Допущения!$E$27+1)/(36-Допущения!$E$27+1))^Допущения!$E$28) -> 1380010.5 | H47: =Допущения!$E$23*IF(H$44<Допущения!$E$27,0,((H$44-Допущения!$E$27+1)/(36-Допущения!$E$27+1))^Допущения!$E$28) -> 1763938.4 | I47: =Допущения!$E$23*IF(I$44<Допущения!$E$27,0,((I$44-Допущения!$E$27+1)/(36-Допущения!$E$27+1))^Допущения!$E$28) -> 2155672.5 | J47: =Допущения!$E$23*IF(J$44<Допущения!$E$27,0,((J$44-Допущения!$E$27+1)/(36-Допущения!$E$27+1))^Допущения!$E$28) -> 2554019.8 | ... AL47: =Допущения!$E$23*IF(AL$44<Допущения!$E$27,0,((AL$44-Допущения!$E$27+1)/(36-Допущения!$E$27+1))^Допущения!$E$28) -> 15000000 | AM47: =SUM(C47:N47) -> 24108975 | AN47: =SUM(O47:Z47) -> 84154517 | AO47: =SUM(AA47:AL47) -> 1.4925538e+08 | AP47: =SUM(C47:AL47) -> 2.5751887e+08
A48: clicks | B48: Клики на Ozon | C48: =C45*Допущения!$E$24+C46*Допущения!$E$25+C47*Допущения!$E$26 -> 0 | D48: =D45*Допущения!$E$24+D46*Допущения!$E$25+D47*Допущения!$E$26 -> 1071.2206 | E48: =E45*Допущения!$E$24+E46*Допущения!$E$25+E47*Допущения!$E$26 -> 2296.2117 | F48: =F45*Допущения!$E$24+F46*Допущения!$E$25+F47*Допущения!$E$26 -> 3586.8426 | G48: =G45*Допущения!$E$24+G46*Допущения!$E$25+G47*Допущения!$E$26 -> 4922.0376 | H48: =H45*Допущения!$E$24+H46*Допущения!$E$25+H47*Допущения!$E$26 -> 6291.3803 | I48: =I45*Допущения!$E$24+I46*Допущения!$E$25+I47*Допущения!$E$26 -> 7688.5653 | J48: =J45*Допущения!$E$24+J46*Допущения!$E$25+J47*Допущения!$E$26 -> 9109.3372 | ... AL48: =AL45*Допущения!$E$24+AL46*Допущения!$E$25+AL47*Допущения!$E$26 -> 53500 | AM48: =SUM(C48:N48) -> 85988.676 | AN48: =SUM(O48:Z48) -> 300151.11 | AO48: =SUM(AA48:AL48) -> 532344.18 | AP48: =SUM(C48:AL48) -> 918483.96
A49: orders | B49: Заказы (с «эффектом Ozon») | C49: =C48*Допущения!$E$6*Допущения!$E$7 -> 0 | D49: =D48*Допущения!$E$6*Допущения!$E$7 -> 80.341548 | E49: =E48*Допущения!$E$6*Допущения!$E$7 -> 172.21588 | F49: =F48*Допущения!$E$6*Допущения!$E$7 -> 269.01319 | G49: =G48*Допущения!$E$6*Допущения!$E$7 -> 369.15282 | H49: =H48*Допущения!$E$6*Допущения!$E$7 -> 471.85352 | I49: =I48*Допущения!$E$6*Допущения!$E$7 -> 576.6424 | J49: =J48*Допущения!$E$6*Допущения!$E$7 -> 683.20029 | ... AL49: =AL48*Допущения!$E$6*Допущения!$E$7 -> 4012.5 | AM49: =SUM(C49:N49) -> 6449.1507 | AN49: =SUM(O49:Z49) -> 22511.333 | AO49: =SUM(AA49:AL49) -> 39925.813 | AP49: =SUM(C49:AL49) -> 68886.297
A50: rev | B50: Оборот на Ozon, ₽ | C50: =C49*Допущения!$E$4 -> 0 | D50: =D49*Допущения!$E$4 -> 160683.1 | E50: =E49*Допущения!$E$4 -> 344431.76 | F50: =F49*Допущения!$E$4 -> 538026.38 | G50: =G49*Допущения!$E$4 -> 738305.63 | H50: =H49*Допущения!$E$4 -> 943707.04 | I50: =I49*Допущения!$E$4 -> 1153284.8 | J50: =J49*Допущения!$E$4 -> 1366400.6 | ... AL50: =AL49*Допущения!$E$4 -> 8025000 | AM50: =SUM(C50:N50) -> 12898301 | AN50: =SUM(O50:Z50) -> 45022667 | AO50: =SUM(AA50:AL50) -> 79851626 | AP50: =SUM(C50:AL50) -> 1.3777259e+08
A51: c_comm | B51: Маржа дропшиппинга | C51: =C50*Допущения!$E$5 -> 0 | D51: =D50*Допущения!$E$5 -> 28922.957 | E51: =E50*Допущения!$E$5 -> 61997.716 | F51: =F50*Допущения!$E$5 -> 96844.749 | G51: =G50*Допущения!$E$5 -> 132895.01 | H51: =H50*Допущения!$E$5 -> 169867.27 | I51: =I50*Допущения!$E$5 -> 207591.26 | J51: =J50*Допущения!$E$5 -> 245952.1 | ... AL51: =AL50*Допущения!$E$5 -> 1444500 | AM51: =SUM(C51:N51) -> 2321694.3 | AN51: =SUM(O51:Z51) -> 8104080 | AO51: =SUM(AA51:AL51) -> 14373293 | AP51: =SUM(C51:AL51) -> 24799067
A52: c_rsya | B52: РСЯ на сайте | C52: =C45/1000*Допущения!$E$8 -> 0 | D52: =D45/1000*Допущения!$E$8 -> 1201.3689 | E52: =E45/1000*Допущения!$E$8 -> 2575.1907 | F52: =F45/1000*Допущения!$E$8 -> 4022.6272 | G52: =G45/1000*Допущения!$E$8 -> 5520.0421 | H52: =H45/1000*Допущения!$E$8 -> 7055.7536 | I52: =I45/1000*Допущения!$E$8 -> 8622.6901 | J52: =J45/1000*Допущения!$E$8 -> 10216.079 | ... AL52: =AL45/1000*Допущения!$E$8 -> 60000 | AM52: =SUM(C52:N52) -> 96435.898 | AN52: =SUM(O52:Z52) -> 336618.07 | AO52: =SUM(AA52:AL52) -> 597021.5 | AP52: =SUM(C52:AL52) -> 1030075.5
A53: c_tg | B53: Реклама в своём Telegram (за вычетом налога) | C53: =IF(C46>=10000,C46*Допущения!$E$11*Допущения!$E$10/1000*Допущения!$E$12*(1-Допущения!$E$14),0) -> 0 | D53: =IF(D46>=10000,D46*Допущения!$E$11*Допущения!$E$10/1000*Допущения!$E$12*(1-Допущения!$E$14),0) -> 0 | E53: =IF(E46>=10000,E46*Допущения!$E$11*Допущения!$E$10/1000*Допущения!$E$12*(1-Допущения!$E$14),0) -> 0 | F53: =IF(F46>=10000,F46*Допущения!$E$11*Допущения!$E$10/1000*Допущения!$E$12*(1-Допущения!$E$14),0) -> 0 | G53: =IF(G46>=10000,G46*Допущения!$E$11*Допущения!$E$10/1000*Допущения!$E$12*(1-Допущения!$E$14),0) -> 0 | H53: =IF(H46>=10000,H46*Допущения!$E$11*Допущения!$E$10/1000*Допущения!$E$12*(1-Допущения!$E$14),0) -> 0 | I53: =IF(I46>=10000,I46*Допущения!$E$11*Допущения!$E$10/1000*Допущения!$E$12*(1-Допущения!$E$14),0) -> 0 | J53: =IF(J46>=10000,J46*Допущения!$E$11*Допущения!$E$10/1000*Допущения!$E$12*(1-Допущения!$E$14),0) -> 28233.156 | ... AL53: =IF(AL46>=10000,AL46*Допущения!$E$11*Допущения!$E$10/1000*Допущения!$E$12*(1-Допущения!$E$14),0) -> 165816 | AM53: =SUM(C53:N53) -> 186372.28 | AN53: =SUM(O53:Z53) -> 930277.7 | AO53: =SUM(AA53:AL53) -> 1649928.6 | AP53: =SUM(C53:AL53) -> 2766578.6
A54: contrib | B54: Маржинальный доход | C54: =C51+C52+C53 -> 0 | D54: =D51+D52+D53 -> 30124.326 | E54: =E51+E52+E53 -> 64572.907 | F54: =F51+F52+F53 -> 100867.38 | G54: =G51+G52+G53 -> 138415.06 | H54: =H51+H52+H53 -> 176923.02 | I54: =I51+I52+I53 -> 216213.95 | J54: =J51+J52+J53 -> 284401.34 | ... AL54: =AL51+AL52+AL53 -> 1670316 | AM54: =SUM(C54:N54) -> 2604502.4 | AN54: =SUM(O54:Z54) -> 9370975.8 | AO54: =SUM(AA54:AL54) -> 16620243 | AP54: =SUM(C54:AL54) -> 28595721
A55: acq | B55: Покупка подписчиков Telegram | C55: =MAX(0,C46-0)*(1-Допущения!$E$13)*Допущения!$E$9 -> 0 | D55: =MAX(0,D46-C46)*(1-Допущения!$E$13)*Допущения!$E$9 -> 48054.758 | E55: =MAX(0,E46-D46)*(1-Допущения!$E$13)*Допущения!$E$9 -> 54952.871 | F55: =MAX(0,F46-E46)*(1-Допущения!$E$13)*Допущения!$E$9 -> 57897.458 | G55: =MAX(0,G46-F46)*(1-Допущения!$E$13)*Допущения!$E$9 -> 59896.599 | H55: =MAX(0,H46-G46)*(1-Допущения!$E$13)*Допущения!$E$9 -> 61428.459 | I55: =MAX(0,I46-H46)*(1-Допущения!$E$13)*Допущения!$E$9 -> 62677.459 | J55: =MAX(0,J46-I46)*(1-Допущения!$E$13)*Допущения!$E$9 -> 63735.559 | K55: =MAX(0,K46-J46)*(1-Допущения!$E$13)*Допущения!$E$9 -> 64655.61 | ... AL55: =MAX(0,AL46-AK46)*(1-Допущения!$E$13)*Допущения!$E$9 -> 75319.88 | AM55: =SUM(C55:N55) -> 671843.85 | AN55: =SUM(O55:Z55) -> 840452.88 | AO55: =SUM(AA55:AL55) -> 887703.27 | AP55: =SUM(C55:AL55) -> 2400000
A56: fixed | B56: Постоянные расходы (команда) | C56: =Допущения!$E$16 -> 360000 | D56: =Допущения!$E$16 -> 360000 | E56: =Допущения!$E$16 -> 360000 | F56: =Допущения!$E$16 -> 360000 | G56: =Допущения!$E$16 -> 360000 | H56: =Допущения!$E$16 -> 360000 | I56: =Допущения!$E$16 -> 360000 | J56: =Допущения!$E$16 -> 360000 | ... AL56: =Допущения!$E$16 -> 360000 | AM56: =SUM(C56:N56) -> 4320000 | AN56: =SUM(O56:Z56) -> 4320000 | AO56: =SUM(AA56:AL56) -> 4320000 | AP56: =SUM(C56:AL56) -> 12960000
A57: op | B57: Операционная прибыль (маржинальный доход − постоянные − привлечение) | C57: =C54-C56-C55 -> -360000 | D57: =D54-D56-D55 -> -377930.43 | E57: =E54-E56-E55 -> -350379.96 | F57: =F54-F56-F55 -> -317030.08 | G57: =G54-G56-G55 -> -281481.54 | H57: =H54-H56-H55 -> -244505.44 | I57: =I54-I56-I55 -> -206463.51 | J57: =J54-J56-J55 -> -139334.22 | ... AL57: =AL54-AL56-AL55 -> 1234996.1 | AM57: =SUM(C57:N57) -> -2387341.4 | AN57: =SUM(O57:Z57) -> 4210522.9 | AO57: =SUM(AA57:AL57) -> 11412540 | AP57: =SUM(C57:AL57) -> 13235721
A58: capex | B58: CAPEX и вложения в оборотку | C58: =IF(C$44=1,Допущения!$E$18,0) -> 300000 | D58: =IF(D$44=1,Допущения!$E$18,0) -> 0 | E58: =IF(E$44=1,Допущения!$E$18,0) -> 0 | F58: =IF(F$44=1,Допущения!$E$18,0) -> 0 | G58: =IF(G$44=1,Допущения!$E$18,0) -> 0 | H58: =IF(H$44=1,Допущения!$E$18,0) -> 0 | I58: =IF(I$44=1,Допущения!$E$18,0) -> 0 | J58: =IF(J$44=1,Допущения!$E$18,0) -> 0 | ... AL58: =IF(AL$44=1,Допущения!$E$18,0) -> 0 | AM58: =SUM(C58:N58) -> 300000 | AN58: =SUM(O58:Z58) -> 0 | AO58: =SUM(AA58:AL58) -> 0 | AP58: =SUM(C58:AL58) -> 300000
A59: cf | B59: Денежный поток | C59: =C57-C58 -> -660000 | D59: =D57-D58 -> -377930.43 | E59: =E57-E58 -> -350379.96 | F59: =F57-F58 -> -317030.08 | G59: =G57-G58 -> -281481.54 | H59: =H57-H58 -> -244505.44 | I59: =I57-I58 -> -206463.51 | J59: =J57-J58 -> -139334.22 | ... AL59: =AL57-AL58 -> 1234996.1 | AM59: =SUM(C59:N59) -> -2687341.4 | AN59: =SUM(O59:Z59) -> 4210522.9 | AO59: =SUM(AA59:AL59) -> 11412540 | AP59: =SUM(C59:AL59) -> 12935721
A60: cum | B60: Накопленный денежный поток | C60: =0+C59 -> -660000 | D60: =C60+D59 -> -1037930.4 | E60: =D60+E59 -> -1388310.4 | F60: =E60+F59 -> -1705340.5 | G60: =F60+G59 -> -1986822 | H60: =G60+H59 -> -2231327.5 | I60: =H60+I59 -> -2437791 | J60: =I60+J59 -> -2577125.2 | K60: =J60+K59 -> -2672381.4 | ... AL60: =AK60+AL59 -> 12935721 | AM60: =N60 -> -2687341.4 | AN60: =Z60 -> 1523181.5 | AO60: =AL60 -> 12935721
A61: be_flag | B61: служебно: месяц устойчивой опер. прибыли | C61: =IF(AND(C57>0,COUNTIF(C57:AL57,"<=0")=0),C$44,99) -> 99 | D61: =IF(AND(D57>0,COUNTIF(D57:AL57,"<=0")=0),D$44,99) -> 99 | E61: =IF(AND(E57>0,COUNTIF(E57:AL57,"<=0")=0),E$44,99) -> 99 | F61: =IF(AND(F57>0,COUNTIF(F57:AL57,"<=0")=0),F$44,99) -> 99 | G61: =IF(AND(G57>0,COUNTIF(G57:AL57,"<=0")=0),G$44,99) -> 99 | H61: =IF(AND(H57>0,COUNTIF(H57:AL57,"<=0")=0),H$44,99) -> 99 | I61: =IF(AND(I57>0,COUNTIF(I57:AL57,"<=0")=0),I$44,99) -> 99 | J61: =IF(AND(J57>0,COUNTIF(J57:AL57,"<=0")=0),J$44,99) -> 99 | K61: =IF(AND(K57>0,COUNTIF(K57:AL57,"<=0")=0),K$44,99) -> 99 | L61: =IF(AND(L57>0,COUNTIF(L57:AL57,"<=0")=0),L$44,99) -> 99 | M61: =IF(AND(M57>0,COUNTIF(M57:AL57,"<=0")=0),M$44,99) -> 99 | N61: =IF(AND(N57>0,COUNTIF(N57:AL57,"<=0")=0),N$44,99) -> 12 | O61: =IF(AND(O57>0,COUNTIF(O57:AL57,"<=0")=0),O$44,99) -> 13 | P61: =IF(AND(P57>0,COUNTIF(P57:AL57,"<=0")=0),P$44,99) -> 14 | Q61: =IF(AND(Q57>0,COUNTIF(Q57:AL57,"<=0")=0),Q$44,99) -> 15 | R61: =IF(AND(R57>0,COUNTIF(R57:AL57,"<=0")=0),R$44,99) -> 16 | S61: =IF(AND(S57>0,COUNTIF(S57:AL57,"<=0")=0),S$44,99) -> 17 | T61: =IF(AND(T57>0,COUNTIF(T57:AL57,"<=0")=0),T$44,99) -> 18 | U61: =IF(AND(U57>0,COUNTIF(U57:AL57,"<=0")=0),U$44,99) -> 19 | V61: =IF(AND(V57>0,COUNTIF(V57:AL57,"<=0")=0),V$44,99) -> 20 | W61: =IF(AND(W57>0,COUNTIF(W57:AL57,"<=0")=0),W$44,99) -> 21 | X61: =IF(AND(X57>0,COUNTIF(X57:AL57,"<=0")=0),X$44,99) -> 22 | Y61: =IF(AND(Y57>0,COUNTIF(Y57:AL57,"<=0")=0),Y$44,99) -> 23 | Z61: =IF(AND(Z57>0,COUNTIF(Z57:AL57,"<=0")=0),Z$44,99) -> 24 | AA61: =IF(AND(AA57>0,COUNTIF(AA57:AL57,"<=0")=0),AA$44,99) -> 25 | AB61: =IF(AND(AB57>0,COUNTIF(AB57:AL57,"<=0")=0),AB$44,99) -> 26 | AC61: =IF(AND(AC57>0,COUNTIF(AC57:AL57,"<=0")=0),AC$44,99) -> 27 | AD61: =IF(AND(AD57>0,COUNTIF(AD57:AL57,"<=0")=0),AD$44,99) -> 28 | AE61: =IF(AND(AE57>0,COUNTIF(AE57:AL57,"<=0")=0),AE$44,99) -> 29 | AF61: =IF(AND(AF57>0,COUNTIF(AF57:AL57,"<=0")=0),AF$44,99) -> 30 | AG61: =IF(AND(AG57>0,COUNTIF(AG57:AL57,"<=0")=0),AG$44,99) -> 31 | AH61: =IF(AND(AH57>0,COUNTIF(AH57:AL57,"<=0")=0),AH$44,99) -> 32 | AI61: =IF(AND(AI57>0,COUNTIF(AI57:AL57,"<=0")=0),AI$44,99) -> 33 | AJ61: =IF(AND(AJ57>0,COUNTIF(AJ57:AL57,"<=0")=0),AJ$44,99) -> 34 | AK61: =IF(AND(AK57>0,COUNTIF(AK57:AL57,"<=0")=0),AK$44,99) -> 35 | AL61: =IF(AND(AL57>0,COUNTIF(AL57:AL57,"<=0")=0),AL$44,99) -> 36
A62: pb_flag | B62: служебно: месяц окупаемости | C62: =IF(AND(C60>=0,COUNTIF(C60:AL60,"<0")=0),C$44,99) -> 99 | D62: =IF(AND(D60>=0,COUNTIF(D60:AL60,"<0")=0),D$44,99) -> 99 | E62: =IF(AND(E60>=0,COUNTIF(E60:AL60,"<0")=0),E$44,99) -> 99 | F62: =IF(AND(F60>=0,COUNTIF(F60:AL60,"<0")=0),F$44,99) -> 99 | G62: =IF(AND(G60>=0,COUNTIF(G60:AL60,"<0")=0),G$44,99) -> 99 | H62: =IF(AND(H60>=0,COUNTIF(H60:AL60,"<0")=0),H$44,99) -> 99 | I62: =IF(AND(I60>=0,COUNTIF(I60:AL60,"<0")=0),I$44,99) -> 99 | J62: =IF(AND(J60>=0,COUNTIF(J60:AL60,"<0")=0),J$44,99) -> 99 | K62: =IF(AND(K60>=0,COUNTIF(K60:AL60,"<0")=0),K$44,99) -> 99 | L62: =IF(AND(L60>=0,COUNTIF(L60:AL60,"<0")=0),L$44,99) -> 99 | M62: =IF(AND(M60>=0,COUNTIF(M60:AL60,"<0")=0),M$44,99) -> 99 | N62: =IF(AND(N60>=0,COUNTIF(N60:AL60,"<0")=0),N$44,99) -> 99 | O62: =IF(AND(O60>=0,COUNTIF(O60:AL60,"<0")=0),O$44,99) -> 99 | P62: =IF(AND(P60>=0,COUNTIF(P60:AL60,"<0")=0),P$44,99) -> 99 | Q62: =IF(AND(Q60>=0,COUNTIF(Q60:AL60,"<0")=0),Q$44,99) -> 99 | R62: =IF(AND(R60>=0,COUNTIF(R60:AL60,"<0")=0),R$44,99) -> 99 | S62: =IF(AND(S60>=0,COUNTIF(S60:AL60,"<0")=0),S$44,99) -> 99 | T62: =IF(AND(T60>=0,COUNTIF(T60:AL60,"<0")=0),T$44,99) -> 99 | U62: =IF(AND(U60>=0,COUNTIF(U60:AL60,"<0")=0),U$44,99) -> 99 | V62: =IF(AND(V60>=0,COUNTIF(V60:AL60,"<0")=0),V$44,99) -> 99 | W62: =IF(AND(W60>=0,COUNTIF(W60:AL60,"<0")=0),W$44,99) -> 99 | X62: =IF(AND(X60>=0,COUNTIF(X60:AL60,"<0")=0),X$44,99) -> 22 | Y62: =IF(AND(Y60>=0,COUNTIF(Y60:AL60,"<0")=0),Y$44,99) -> 23 | Z62: =IF(AND(Z60>=0,COUNTIF(Z60:AL60,"<0")=0),Z$44,99) -> 24 | AA62: =IF(AND(AA60>=0,COUNTIF(AA60:AL60,"<0")=0),AA$44,99) -> 25 | AB62: =IF(AND(AB60>=0,COUNTIF(AB60:AL60,"<0")=0),AB$44,99) -> 26 | AC62: =IF(AND(AC60>=0,COUNTIF(AC60:AL60,"<0")=0),AC$44,99) -> 27 | AD62: =IF(AND(AD60>=0,COUNTIF(AD60:AL60,"<0")=0),AD$44,99) -> 28 | AE62: =IF(AND(AE60>=0,COUNTIF(AE60:AL60,"<0")=0),AE$44,99) -> 29 | AF62: =IF(AND(AF60>=0,COUNTIF(AF60:AL60,"<0")=0),AF$44,99) -> 30 | AG62: =IF(AND(AG60>=0,COUNTIF(AG60:AL60,"<0")=0),AG$44,99) -> 31 | AH62: =IF(AND(AH60>=0,COUNTIF(AH60:AL60,"<0")=0),AH$44,99) -> 32 | AI62: =IF(AND(AI60>=0,COUNTIF(AI60:AL60,"<0")=0),AI$44,99) -> 33 | AJ62: =IF(AND(AJ60>=0,COUNTIF(AJ60:AL60,"<0")=0),AJ$44,99) -> 34 | AK62: =IF(AND(AK60>=0,COUNTIF(AK60:AL60,"<0")=0),AK$44,99) -> 35 | AL62: =IF(AND(AL60>=0,COUNTIF(AL60:AL60,"<0")=0),AL$44,99) -> 36

Sheet D_курсы_родителям
A1: D. Полный эскалатор + платные курсы и клуб для родителей (включает всю коммерцию A)
A4: Сценарий: Осторожный | B4: Месяц → | C4: 1 | D4: 2 | E4: 3 | F4: 4 | G4: 5 | H4: 6 | I4: 7 | J4: 8 | K4: 9 | L4: 10 | M4: 11 | N4: 12 | O4: 13 | P4: 14 | Q4: 15 | R4: 16 | S4: 17 | T4: 18 | U4: 19 | V4: 20 | W4: 21 | X4: 22 | Y4: 23 | Z4: 24 | AA4: 25 | AB4: 26 | AC4: 27 | AD4: 28 | AE4: 29 | AF4: 30 | AG4: 31 | AH4: 32 | AI4: 33 | AJ4: 34 | AK4: 35 | AL4: 36 | AM4: Год 1 | AN4: Год 2 | AO4: Год 3 | AP4: Итого 36 мес
A5: contribA | B5: Маржинальный доход A (коммерция, РСЯ, TG) | C5: =A_дропшиппинг!C14 -> 0 | D5: =A_дропшиппинг!D14 -> 0 | E5: =A_дропшиппинг!E14 -> 33.089139 | F5: =A_дропшиппинг!F14 -> 93.590218 | G5: =A_дропшиппинг!G14 -> 171.93621 | H5: =A_дропшиппинг!H14 -> 264.71311 | I5: =A_дропшиппинг!I14 -> 369.94782 | J5: =A_дропшиппинг!J14 -> 486.30904 | ... AL5: =A_дропшиппинг!AL14 -> 9041.6 | AM5: =SUM(C5:N5) -> 4720.9039 | AN5: =SUM(O5:Z5) -> 27051.945 | AO5: =SUM(AA5:AL5) -> 63228.025 | AP5: =SUM(C5:AL5) -> 95000.874
A6: warm | B6: Тёплая база (TG + email/VK) | C6: =A_дропшиппинг!C6*(1+Допущения!$C$34) -> 0 | D6: =A_дропшиппинг!D6*(1+Допущения!$C$34) -> 0 | E6: =A_дропшиппинг!E6*(1+Допущения!$C$34) -> 75.661141 | F6: =A_дропшиппинг!F6*(1+Допущения!$C$34) -> 214.00202 | G6: =A_дропшиппинг!G6*(1+Допущения!$C$34) -> 393.14682 | H6: =A_дропшиппинг!H6*(1+Допущения!$C$34) -> 605.28912 | I6: =A_дропшиппинг!I6*(1+Допущения!$C$34) -> 845.91727 | J6: =A_дропшиппинг!J6*(1+Допущения!$C$34) -> 1111.9871 | ... AL6: =A_дропшиппинг!AL6*(1+Допущения!$C$34) -> 15000 | AM6: =N6 -> 2392.6153 | AN6: =Z6 -> 7807.4085 | AO6: =AL6 -> 15000
A7: course | B7: Выручка курсов (сглажено по месяцам) | C7: =IF(C$4>=Допущения!$C$30,C6*Допущения!$C$33*Допущения!$C$31*Допущения!$C$32/12,0) -> 0 | D7: =IF(D$4>=Допущения!$C$30,D6*Допущения!$C$33*Допущения!$C$31*Допущения!$C$32/12,0) -> 0 | E7: =IF(E$4>=Допущения!$C$30,E6*Допущения!$C$33*Допущения!$C$31*Допущения!$C$32/12,0) -> 0 | F7: =IF(F$4>=Допущения!$C$30,F6*Допущения!$C$33*Допущения!$C$31*Допущения!$C$32/12,0) -> 0 | G7: =IF(G$4>=Допущения!$C$30,G6*Допущения!$C$33*Допущения!$C$31*Допущения!$C$32/12,0) -> 0 | H7: =IF(H$4>=Допущения!$C$30,H6*Допущения!$C$33*Допущения!$C$31*Допущения!$C$32/12,0) -> 0 | I7: =IF(I$4>=Допущения!$C$30,I6*Допущения!$C$33*Допущения!$C$31*Допущения!$C$32/12,0) -> 0 | J7: =IF(J$4>=Допущения!$C$30,J6*Допущения!$C$33*Допущения!$C$31*Допущения!$C$32/12,0) -> 0 | ... AL7: =IF(AL$4>=Допущения!$C$30,AL6*Допущения!$C$33*Допущения!$C$31*Допущения!$C$32/12,0) -> 19000 | AM7: =SUM(C7:N7) -> 3030.6461 | AN7: =SUM(O7:Z7) -> 78351.671 | AO7: =SUM(AA7:AL7) -> 175942.39 | AP7: =SUM(C7:AL7) -> 257324.71
A8: club | B8: Выручка клуба | C8: =IF(C$4>=Допущения!$C$30,C6*Допущения!$C$36*Допущения!$C$35,0) -> 0 | D8: =IF(D$4>=Допущения!$C$30,D6*Допущения!$C$36*Допущения!$C$35,0) -> 0 | E8: =IF(E$4>=Допущения!$C$30,E6*Допущения!$C$36*Допущения!$C$35,0) -> 0 | F8: =IF(F$4>=Допущения!$C$30,F6*Допущения!$C$36*Допущения!$C$35,0) -> 0 | G8: =IF(G$4>=Допущения!$C$30,G6*Допущения!$C$36*Допущения!$C$35,0) -> 0 | H8: =IF(H$4>=Допущения!$C$30,H6*Допущения!$C$36*Допущения!$C$35,0) -> 0 | I8: =IF(I$4>=Допущения!$C$30,I6*Допущения!$C$36*Допущения!$C$35,0) -> 0 | J8: =IF(J$4>=Допущения!$C$30,J6*Допущения!$C$36*Допущения!$C$35,0) -> 0 | ... AL8: =IF(AL$4>=Допущения!$C$30,AL6*Допущения!$C$36*Допущения!$C$35,0) -> 13050 | AM8: =SUM(C8:N8) -> 2081.5753 | AN8: =SUM(O8:Z8) -> 53815.226 | AO8: =SUM(AA8:AL8) -> 120844.64 | AP8: =SUM(C8:AL8) -> 176741.44
A9: rev | B9: Выручка платных продуктов | C9: =C7+C8 -> 0 | D9: =D7+D8 -> 0 | E9: =E7+E8 -> 0 | F9: =F7+F8 -> 0 | G9: =G7+G8 -> 0 | H9: =H7+H8 -> 0 | I9: =I7+I8 -> 0 | J9: =J7+J8 -> 0 | ... AL9: =AL7+AL8 -> 32050 | AM9: =SUM(C9:N9) -> 5112.2215 | AN9: =SUM(O9:Z9) -> 132166.9 | AO9: =SUM(AA9:AL9) -> 296787.03 | AP9: =SUM(C9:AL9) -> 434066.15
A10: contrib | B10: Маржинальный доход (A + продукты − комиссии, реклама запусков, налог) | C10: =C5+C9*(1-Допущения!$C$37-Допущения!$C$14)-C7*Допущения!$C$38 -> 0 | D10: =D5+D9*(1-Допущения!$C$37-Допущения!$C$14)-D7*Допущения!$C$38 -> 0 | E10: =E5+E9*(1-Допущения!$C$37-Допущения!$C$14)-E7*Допущения!$C$38 -> 33.089139 | F10: =F5+F9*(1-Допущения!$C$37-Допущения!$C$14)-F7*Допущения!$C$38 -> 93.590218 | G10: =G5+G9*(1-Допущения!$C$37-Допущения!$C$14)-G7*Допущения!$C$38 -> 171.93621 | H10: =H5+H9*(1-Допущения!$C$37-Допущения!$C$14)-H7*Допущения!$C$38 -> 264.71311 | I10: =I5+I9*(1-Допущения!$C$37-Допущения!$C$14)-I7*Допущения!$C$38 -> 369.94782 | J10: =J5+J9*(1-Допущения!$C$37-Допущения!$C$14)-J7*Допущения!$C$38 -> 486.30904 | ... AL10: =AL5+AL9*(1-Допущения!$C$37-Допущения!$C$14)-AL7*Допущения!$C$38 -> 30572.6 | AM10: =SUM(C10:N10) -> 8155.264 | AN10: =SUM(O10:Z10) -> 115840.88 | AO10: =SUM(AA10:AL10) -> 262607.79 | AP10: =SUM(C10:AL10) -> 386603.94
A11: acq | B11: Покупка подписчиков Telegram | C11: =A_дропшиппинг!C15 -> 0 | D11: =A_дропшиппинг!D15 -> 0 | E11: =A_дропшиппинг!E15 -> 12105.782 | F11: =A_дропшиппинг!F15 -> 22134.541 | G11: =A_дропшиппинг!G15 -> 28663.167 | H11: =A_дропшиппинг!H15 -> 33942.769 | I11: =A_дропшиппинг!I15 -> 38500.503 | J11: =A_дропшиппинг!J15 -> 42571.177 | ... AL11: =A_дропшиппинг!AL15 -> 105099.95 | AM11: =SUM(C11:N11) -> 382818.45 | AN11: =SUM(O11:Z11) -> 866366.91 | AO11: =SUM(AA11:AL11) -> 1150814.6 | AP11: =SUM(C11:AL11) -> 2400000
A12: fixed | B12: Постоянные расходы (команда) | C12: =Допущения!$C$16+IF(C$4>=Допущения!$C$30-1,Допущения!$C$39,0) -> 480000 | D12: =Допущения!$C$16+IF(D$4>=Допущения!$C$30-1,Допущения!$C$39,0) -> 480000 | E12: =Допущения!$C$16+IF(E$4>=Допущения!$C$30-1,Допущения!$C$39,0) -> 480000 | F12: =Допущения!$C$16+IF(F$4>=Допущения!$C$30-1,Допущения!$C$39,0) -> 480000 | G12: =Допущения!$C$16+IF(G$4>=Допущения!$C$30-1,Допущения!$C$39,0) -> 480000 | H12: =Допущения!$C$16+IF(H$4>=Допущения!$C$30-1,Допущения!$C$39,0) -> 480000 | I12: =Допущения!$C$16+IF(I$4>=Допущения!$C$30-1,Допущения!$C$39,0) -> 480000 | J12: =Допущения!$C$16+IF(J$4>=Допущения!$C$30-1,Допущения!$C$39,0) -> 480000 | ... AL12: =Допущения!$C$16+IF(AL$4>=Допущения!$C$30-1,Допущения!$C$39,0) -> 600000 | AM12: =SUM(C12:N12) -> 6000000 | AN12: =SUM(O12:Z12) -> 7200000 | AO12: =SUM(AA12:AL12) -> 7200000 | AP12: =SUM(C12:AL12) -> 20400000
A13: op | B13: Операционная прибыль (маржинальный доход − постоянные − привлечение) | C13: =C10-C12-C11 -> -480000 | D13: =D10-D12-D11 -> -480000 | E13: =E10-E12-E11 -> -492072.69 | F13: =F10-F12-F11 -> -502040.95 | G13: =G10-G12-G11 -> -508491.23 | H13: =H10-H12-H11 -> -513678.06 | I13: =I10-I12-I11 -> -518130.56 | J13: =J10-J12-J11 -> -522084.87 | ... AL13: =AL10-AL12-AL11 -> -674527.35 | AM13: =SUM(C13:N13) -> -6374663.2 | AN13: =SUM(O13:Z13) -> -7950526 | AO13: =SUM(AA13:AL13) -> -8088206.8 | AP13: =SUM(C13:AL13) -> -22413396
A14: capex | B14: CAPEX и вложения в оборотку | C14: =IF(C$4=1,Допущения!$C$18,0)+IF(AND(C$4>=Допущения!$C$30-3,C$4<Допущения!$C$30),Допущения!$C$40/3,0) -> 600000 | D14: =IF(D$4=1,Допущения!$C$18,0)+IF(AND(D$4>=Допущения!$C$30-3,D$4<Допущения!$C$30),Допущения!$C$40/3,0) -> 0 | E14: =IF(E$4=1,Допущения!$C$18,0)+IF(AND(E$4>=Допущения!$C$30-3,E$4<Допущения!$C$30),Допущения!$C$40/3,0) -> 0 | F14: =IF(F$4=1,Допущения!$C$18,0)+IF(AND(F$4>=Допущения!$C$30-3,F$4<Допущения!$C$30),Допущения!$C$40/3,0) -> 0 | G14: =IF(G$4=1,Допущения!$C$18,0)+IF(AND(G$4>=Допущения!$C$30-3,G$4<Допущения!$C$30),Допущения!$C$40/3,0) -> 0 | H14: =IF(H$4=1,Допущения!$C$18,0)+IF(AND(H$4>=Допущения!$C$30-3,H$4<Допущения!$C$30),Допущения!$C$40/3,0) -> 0 | I14: =IF(I$4=1,Допущения!$C$18,0)+IF(AND(I$4>=Допущения!$C$30-3,I$4<Допущения!$C$30),Допущения!$C$40/3,0) -> 0 | J14: =IF(J$4=1,Допущения!$C$18,0)+IF(AND(J$4>=Допущения!$C$30-3,J$4<Допущения!$C$30),Допущения!$C$40/3,0) -> 0 | ... AL14: =IF(AL$4=1,Допущения!$C$18,0)+IF(AND(AL$4>=Допущения!$C$30-3,AL$4<Допущения!$C$30),Допущения!$C$40/3,0) -> 0 | AM14: =SUM(C14:N14) -> 1800000 | AN14: =SUM(O14:Z14) -> 0 | AO14: =SUM(AA14:AL14) -> 0 | AP14: =SUM(C14:AL14) -> 1800000
A15: cf | B15: Денежный поток | C15: =C13-C14 -> -1080000 | D15: =D13-D14 -> -480000 | E15: =E13-E14 -> -492072.69 | F15: =F13-F14 -> -502040.95 | G15: =G13-G14 -> -508491.23 | H15: =H13-H14 -> -513678.06 | I15: =I13-I14 -> -518130.56 | J15: =J13-J14 -> -522084.87 | ... AL15: =AL13-AL14 -> -674527.35 | AM15: =SUM(C15:N15) -> -8174663.2 | AN15: =SUM(O15:Z15) -> -7950526 | AO15: =SUM(AA15:AL15) -> -8088206.8 | AP15: =SUM(C15:AL15) -> -24213396
A16: cum | B16: Накопленный денежный поток | C16: =0+C15 -> -1080000 | D16: =C16+D15 -> -1560000 | E16: =D16+E15 -> -2052072.7 | F16: =E16+F15 -> -2554113.6 | G16: =F16+G15 -> -3062604.9 | H16: =G16+H15 -> -3576282.9 | I16: =H16+I15 -> -4094413.5 | J16: =I16+J15 -> -4616498.4 | K16: =J16+K15 -> -5542169.8 | ... AL16: =AK16+AL15 -> -24213396 | AM16: =N16 -> -8174663.2 | AN16: =Z16 -> -16125189 | AO16: =AL16 -> -24213396
A17: be_flag | B17: служебно: месяц устойчивой опер. прибыли | C17: =IF(AND(C13>0,COUNTIF(C13:AL13,"<=0")=0),C$4,99) -> 99 | D17: =IF(AND(D13>0,COUNTIF(D13:AL13,"<=0")=0),D$4,99) -> 99 | E17: =IF(AND(E13>0,COUNTIF(E13:AL13,"<=0")=0),E$4,99) -> 99 | F17: =IF(AND(F13>0,COUNTIF(F13:AL13,"<=0")=0),F$4,99) -> 99 | G17: =IF(AND(G13>0,COUNTIF(G13:AL13,"<=0")=0),G$4,99) -> 99 | H17: =IF(AND(H13>0,COUNTIF(H13:AL13,"<=0")=0),H$4,99) -> 99 | I17: =IF(AND(I13>0,COUNTIF(I13:AL13,"<=0")=0),I$4,99) -> 99 | J17: =IF(AND(J13>0,COUNTIF(J13:AL13,"<=0")=0),J$4,99) -> 99 | K17: =IF(AND(K13>0,COUNTIF(K13:AL13,"<=0")=0),K$4,99) -> 99 | L17: =IF(AND(L13>0,COUNTIF(L13:AL13,"<=0")=0),L$4,99) -> 99 | M17: =IF(AND(M13>0,COUNTIF(M13:AL13,"<=0")=0),M$4,99) -> 99 | N17: =IF(AND(N13>0,COUNTIF(N13:AL13,"<=0")=0),N$4,99) -> 99 | O17: =IF(AND(O13>0,COUNTIF(O13:AL13,"<=0")=0),O$4,99) -> 99 | P17: =IF(AND(P13>0,COUNTIF(P13:AL13,"<=0")=0),P$4,99) -> 99 | Q17: =IF(AND(Q13>0,COUNTIF(Q13:AL13,"<=0")=0),Q$4,99) -> 99 | R17: =IF(AND(R13>0,COUNTIF(R13:AL13,"<=0")=0),R$4,99) -> 99 | S17: =IF(AND(S13>0,COUNTIF(S13:AL13,"<=0")=0),S$4,99) -> 99 | T17: =IF(AND(T13>0,COUNTIF(T13:AL13,"<=0")=0),T$4,99) -> 99 | U17: =IF(AND(U13>0,COUNTIF(U13:AL13,"<=0")=0),U$4,99) -> 99 | V17: =IF(AND(V13>0,COUNTIF(V13:AL13,"<=0")=0),V$4,99) -> 99 | W17: =IF(AND(W13>0,COUNTIF(W13:AL13,"<=0")=0),W$4,99) -> 99 | X17: =IF(AND(X13>0,COUNTIF(X13:AL13,"<=0")=0),X$4,99) -> 99 | Y17: =IF(AND(Y13>0,COUNTIF(Y13:AL13,"<=0")=0),Y$4,99) -> 99 | Z17: =IF(AND(Z13>0,COUNTIF(Z13:AL13,"<=0")=0),Z$4,99) -> 99 | AA17: =IF(AND(AA13>0,COUNTIF(AA13:AL13,"<=0")=0),AA$4,99) -> 99 | AB17: =IF(AND(AB13>0,COUNTIF(AB13:AL13,"<=0")=0),AB$4,99) -> 99 | AC17: =IF(AND(AC13>0,COUNTIF(AC13:AL13,"<=0")=0),AC$4,99) -> 99 | AD17: =IF(AND(AD13>0,COUNTIF(AD13:AL13,"<=0")=0),AD$4,99) -> 99 | AE17: =IF(AND(AE13>0,COUNTIF(AE13:AL13,"<=0")=0),AE$4,99) -> 99 | AF17: =IF(AND(AF13>0,COUNTIF(AF13:AL13,"<=0")=0),AF$4,99) -> 99 | AG17: =IF(AND(AG13>0,COUNTIF(AG13:AL13,"<=0")=0),AG$4,99) -> 99 | AH17: =IF(AND(AH13>0,COUNTIF(AH13:AL13,"<=0")=0),AH$4,99) -> 99 | AI17: =IF(AND(AI13>0,COUNTIF(AI13:AL13,"<=0")=0),AI$4,99) -> 99 | AJ17: =IF(AND(AJ13>0,COUNTIF(AJ13:AL13,"<=0")=0),AJ$4,99) -> 99 | AK17: =IF(AND(AK13>0,COUNTIF(AK13:AL13,"<=0")=0),AK$4,99) -> 99 | AL17: =IF(AND(AL13>0,COUNTIF(AL13:AL13,"<=0")=0),AL$4,99) -> 99
A18: pb_flag | B18: служебно: месяц окупаемости | C18: =IF(AND(C16>=0,COUNTIF(C16:AL16,"<0")=0),C$4,99) -> 99 | D18: =IF(AND(D16>=0,COUNTIF(D16:AL16,"<0")=0),D$4,99) -> 99 | E18: =IF(AND(E16>=0,COUNTIF(E16:AL16,"<0")=0),E$4,99) -> 99 | F18: =IF(AND(F16>=0,COUNTIF(F16:AL16,"<0")=0),F$4,99) -> 99 | G18: =IF(AND(G16>=0,COUNTIF(G16:AL16,"<0")=0),G$4,99) -> 99 | H18: =IF(AND(H16>=0,COUNTIF(H16:AL16,"<0")=0),H$4,99) -> 99 | I18: =IF(AND(I16>=0,COUNTIF(I16:AL16,"<0")=0),I$4,99) -> 99 | J18: =IF(AND(J16>=0,COUNTIF(J16:AL16,"<0")=0),J$4,99) -> 99 | K18: =IF(AND(K16>=0,COUNTIF(K16:AL16,"<0")=0),K$4,99) -> 99 | L18: =IF(AND(L16>=0,COUNTIF(L16:AL16,"<0")=0),L$4,99) -> 99 | M18: =IF(AND(M16>=0,COUNTIF(M16:AL16,"<0")=0),M$4,99) -> 99 | N18: =IF(AND(N16>=0,COUNTIF(N16:AL16,"<0")=0),N$4,99) -> 99 | O18: =IF(AND(O16>=0,COUNTIF(O16:AL16,"<0")=0),O$4,99) -> 99 | P18: =IF(AND(P16>=0,COUNTIF(P16:AL16,"<0")=0),P$4,99) -> 99 | Q18: =IF(AND(Q16>=0,COUNTIF(Q16:AL16,"<0")=0),Q$4,99) -> 99 | R18: =IF(AND(R16>=0,COUNTIF(R16:AL16,"<0")=0),R$4,99) -> 99 | S18: =IF(AND(S16>=0,COUNTIF(S16:AL16,"<0")=0),S$4,99) -> 99 | T18: =IF(AND(T16>=0,COUNTIF(T16:AL16,"<0")=0),T$4,99) -> 99 | U18: =IF(AND(U16>=0,COUNTIF(U16:AL16,"<0")=0),U$4,99) -> 99 | V18: =IF(AND(V16>=0,COUNTIF(V16:AL16,"<0")=0),V$4,99) -> 99 | W18: =IF(AND(W16>=0,COUNTIF(W16:AL16,"<0")=0),W$4,99) -> 99 | X18: =IF(AND(X16>=0,COUNTIF(X16:AL16,"<0")=0),X$4,99) -> 99 | Y18: =IF(AND(Y16>=0,COUNTIF(Y16:AL16,"<0")=0),Y$4,99) -> 99 | Z18: =IF(AND(Z16>=0,COUNTIF(Z16:AL16,"<0")=0),Z$4,99) -> 99 | AA18: =IF(AND(AA16>=0,COUNTIF(AA16:AL16,"<0")=0),AA$4,99) -> 99 | AB18: =IF(AND(AB16>=0,COUNTIF(AB16:AL16,"<0")=0),AB$4,99) -> 99 | AC18: =IF(AND(AC16>=0,COUNTIF(AC16:AL16,"<0")=0),AC$4,99) -> 99 | AD18: =IF(AND(AD16>=0,COUNTIF(AD16:AL16,"<0")=0),AD$4,99) -> 99 | AE18: =IF(AND(AE16>=0,COUNTIF(AE16:AL16,"<0")=0),AE$4,99) -> 99 | AF18: =IF(AND(AF16>=0,COUNTIF(AF16:AL16,"<0")=0),AF$4,99) -> 99 | AG18: =IF(AND(AG16>=0,COUNTIF(AG16:AL16,"<0")=0),AG$4,99) -> 99 | AH18: =IF(AND(AH16>=0,COUNTIF(AH16:AL16,"<0")=0),AH$4,99) -> 99 | AI18: =IF(AND(AI16>=0,COUNTIF(AI16:AL16,"<0")=0),AI$4,99) -> 99 | AJ18: =IF(AND(AJ16>=0,COUNTIF(AJ16:AL16,"<0")=0),AJ$4,99) -> 99 | AK18: =IF(AND(AK16>=0,COUNTIF(AK16:AL16,"<0")=0),AK$4,99) -> 99 | AL18: =IF(AND(AL16>=0,COUNTIF(AL16:AL16,"<0")=0),AL$4,99) -> 99
A20: Сценарий: Базовый | B20: Месяц → | C20: 1 | D20: 2 | E20: 3 | F20: 4 | G20: 5 | H20: 6 | I20: 7 | J20: 8 | K20: 9 | L20: 10 | M20: 11 | N20: 12 | O20: 13 | P20: 14 | Q20: 15 | R20: 16 | S20: 17 | T20: 18 | U20: 19 | V20: 20 | W20: 21 | X20: 22 | Y20: 23 | Z20: 24 | AA20: 25 | AB20: 26 | AC20: 27 | AD20: 28 | AE20: 29 | AF20: 30 | AG20: 31 | AH20: 32 | AI20: 33 | AJ20: 34 | AK20: 35 | AL20: 36 | AM20: Год 1 | AN20: Год 2 | AO20: Год 3 | AP20: Итого 36 мес
A21: contribA | B21: Маржинальный доход A (коммерция, РСЯ, TG) | C21: =A_дропшиппинг!C34 -> 0 | D21: =A_дропшиппинг!D34 -> 0 | E21: =A_дропшиппинг!E34 -> 998.46074 | F21: =A_дропшиппинг!F34 -> 2458.4987 | G21: =A_дропшиппинг!G34 -> 4164.747 | H21: =A_дропшиппинг!H34 -> 6053.534 | I21: =A_дропшиппинг!I34 -> 8090.8099 | J21: =A_дропшиппинг!J34 -> 10254.81 | ... AL21: =A_дропшиппинг!AL34 -> 124100.8 | AM21: =SUM(C21:N21) -> 96750.391 | AN21: =SUM(O21:Z21) -> 539113.59 | AO21: =SUM(AA21:AL21) -> 1187341.1 | AP21: =SUM(C21:AL21) -> 1823205.1
A22: warm | B22: Тёплая база (TG + email/VK) | C22: =A_дропшиппинг!C26*(1+Допущения!$D$34) -> 0 | D22: =A_дропшиппинг!D26*(1+Допущения!$D$34) -> 0 | E22: =A_дропшиппинг!E26*(1+Допущения!$D$34) -> 459.50466 | F22: =A_дропшиппинг!F26*(1+Допущения!$D$34) -> 1131.4332 | G22: =A_дропшиппинг!G26*(1+Допущения!$D$34) -> 1916.6709 | H22: =A_дропшиппинг!H26*(1+Допущения!$D$34) -> 2785.9153 | I22: =A_дропшиппинг!I26*(1+Допущения!$D$34) -> 3723.4963 | J22: =A_дропшиппинг!J26*(1+Допущения!$D$34) -> 4719.3974 | ... AL22: =A_дропшиппинг!AL26*(1+Допущения!$D$34) -> 45000 | AM22: =N22 -> 9168.3233 | AN22: =Z22 -> 25552.854 | AO22: =AL22 -> 45000
A23: course | B23: Выручка курсов (сглажено по месяцам) | C23: =IF(C$20>=Допущения!$D$30,C22*Допущения!$D$33*Допущения!$D$31*Допущения!$D$32/12,0) -> 0 | D23: =IF(D$20>=Допущения!$D$30,D22*Допущения!$D$33*Допущения!$D$31*Допущения!$D$32/12,0) -> 0 | E23: =IF(E$20>=Допущения!$D$30,E22*Допущения!$D$33*Допущения!$D$31*Допущения!$D$32/12,0) -> 0 | F23: =IF(F$20>=Допущения!$D$30,F22*Допущения!$D$33*Допущения!$D$31*Допущения!$D$32/12,0) -> 0 | G23: =IF(G$20>=Допущения!$D$30,G22*Допущения!$D$33*Допущения!$D$31*Допущения!$D$32/12,0) -> 0 | H23: =IF(H$20>=Допущения!$D$30,H22*Допущения!$D$33*Допущения!$D$31*Допущения!$D$32/12,0) -> 0 | I23: =IF(I$20>=Допущения!$D$30,I22*Допущения!$D$33*Допущения!$D$31*Допущения!$D$32/12,0) -> 0 | J23: =IF(J$20>=Допущения!$D$30,J22*Допущения!$D$33*Допущения!$D$31*Допущения!$D$32/12,0) -> 0 | ... AL23: =IF(AL$20>=Допущения!$D$30,AL22*Допущения!$D$33*Допущения!$D$31*Допущения!$D$32/12,0) -> 326250 | AM23: =SUM(C23:N23) -> 215972.96 | AN23: =SUM(O23:Z23) -> 1542619.4 | AO23: =SUM(AA23:AL23) -> 3121414.4 | AP23: =SUM(C23:AL23) -> 4880006.8
A24: club | B24: Выручка клуба | C24: =IF(C$20>=Допущения!$D$30,C22*Допущения!$D$36*Допущения!$D$35,0) -> 0 | D24: =IF(D$20>=Допущения!$D$30,D22*Допущения!$D$36*Допущения!$D$35,0) -> 0 | E24: =IF(E$20>=Допущения!$D$30,E22*Допущения!$D$36*Допущения!$D$35,0) -> 0 | F24: =IF(F$20>=Допущения!$D$30,F22*Допущения!$D$36*Допущения!$D$35,0) -> 0 | G24: =IF(G$20>=Допущения!$D$30,G22*Допущения!$D$36*Допущения!$D$35,0) -> 0 | H24: =IF(H$20>=Допущения!$D$30,H22*Допущения!$D$36*Допущения!$D$35,0) -> 0 | I24: =IF(I$20>=Допущения!$D$30,I22*Допущения!$D$36*Допущения!$D$35,0) -> 0 | J24: =IF(J$20>=Допущения!$D$30,J22*Допущения!$D$36*Допущения!$D$35,0) -> 0 | ... AL24: =IF(AL$20>=Допущения!$D$30,AL22*Допущения!$D$36*Допущения!$D$35,0) -> 140400 | AM24: =SUM(C24:N24) -> 92942.848 | AN24: =SUM(O24:Z24) -> 663858.29 | AO24: =SUM(AA24:AL24) -> 1343284.5 | AP24: =SUM(C24:AL24) -> 2100085.7
A25: rev | B25: Выручка платных продуктов | C25: =C23+C24 -> 0 | D25: =D23+D24 -> 0 | E25: =E23+E24 -> 0 | F25: =F23+F24 -> 0 | G25: =G23+G24 -> 0 | H25: =H23+H24 -> 0 | I25: =I23+I24 -> 0 | J25: =J23+J24 -> 0 | ... AL25: =AL23+AL24 -> 466650 | AM25: =SUM(C25:N25) -> 308915.81 | AN25: =SUM(O25:Z25) -> 2206477.7 | AO25: =SUM(AA25:AL25) -> 4464699 | AP25: =SUM(C25:AL25) -> 6980092.5
A26: contrib | B26: Маржинальный доход (A + продукты − комиссии, реклама запусков, налог) | C26: =C21+C25*(1-Допущения!$D$37-Допущения!$D$14)-C23*Допущения!$D$38 -> 0 | D26: =D21+D25*(1-Допущения!$D$37-Допущения!$D$14)-D23*Допущения!$D$38 -> 0 | E26: =E21+E25*(1-Допущения!$D$37-Допущения!$D$14)-E23*Допущения!$D$38 -> 998.46074 | F26: =F21+F25*(1-Допущения!$D$37-Допущения!$D$14)-F23*Допущения!$D$38 -> 2458.4987 | G26: =G21+G25*(1-Допущения!$D$37-Допущения!$D$14)-G23*Допущения!$D$38 -> 4164.747 | H26: =H21+H25*(1-Допущения!$D$37-Допущения!$D$14)-H23*Допущения!$D$38 -> 6053.534 | I26: =I21+I25*(1-Допущения!$D$37-Допущения!$D$14)-I23*Допущения!$D$38 -> 8090.8099 | J26: =J21+J25*(1-Допущения!$D$37-Допущения!$D$14)-J23*Допущения!$D$38 -> 10254.81 | ... AL26: =AL21+AL25*(1-Допущения!$D$37-Допущения!$D$14)-AL23*Допущения!$D$38 -> 450836.8 | AM26: =SUM(C26:N26) -> 313045.08 | AN26: =SUM(O26:Z26) -> 2084031 | AO26: =SUM(AA26:AL26) -> 4313405.3 | AP26: =SUM(C26:AL26) -> 6710481.4
A27: acq | B27: Покупка подписчиков Telegram | C27: =A_дропшиппинг!C35 -> 0 | D27: =A_дропшиппинг!D35 -> 0 | E27: =A_дропшиппинг!E35 -> 27570.28 | F27: =A_дропшиппинг!F35 -> 40315.712 | G27: =A_дропшиппинг!G35 -> 47114.263 | H27: =A_дропшиппинг!H35 -> 52154.664 | I27: =A_дропшиппинг!I35 -> 56254.86 | J27: =A_дропшиппинг!J35 -> 59754.064 | ... AL27: =A_дропшиппинг!AL35 -> 102776.68 | AM27: =SUM(C27:N27) -> 550099.4 | AN27: =SUM(O27:Z27) -> 983071.81 | AO27: =SUM(AA27:AL27) -> 1166828.8 | AP27: =SUM(C27:AL27) -> 2700000
A28: fixed | B28: Постоянные расходы (команда) | C28: =Допущения!$D$16+IF(C$20>=Допущения!$D$30-1,Допущения!$D$39,0) -> 420000 | D28: =Допущения!$D$16+IF(D$20>=Допущения!$D$30-1,Допущения!$D$39,0) -> 420000 | E28: =Допущения!$D$16+IF(E$20>=Допущения!$D$30-1,Допущения!$D$39,0) -> 420000 | F28: =Допущения!$D$16+IF(F$20>=Допущения!$D$30-1,Допущения!$D$39,0) -> 420000 | G28: =Допущения!$D$16+IF(G$20>=Допущения!$D$30-1,Допущения!$D$39,0) -> 420000 | H28: =Допущения!$D$16+IF(H$20>=Допущения!$D$30-1,Допущения!$D$39,0) -> 420000 | I28: =Допущения!$D$16+IF(I$20>=Допущения!$D$30-1,Допущения!$D$39,0) -> 420000 | J28: =Допущения!$D$16+IF(J$20>=Допущения!$D$30-1,Допущения!$D$39,0) -> 520000 | ... AL28: =Допущения!$D$16+IF(AL$20>=Допущения!$D$30-1,Допущения!$D$39,0) -> 520000 | AM28: =SUM(C28:N28) -> 5540000 | AN28: =SUM(O28:Z28) -> 6240000 | AO28: =SUM(AA28:AL28) -> 6240000 | AP28: =SUM(C28:AL28) -> 18020000
A29: op | B29: Операционная прибыль (маржинальный доход − постоянные − привлечение) | C29: =C26-C28-C27 -> -420000 | D29: =D26-D28-D27 -> -420000 | E29: =E26-E28-E27 -> -446571.82 | F29: =F26-F28-F27 -> -457857.21 | G29: =G26-G28-G27 -> -462949.52 | H29: =H26-H28-H27 -> -466101.13 | I29: =I26-I28-I27 -> -468164.05 | J29: =J26-J28-J27 -> -569499.25 | ... AL29: =AL26-AL28-AL27 -> -171939.88 | AM29: =SUM(C29:N29) -> -5777054.3 | AN29: =SUM(O29:Z29) -> -5139040.8 | AO29: =SUM(AA29:AL29) -> -3093423.5 | AP29: =SUM(C29:AL29) -> -14009519
A30: capex | B30: CAPEX и вложения в оборотку | C30: =IF(C$20=1,Допущения!$D$18,0)+IF(AND(C$20>=Допущения!$D$30-3,C$20<Допущения!$D$30),Допущения!$D$40/3,0) -> 400000 | D30: =IF(D$20=1,Допущения!$D$18,0)+IF(AND(D$20>=Допущения!$D$30-3,D$20<Допущения!$D$30),Допущения!$D$40/3,0) -> 0 | E30: =IF(E$20=1,Допущения!$D$18,0)+IF(AND(E$20>=Допущения!$D$30-3,E$20<Допущения!$D$30),Допущения!$D$40/3,0) -> 0 | F30: =IF(F$20=1,Допущения!$D$18,0)+IF(AND(F$20>=Допущения!$D$30-3,F$20<Допущения!$D$30),Допущения!$D$40/3,0) -> 0 | G30: =IF(G$20=1,Допущения!$D$18,0)+IF(AND(G$20>=Допущения!$D$30-3,G$20<Допущения!$D$30),Допущения!$D$40/3,0) -> 0 | H30: =IF(H$20=1,Допущения!$D$18,0)+IF(AND(H$20>=Допущения!$D$30-3,H$20<Допущения!$D$30),Допущения!$D$40/3,0) -> 266666.67 | I30: =IF(I$20=1,Допущения!$D$18,0)+IF(AND(I$20>=Допущения!$D$30-3,I$20<Допущения!$D$30),Допущения!$D$40/3,0) -> 266666.67 | J30: =IF(J$20=1,Допущения!$D$18,0)+IF(AND(J$20>=Допущения!$D$30-3,J$20<Допущения!$D$30),Допущения!$D$40/3,0) -> 266666.67 | ... AL30: =IF(AL$20=1,Допущения!$D$18,0)+IF(AND(AL$20>=Допущения!$D$30-3,AL$20<Допущения!$D$30),Допущения!$D$40/3,0) -> 0 | AM30: =SUM(C30:N30) -> 1200000 | AN30: =SUM(O30:Z30) -> 0 | AO30: =SUM(AA30:AL30) -> 0 | AP30: =SUM(C30:AL30) -> 1200000
A31: cf | B31: Денежный поток | C31: =C29-C30 -> -820000 | D31: =D29-D30 -> -420000 | E31: =E29-E30 -> -446571.82 | F31: =F29-F30 -> -457857.21 | G31: =G29-G30 -> -462949.52 | H31: =H29-H30 -> -732767.8 | I31: =I29-I30 -> -734830.72 | J31: =J29-J30 -> -836165.92 | ... AL31: =AL29-AL30 -> -171939.88 | AM31: =SUM(C31:N31) -> -6977054.3 | AN31: =SUM(O31:Z31) -> -5139040.8 | AO31: =SUM(AA31:AL31) -> -3093423.5 | AP31: =SUM(C31:AL31) -> -15209519
A32: cum | B32: Накопленный денежный поток | C32: =0+C31 -> -820000 | D32: =C32+D31 -> -1240000 | E32: =D32+E31 -> -1686571.8 | F32: =E32+F31 -> -2144429 | G32: =F32+G31 -> -2607378.5 | H32: =G32+H31 -> -3340146.3 | I32: =H32+I31 -> -4074977.1 | J32: =I32+J31 -> -4911143 | K32: =J32+K31 -> -5439573.1 | ... AL32: =AK32+AL31 -> -15209519 | AM32: =N32 -> -6977054.3 | AN32: =Z32 -> -12116095 | AO32: =AL32 -> -15209519
A33: be_flag | B33: служебно: месяц устойчивой опер. прибыли | C33: =IF(AND(C29>0,COUNTIF(C29:AL29,"<=0")=0),C$20,99) -> 99 | D33: =IF(AND(D29>0,COUNTIF(D29:AL29,"<=0")=0),D$20,99) -> 99 | E33: =IF(AND(E29>0,COUNTIF(E29:AL29,"<=0")=0),E$20,99) -> 99 | F33: =IF(AND(F29>0,COUNTIF(F29:AL29,"<=0")=0),F$20,99) -> 99 | G33: =IF(AND(G29>0,COUNTIF(G29:AL29,"<=0")=0),G$20,99) -> 99 | H33: =IF(AND(H29>0,COUNTIF(H29:AL29,"<=0")=0),H$20,99) -> 99 | I33: =IF(AND(I29>0,COUNTIF(I29:AL29,"<=0")=0),I$20,99) -> 99 | J33: =IF(AND(J29>0,COUNTIF(J29:AL29,"<=0")=0),J$20,99) -> 99 | K33: =IF(AND(K29>0,COUNTIF(K29:AL29,"<=0")=0),K$20,99) -> 99 | L33: =IF(AND(L29>0,COUNTIF(L29:AL29,"<=0")=0),L$20,99) -> 99 | M33: =IF(AND(M29>0,COUNTIF(M29:AL29,"<=0")=0),M$20,99) -> 99 | N33: =IF(AND(N29>0,COUNTIF(N29:AL29,"<=0")=0),N$20,99) -> 99 | O33: =IF(AND(O29>0,COUNTIF(O29:AL29,"<=0")=0),O$20,99) -> 99 | P33: =IF(AND(P29>0,COUNTIF(P29:AL29,"<=0")=0),P$20,99) -> 99 | Q33: =IF(AND(Q29>0,COUNTIF(Q29:AL29,"<=0")=0),Q$20,99) -> 99 | R33: =IF(AND(R29>0,COUNTIF(R29:AL29,"<=0")=0),R$20,99) -> 99 | S33: =IF(AND(S29>0,COUNTIF(S29:AL29,"<=0")=0),S$20,99) -> 99 | T33: =IF(AND(T29>0,COUNTIF(T29:AL29,"<=0")=0),T$20,99) -> 99 | U33: =IF(AND(U29>0,COUNTIF(U29:AL29,"<=0")=0),U$20,99) -> 99 | V33: =IF(AND(V29>0,COUNTIF(V29:AL29,"<=0")=0),V$20,99) -> 99 | W33: =IF(AND(W29>0,COUNTIF(W29:AL29,"<=0")=0),W$20,99) -> 99 | X33: =IF(AND(X29>0,COUNTIF(X29:AL29,"<=0")=0),X$20,99) -> 99 | Y33: =IF(AND(Y29>0,COUNTIF(Y29:AL29,"<=0")=0),Y$20,99) -> 99 | Z33: =IF(AND(Z29>0,COUNTIF(Z29:AL29,"<=0")=0),Z$20,99) -> 99 | AA33: =IF(AND(AA29>0,COUNTIF(AA29:AL29,"<=0")=0),AA$20,99) -> 99 | AB33: =IF(AND(AB29>0,COUNTIF(AB29:AL29,"<=0")=0),AB$20,99) -> 99 | AC33: =IF(AND(AC29>0,COUNTIF(AC29:AL29,"<=0")=0),AC$20,99) -> 99 | AD33: =IF(AND(AD29>0,COUNTIF(AD29:AL29,"<=0")=0),AD$20,99) -> 99 | AE33: =IF(AND(AE29>0,COUNTIF(AE29:AL29,"<=0")=0),AE$20,99) -> 99 | AF33: =IF(AND(AF29>0,COUNTIF(AF29:AL29,"<=0")=0),AF$20,99) -> 99 | AG33: =IF(AND(AG29>0,COUNTIF(AG29:AL29,"<=0")=0),AG$20,99) -> 99 | AH33: =IF(AND(AH29>0,COUNTIF(AH29:AL29,"<=0")=0),AH$20,99) -> 99 | AI33: =IF(AND(AI29>0,COUNTIF(AI29:AL29,"<=0")=0),AI$20,99) -> 99 | AJ33: =IF(AND(AJ29>0,COUNTIF(AJ29:AL29,"<=0")=0),AJ$20,99) -> 99 | AK33: =IF(AND(AK29>0,COUNTIF(AK29:AL29,"<=0")=0),AK$20,99) -> 99 | AL33: =IF(AND(AL29>0,COUNTIF(AL29:AL29,"<=0")=0),AL$20,99) -> 99
A34: pb_flag | B34: служебно: месяц окупаемости | C34: =IF(AND(C32>=0,COUNTIF(C32:AL32,"<0")=0),C$20,99) -> 99 | D34: =IF(AND(D32>=0,COUNTIF(D32:AL32,"<0")=0),D$20,99) -> 99 | E34: =IF(AND(E32>=0,COUNTIF(E32:AL32,"<0")=0),E$20,99) -> 99 | F34: =IF(AND(F32>=0,COUNTIF(F32:AL32,"<0")=0),F$20,99) -> 99 | G34: =IF(AND(G32>=0,COUNTIF(G32:AL32,"<0")=0),G$20,99) -> 99 | H34: =IF(AND(H32>=0,COUNTIF(H32:AL32,"<0")=0),H$20,99) -> 99 | I34: =IF(AND(I32>=0,COUNTIF(I32:AL32,"<0")=0),I$20,99) -> 99 | J34: =IF(AND(J32>=0,COUNTIF(J32:AL32,"<0")=0),J$20,99) -> 99 | K34: =IF(AND(K32>=0,COUNTIF(K32:AL32,"<0")=0),K$20,99) -> 99 | L34: =IF(AND(L32>=0,COUNTIF(L32:AL32,"<0")=0),L$20,99) -> 99 | M34: =IF(AND(M32>=0,COUNTIF(M32:AL32,"<0")=0),M$20,99) -> 99 | N34: =IF(AND(N32>=0,COUNTIF(N32:AL32,"<0")=0),N$20,99) -> 99 | O34: =IF(AND(O32>=0,COUNTIF(O32:AL32,"<0")=0),O$20,99) -> 99 | P34: =IF(AND(P32>=0,COUNTIF(P32:AL32,"<0")=0),P$20,99) -> 99 | Q34: =IF(AND(Q32>=0,COUNTIF(Q32:AL32,"<0")=0),Q$20,99) -> 99 | R34: =IF(AND(R32>=0,COUNTIF(R32:AL32,"<0")=0),R$20,99) -> 99 | S34: =IF(AND(S32>=0,COUNTIF(S32:AL32,"<0")=0),S$20,99) -> 99 | T34: =IF(AND(T32>=0,COUNTIF(T32:AL32,"<0")=0),T$20,99) -> 99 | U34: =IF(AND(U32>=0,COUNTIF(U32:AL32,"<0")=0),U$20,99) -> 99 | V34: =IF(AND(V32>=0,COUNTIF(V32:AL32,"<0")=0),V$20,99) -> 99 | W34: =IF(AND(W32>=0,COUNTIF(W32:AL32,"<0")=0),W$20,99) -> 99 | X34: =IF(AND(X32>=0,COUNTIF(X32:AL32,"<0")=0),X$20,99) -> 99 | Y34: =IF(AND(Y32>=0,COUNTIF(Y32:AL32,"<0")=0),Y$20,99) -> 99 | Z34: =IF(AND(Z32>=0,COUNTIF(Z32:AL32,"<0")=0),Z$20,99) -> 99 | AA34: =IF(AND(AA32>=0,COUNTIF(AA32:AL32,"<0")=0),AA$20,99) -> 99 | AB34: =IF(AND(AB32>=0,COUNTIF(AB32:AL32,"<0")=0),AB$20,99) -> 99 | AC34: =IF(AND(AC32>=0,COUNTIF(AC32:AL32,"<0")=0),AC$20,99) -> 99 | AD34: =IF(AND(AD32>=0,COUNTIF(AD32:AL32,"<0")=0),AD$20,99) -> 99 | AE34: =IF(AND(AE32>=0,COUNTIF(AE32:AL32,"<0")=0),AE$20,99) -> 99 | AF34: =IF(AND(AF32>=0,COUNTIF(AF32:AL32,"<0")=0),AF$20,99) -> 99 | AG34: =IF(AND(AG32>=0,COUNTIF(AG32:AL32,"<0")=0),AG$20,99) -> 99 | AH34: =IF(AND(AH32>=0,COUNTIF(AH32:AL32,"<0")=0),AH$20,99) -> 99 | AI34: =IF(AND(AI32>=0,COUNTIF(AI32:AL32,"<0")=0),AI$20,99) -> 99 | AJ34: =IF(AND(AJ32>=0,COUNTIF(AJ32:AL32,"<0")=0),AJ$20,99) -> 99 | AK34: =IF(AND(AK32>=0,COUNTIF(AK32:AL32,"<0")=0),AK$20,99) -> 99 | AL34: =IF(AND(AL32>=0,COUNTIF(AL32:AL32,"<0")=0),AL$20,99) -> 99
A36: Сценарий: Оптимистичный | B36: Месяц → | C36: 1 | D36: 2 | E36: 3 | F36: 4 | G36: 5 | H36: 6 | I36: 7 | J36: 8 | K36: 9 | L36: 10 | M36: 11 | N36: 12 | O36: 13 | P36: 14 | Q36: 15 | R36: 16 | S36: 17 | T36: 18 | U36: 19 | V36: 20 | W36: 21 | X36: 22 | Y36: 23 | Z36: 24 | AA36: 25 | AB36: 26 | AC36: 27 | AD36: 28 | AE36: 29 | AF36: 30 | AG36: 31 | AH36: 32 | AI36: 33 | AJ36: 34 | AK36: 35 | AL36: 36 | AM36: Год 1 | AN36: Год 2 | AO36: Год 3 | AP36: Итого 36 мес
A37: contribA | B37: Маржинальный доход A (коммерция, РСЯ, TG) | C37: =A_дропшиппинг!C54 -> 0 | D37: =A_дропшиппинг!D54 -> 30124.326 | E37: =A_дропшиппинг!E54 -> 64572.907 | F37: =A_дропшиппинг!F54 -> 100867.38 | G37: =A_дропшиппинг!G54 -> 138415.06 | H37: =A_дропшиппинг!H54 -> 176923.02 | I37: =A_дропшиппинг!I54 -> 216213.95 | J37: =A_дропшиппинг!J54 -> 284401.34 | ... AL37: =A_дропшиппинг!AL54 -> 1670316 | AM37: =SUM(C37:N37) -> 2604502.4 | AN37: =SUM(O37:Z37) -> 9370975.8 | AO37: =SUM(AA37:AL37) -> 16620243 | AP37: =SUM(C37:AL37) -> 28595721
A38: warm | B38: Тёплая база (TG + email/VK) | C38: =A_дропшиппинг!C46*(1+Допущения!$E$34) -> 0 | D38: =A_дропшиппинг!D46*(1+Допущения!$E$34) -> 2402.7379 | E38: =A_дропшиппинг!E46*(1+Допущения!$E$34) -> 5150.3814 | F38: =A_дропшиппинг!F46*(1+Допущения!$E$34) -> 8045.2543 | G38: =A_дропшиппинг!G46*(1+Допущения!$E$34) -> 11040.084 | H38: =A_дропшиппинг!H46*(1+Допущения!$E$34) -> 14111.507 | I38: =A_дропшиппинг!I46*(1+Допущения!$E$34) -> 17245.38 | J38: =A_дропшиппинг!J46*(1+Допущения!$E$34) -> 20432.158 | ... AL38: =A_дропшиппинг!AL46*(1+Допущения!$E$34) -> 120000 | AM38: =N38 -> 33592.193 | AN38: =Z38 -> 75614.836 | AO38: =AL38 -> 120000
A39: course | B39: Выручка курсов (сглажено по месяцам) | C39: =IF(C$36>=Допущения!$E$30,C38*Допущения!$E$33*Допущения!$E$31*Допущения!$E$32/12,0) -> 0 | D39: =IF(D$36>=Допущения!$E$30,D38*Допущения!$E$33*Допущения!$E$31*Допущения!$E$32/12,0) -> 0 | E39: =IF(E$36>=Допущения!$E$30,E38*Допущения!$E$33*Допущения!$E$31*Допущения!$E$32/12,0) -> 0 | F39: =IF(F$36>=Допущения!$E$30,F38*Допущения!$E$33*Допущения!$E$31*Допущения!$E$32/12,0) -> 0 | G39: =IF(G$36>=Допущения!$E$30,G38*Допущения!$E$33*Допущения!$E$31*Допущения!$E$32/12,0) -> 0 | H39: =IF(H$36>=Допущения!$E$30,H38*Допущения!$E$33*Допущения!$E$31*Допущения!$E$32/12,0) -> 0 | I39: =IF(I$36>=Допущения!$E$30,I38*Допущения!$E$33*Допущения!$E$31*Допущения!$E$32/12,0) -> 403541.9 | J39: =IF(J$36>=Допущения!$E$30,J38*Допущения!$E$33*Допущения!$E$31*Допущения!$E$32/12,0) -> 478112.5 | ... AL39: =IF(AL$36>=Допущения!$E$30,AL38*Допущения!$E$33*Допущения!$E$31*Допущения!$E$32/12,0) -> 2808000 | AM39: =SUM(C39:N39) -> 3559650.9 | AN39: =SUM(O39:Z39) -> 15753726 | AO39: =SUM(AA39:AL39) -> 27940606 | AP39: =SUM(C39:AL39) -> 47253983
A40: club | B40: Выручка клуба | C40: =IF(C$36>=Допущения!$E$30,C38*Допущения!$E$36*Допущения!$E$35,0) -> 0 | D40: =IF(D$36>=Допущения!$E$30,D38*Допущения!$E$36*Допущения!$E$35,0) -> 0 | E40: =IF(E$36>=Допущения!$E$30,E38*Допущения!$E$36*Допущения!$E$35,0) -> 0 | F40: =IF(F$36>=Допущения!$E$30,F38*Допущения!$E$36*Допущения!$E$35,0) -> 0 | G40: =IF(G$36>=Допущения!$E$30,G38*Допущения!$E$36*Допущения!$E$35,0) -> 0 | H40: =IF(H$36>=Допущения!$E$30,H38*Допущения!$E$36*Допущения!$E$35,0) -> 0 | I40: =IF(I$36>=Допущения!$E$30,I38*Допущения!$E$36*Допущения!$E$35,0) -> 126753.54 | J40: =IF(J$36>=Допущения!$E$30,J38*Допущения!$E$36*Допущения!$E$35,0) -> 150176.36 | ... AL40: =IF(AL$36>=Допущения!$E$30,AL38*Допущения!$E$36*Допущения!$E$35,0) -> 882000 | AM40: =SUM(C40:N40) -> 1118095.5 | AN40: =SUM(O40:Z40) -> 4948285.6 | AO40: =SUM(AA40:AL40) -> 8776216.1 | AP40: =SUM(C40:AL40) -> 14842597
A41: rev | B41: Выручка платных продуктов | C41: =C39+C40 -> 0 | D41: =D39+D40 -> 0 | E41: =E39+E40 -> 0 | F41: =F39+F40 -> 0 | G41: =G39+G40 -> 0 | H41: =H39+H40 -> 0 | I41: =I39+I40 -> 530295.44 | J41: =J39+J40 -> 628288.86 | ... AL41: =AL39+AL40 -> 3690000 | AM41: =SUM(C41:N41) -> 4677746.3 | AN41: =SUM(O41:Z41) -> 20702011 | AO41: =SUM(AA41:AL41) -> 36716823 | AP41: =SUM(C41:AL41) -> 62096580
A42: contrib | B42: Маржинальный доход (A + продукты − комиссии, реклама запусков, налог) | C42: =C37+C41*(1-Допущения!$E$37-Допущения!$E$14)-C39*Допущения!$E$38 -> 0 | D42: =D37+D41*(1-Допущения!$E$37-Допущения!$E$14)-D39*Допущения!$E$38 -> 30124.326 | E42: =E37+E41*(1-Допущения!$E$37-Допущения!$E$14)-E39*Допущения!$E$38 -> 64572.907 | F42: =F37+F41*(1-Допущения!$E$37-Допущения!$E$14)-F39*Допущения!$E$38 -> 100867.38 | G42: =G37+G41*(1-Допущения!$E$37-Допущения!$E$14)-G39*Допущения!$E$38 -> 138415.06 | H42: =H37+H41*(1-Допущения!$E$37-Допущения!$E$14)-H39*Допущения!$E$38 -> 176923.02 | I42: =I37+I41*(1-Допущения!$E$37-Допущения!$E$14)-I39*Допущения!$E$38 -> 611736.75 | J42: =J37+J41*(1-Допущения!$E$37-Допущения!$E$14)-J39*Допущения!$E$38 -> 753012.89 | ... AL42: =AL37+AL41*(1-Допущения!$E$37-Допущения!$E$14)-AL39*Допущения!$E$38 -> 4422516 | AM42: =SUM(C42:N42) -> 6093416.6 | AN42: =SUM(O42:Z42) -> 24811647 | AO42: =SUM(AA42:AL42) -> 44005619 | AP42: =SUM(C42:AL42) -> 74910683
A43: acq | B43: Покупка подписчиков Telegram | C43: =A_дропшиппинг!C55 -> 0 | D43: =A_дропшиппинг!D55 -> 48054.758 | E43: =A_дропшиппинг!E55 -> 54952.871 | F43: =A_дропшиппинг!F55 -> 57897.458 | G43: =A_дропшиппинг!G55 -> 59896.599 | H43: =A_дропшиппинг!H55 -> 61428.459 | I43: =A_дропшиппинг!I55 -> 62677.459 | J43: =A_дропшиппинг!J55 -> 63735.559 | ... AL43: =A_дропшиппинг!AL55 -> 75319.88 | AM43: =SUM(C43:N43) -> 671843.85 | AN43: =SUM(O43:Z43) -> 840452.88 | AO43: =SUM(AA43:AL43) -> 887703.27 | AP43: =SUM(C43:AL43) -> 2400000
A44: fixed | B44: Постоянные расходы (команда) | C44: =Допущения!$E$16+IF(C$36>=Допущения!$E$30-1,Допущения!$E$39,0) -> 360000 | D44: =Допущения!$E$16+IF(D$36>=Допущения!$E$30-1,Допущения!$E$39,0) -> 360000 | E44: =Допущения!$E$16+IF(E$36>=Допущения!$E$30-1,Допущения!$E$39,0) -> 360000 | F44: =Допущения!$E$16+IF(F$36>=Допущения!$E$30-1,Допущения!$E$39,0) -> 360000 | G44: =Допущения!$E$16+IF(G$36>=Допущения!$E$30-1,Допущения!$E$39,0) -> 360000 | H44: =Допущения!$E$16+IF(H$36>=Допущения!$E$30-1,Допущения!$E$39,0) -> 440000 | I44: =Допущения!$E$16+IF(I$36>=Допущения!$E$30-1,Допущения!$E$39,0) -> 440000 | J44: =Допущения!$E$16+IF(J$36>=Допущения!$E$30-1,Допущения!$E$39,0) -> 440000 | ... AL44: =Допущения!$E$16+IF(AL$36>=Допущения!$E$30-1,Допущения!$E$39,0) -> 440000 | AM44: =SUM(C44:N44) -> 4880000 | AN44: =SUM(O44:Z44) -> 5280000 | AO44: =SUM(AA44:AL44) -> 5280000 | AP44: =SUM(C44:AL44) -> 15440000
A45: op | B45: Операционная прибыль (маржинальный доход − постоянные − привлечение) | C45: =C42-C44-C43 -> -360000 | D45: =D42-D44-D43 -> -377930.43 | E45: =E42-E44-E43 -> -350379.96 | F45: =F42-F44-F43 -> -317030.08 | G45: =G42-G44-G43 -> -281481.54 | H45: =H42-H44-H43 -> -324505.44 | I45: =I42-I44-I43 -> 109059.29 | J45: =J42-J44-J43 -> 249277.33 | ... AL45: =AL42-AL44-AL43 -> 3907196.1 | AM45: =SUM(C45:N45) -> 541572.79 | AN45: =SUM(O45:Z45) -> 18691194 | AO45: =SUM(AA45:AL45) -> 37837916 | AP45: =SUM(C45:AL45) -> 57070683
A46: capex | B46: CAPEX и вложения в оборотку | C46: =IF(C$36=1,Допущения!$E$18,0)+IF(AND(C$36>=Допущения!$E$30-3,C$36<Допущения!$E$30),Допущения!$E$40/3,0) -> 300000 | D46: =IF(D$36=1,Допущения!$E$18,0)+IF(AND(D$36>=Допущения!$E$30-3,D$36<Допущения!$E$30),Допущения!$E$40/3,0) -> 0 | E46: =IF(E$36=1,Допущения!$E$18,0)+IF(AND(E$36>=Допущения!$E$30-3,E$36<Допущения!$E$30),Допущения!$E$40/3,0) -> 0 | F46: =IF(F$36=1,Допущения!$E$18,0)+IF(AND(F$36>=Допущения!$E$30-3,F$36<Допущения!$E$30),Допущения!$E$40/3,0) -> 200000 | G46: =IF(G$36=1,Допущения!$E$18,0)+IF(AND(G$36>=Допущения!$E$30-3,G$36<Допущения!$E$30),Допущения!$E$40/3,0) -> 200000 | H46: =IF(H$36=1,Допущения!$E$18,0)+IF(AND(H$36>=Допущения!$E$30-3,H$36<Допущения!$E$30),Допущения!$E$40/3,0) -> 200000 | I46: =IF(I$36=1,Допущения!$E$18,0)+IF(AND(I$36>=Допущения!$E$30-3,I$36<Допущения!$E$30),Допущения!$E$40/3,0) -> 0 | J46: =IF(J$36=1,Допущения!$E$18,0)+IF(AND(J$36>=Допущения!$E$30-3,J$36<Допущения!$E$30),Допущения!$E$40/3,0) -> 0 | ... AL46: =IF(AL$36=1,Допущения!$E$18,0)+IF(AND(AL$36>=Допущения!$E$30-3,AL$36<Допущения!$E$30),Допущения!$E$40/3,0) -> 0 | AM46: =SUM(C46:N46) -> 900000 | AN46: =SUM(O46:Z46) -> 0 | AO46: =SUM(AA46:AL46) -> 0 | AP46: =SUM(C46:AL46) -> 900000
A47: cf | B47: Денежный поток | C47: =C45-C46 -> -660000 | D47: =D45-D46 -> -377930.43 | E47: =E45-E46 -> -350379.96 | F47: =F45-F46 -> -517030.08 | G47: =G45-G46 -> -481481.54 | H47: =H45-H46 -> -524505.44 | I47: =I45-I46 -> 109059.29 | J47: =J45-J46 -> 249277.33 | ... AL47: =AL45-AL46 -> 3907196.1 | AM47: =SUM(C47:N47) -> -358427.21 | AN47: =SUM(O47:Z47) -> 18691194 | AO47: =SUM(AA47:AL47) -> 37837916 | AP47: =SUM(C47:AL47) -> 56170683
A48: cum | B48: Накопленный денежный поток | C48: =0+C47 -> -660000 | D48: =C48+D47 -> -1037930.4 | E48: =D48+E47 -> -1388310.4 | F48: =E48+F47 -> -1905340.5 | G48: =F48+G47 -> -2386822 | H48: =G48+H47 -> -2911327.5 | I48: =H48+I47 -> -2802268.2 | J48: =I48+J47 -> -2552990.8 | K48: =J48+K47 -> -2185491.7 | ... AL48: =AK48+AL47 -> 56170683 | AM48: =N48 -> -358427.21 | AN48: =Z48 -> 18332767 | AO48: =AL48 -> 56170683
A49: be_flag | B49: служебно: месяц устойчивой опер. прибыли | C49: =IF(AND(C45>0,COUNTIF(C45:AL45,"<=0")=0),C$36,99) -> 99 | D49: =IF(AND(D45>0,COUNTIF(D45:AL45,"<=0")=0),D$36,99) -> 99 | E49: =IF(AND(E45>0,COUNTIF(E45:AL45,"<=0")=0),E$36,99) -> 99 | F49: =IF(AND(F45>0,COUNTIF(F45:AL45,"<=0")=0),F$36,99) -> 99 | G49: =IF(AND(G45>0,COUNTIF(G45:AL45,"<=0")=0),G$36,99) -> 99 | H49: =IF(AND(H45>0,COUNTIF(H45:AL45,"<=0")=0),H$36,99) -> 99 | I49: =IF(AND(I45>0,COUNTIF(I45:AL45,"<=0")=0),I$36,99) -> 7 | J49: =IF(AND(J45>0,COUNTIF(J45:AL45,"<=0")=0),J$36,99) -> 8 | K49: =IF(AND(K45>0,COUNTIF(K45:AL45,"<=0")=0),K$36,99) -> 9 | L49: =IF(AND(L45>0,COUNTIF(L45:AL45,"<=0")=0),L$36,99) -> 10 | M49: =IF(AND(M45>0,COUNTIF(M45:AL45,"<=0")=0),M$36,99) -> 11 | N49: =IF(AND(N45>0,COUNTIF(N45:AL45,"<=0")=0),N$36,99) -> 12 | O49: =IF(AND(O45>0,COUNTIF(O45:AL45,"<=0")=0),O$36,99) -> 13 | P49: =IF(AND(P45>0,COUNTIF(P45:AL45,"<=0")=0),P$36,99) -> 14 | Q49: =IF(AND(Q45>0,COUNTIF(Q45:AL45,"<=0")=0),Q$36,99) -> 15 | R49: =IF(AND(R45>0,COUNTIF(R45:AL45,"<=0")=0),R$36,99) -> 16 | S49: =IF(AND(S45>0,COUNTIF(S45:AL45,"<=0")=0),S$36,99) -> 17 | T49: =IF(AND(T45>0,COUNTIF(T45:AL45,"<=0")=0),T$36,99) -> 18 | U49: =IF(AND(U45>0,COUNTIF(U45:AL45,"<=0")=0),U$36,99) -> 19 | V49: =IF(AND(V45>0,COUNTIF(V45:AL45,"<=0")=0),V$36,99) -> 20 | W49: =IF(AND(W45>0,COUNTIF(W45:AL45,"<=0")=0),W$36,99) -> 21 | X49: =IF(AND(X45>0,COUNTIF(X45:AL45,"<=0")=0),X$36,99) -> 22 | Y49: =IF(AND(Y45>0,COUNTIF(Y45:AL45,"<=0")=0),Y$36,99) -> 23 | Z49: =IF(AND(Z45>0,COUNTIF(Z45:AL45,"<=0")=0),Z$36,99) -> 24 | AA49: =IF(AND(AA45>0,COUNTIF(AA45:AL45,"<=0")=0),AA$36,99) -> 25 | AB49: =IF(AND(AB45>0,COUNTIF(AB45:AL45,"<=0")=0),AB$36,99) -> 26 | AC49: =IF(AND(AC45>0,COUNTIF(AC45:AL45,"<=0")=0),AC$36,99) -> 27 | AD49: =IF(AND(AD45>0,COUNTIF(AD45:AL45,"<=0")=0),AD$36,99) -> 28 | AE49: =IF(AND(AE45>0,COUNTIF(AE45:AL45,"<=0")=0),AE$36,99) -> 29 | AF49: =IF(AND(AF45>0,COUNTIF(AF45:AL45,"<=0")=0),AF$36,99) -> 30 | AG49: =IF(AND(AG45>0,COUNTIF(AG45:AL45,"<=0")=0),AG$36,99) -> 31 | AH49: =IF(AND(AH45>0,COUNTIF(AH45:AL45,"<=0")=0),AH$36,99) -> 32 | AI49: =IF(AND(AI45>0,COUNTIF(AI45:AL45,"<=0")=0),AI$36,99) -> 33 | AJ49: =IF(AND(AJ45>0,COUNTIF(AJ45:AL45,"<=0")=0),AJ$36,99) -> 34 | AK49: =IF(AND(AK45>0,COUNTIF(AK45:AL45,"<=0")=0),AK$36,99) -> 35 | AL49: =IF(AND(AL45>0,COUNTIF(AL45:AL45,"<=0")=0),AL$36,99) -> 36
A50: pb_flag | B50: служебно: месяц окупаемости | C50: =IF(AND(C48>=0,COUNTIF(C48:AL48,"<0")=0),C$36,99) -> 99 | D50: =IF(AND(D48>=0,COUNTIF(D48:AL48,"<0")=0),D$36,99) -> 99 | E50: =IF(AND(E48>=0,COUNTIF(E48:AL48,"<0")=0),E$36,99) -> 99 | F50: =IF(AND(F48>=0,COUNTIF(F48:AL48,"<0")=0),F$36,99) -> 99 | G50: =IF(AND(G48>=0,COUNTIF(G48:AL48,"<0")=0),G$36,99) -> 99 | H50: =IF(AND(H48>=0,COUNTIF(H48:AL48,"<0")=0),H$36,99) -> 99 | I50: =IF(AND(I48>=0,COUNTIF(I48:AL48,"<0")=0),I$36,99) -> 99 | J50: =IF(AND(J48>=0,COUNTIF(J48:AL48,"<0")=0),J$36,99) -> 99 | K50: =IF(AND(K48>=0,COUNTIF(K48:AL48,"<0")=0),K$36,99) -> 99 | L50: =IF(AND(L48>=0,COUNTIF(L48:AL48,"<0")=0),L$36,99) -> 99 | M50: =IF(AND(M48>=0,COUNTIF(M48:AL48,"<0")=0),M$36,99) -> 99 | N50: =IF(AND(N48>=0,COUNTIF(N48:AL48,"<0")=0),N$36,99) -> 99 | O50: =IF(AND(O48>=0,COUNTIF(O48:AL48,"<0")=0),O$36,99) -> 13 | P50: =IF(AND(P48>=0,COUNTIF(P48:AL48,"<0")=0),P$36,99) -> 14 | Q50: =IF(AND(Q48>=0,COUNTIF(Q48:AL48,"<0")=0),Q$36,99) -> 15 | R50: =IF(AND(R48>=0,COUNTIF(R48:AL48,"<0")=0),R$36,99) -> 16 | S50: =IF(AND(S48>=0,COUNTIF(S48:AL48,"<0")=0),S$36,99) -> 17 | T50: =IF(AND(T48>=0,COUNTIF(T48:AL48,"<0")=0),T$36,99) -> 18 | U50: =IF(AND(U48>=0,COUNTIF(U48:AL48,"<0")=0),U$36,99) -> 19 | V50: =IF(AND(V48>=0,COUNTIF(V48:AL48,"<0")=0),V$36,99) -> 20 | W50: =IF(AND(W48>=0,COUNTIF(W48:AL48,"<0")=0),W$36,99) -> 21 | X50: =IF(AND(X48>=0,COUNTIF(X48:AL48,"<0")=0),X$36,99) -> 22 | Y50: =IF(AND(Y48>=0,COUNTIF(Y48:AL48,"<0")=0),Y$36,99) -> 23 | Z50: =IF(AND(Z48>=0,COUNTIF(Z48:AL48,"<0")=0),Z$36,99) -> 24 | AA50: =IF(AND(AA48>=0,COUNTIF(AA48:AL48,"<0")=0),AA$36,99) -> 25 | AB50: =IF(AND(AB48>=0,COUNTIF(AB48:AL48,"<0")=0),AB$36,99) -> 26 | AC50: =IF(AND(AC48>=0,COUNTIF(AC48:AL48,"<0")=0),AC$36,99) -> 27 | AD50: =IF(AND(AD48>=0,COUNTIF(AD48:AL48,"<0")=0),AD$36,99) -> 28 | AE50: =IF(AND(AE48>=0,COUNTIF(AE48:AL48,"<0")=0),AE$36,99) -> 29 | AF50: =IF(AND(AF48>=0,COUNTIF(AF48:AL48,"<0")=0),AF$36,99) -> 30 | AG50: =IF(AND(AG48>=0,COUNTIF(AG48:AL48,"<0")=0),AG$36,99) -> 31 | AH50: =IF(AND(AH48>=0,COUNTIF(AH48:AL48,"<0")=0),AH$36,99) -> 32 | AI50: =IF(AND(AI48>=0,COUNTIF(AI48:AL48,"<0")=0),AI$36,99) -> 33 | AJ50: =IF(AND(AJ48>=0,COUNTIF(AJ48:AL48,"<0")=0),AJ$36,99) -> 34 | AK50: =IF(AND(AK48>=0,COUNTIF(AK48:AL48,"<0")=0),AK$36,99) -> 35 | AL50: =IF(AND(AL48>=0,COUNTIF(AL48:AL48,"<0")=0),AL$36,99) -> 36

Sheet B_свой_бренд
A1: B. Private label: свой бренд детского текстиля на Ozon (контент — поддержка, а не двигатель)
A2: Запас: не меньше тиража (100 шт на SKU) либо B_inv месяцев продаж. Вложения в запас идут в CAPEX-строку.
A4: Сценарий: Осторожный | B4: Месяц → | C4: 1 | D4: 2 | E4: 3 | F4: 4 | G4: 5 | H4: 6 | I4: 7 | J4: 8 | K4: 9 | L4: 10 | M4: 11 | N4: 12 | O4: 13 | P4: 14 | Q4: 15 | R4: 16 | S4: 17 | T4: 18 | U4: 19 | V4: 20 | W4: 21 | X4: 22 | Y4: 23 | Z4: 24 | AA4: 25 | AB4: 26 | AC4: 27 | AD4: 28 | AE4: 29 | AF4: 30 | AG4: 31 | AH4: 32 | AI4: 33 | AJ4: 34 | AK4: 35 | AL4: 36 | AM4: Год 1 | AN4: Год 2 | AO4: Год 3 | AP4: Итого 36 мес
A5: units | B5: Продажи, шт | C5: =Допущения!$C$43*Допущения!$C$44*IF(C$4<Допущения!$C$42,0,((C$4-Допущения!$C$42+1)/(36-Допущения!$C$42+1))^Допущения!$C$56) -> 0 | D5: =Допущения!$C$43*Допущения!$C$44*IF(D$4<Допущения!$C$42,0,((D$4-Допущения!$C$42+1)/(36-Допущения!$C$42+1))^Допущения!$C$56) -> 0 | E5: =Допущения!$C$43*Допущения!$C$44*IF(E$4<Допущения!$C$42,0,((E$4-Допущения!$C$42+1)/(36-Допущения!$C$42+1))^Допущения!$C$56) -> 0 | F5: =Допущения!$C$43*Допущения!$C$44*IF(F$4<Допущения!$C$42,0,((F$4-Допущения!$C$42+1)/(36-Допущения!$C$42+1))^Допущения!$C$56) -> 0 | G5: =Допущения!$C$43*Допущения!$C$44*IF(G$4<Допущения!$C$42,0,((G$4-Допущения!$C$42+1)/(36-Допущения!$C$42+1))^Допущения!$C$56) -> 9.375 | H5: =Допущения!$C$43*Допущения!$C$44*IF(H$4<Допущения!$C$42,0,((H$4-Допущения!$C$42+1)/(36-Допущения!$C$42+1))^Допущения!$C$56) -> 21.538094 | I5: =Допущения!$C$43*Допущения!$C$44*IF(I$4<Допущения!$C$42,0,((I$4-Допущения!$C$42+1)/(36-Допущения!$C$42+1))^Допущения!$C$56) -> 35.036183 | J5: =Допущения!$C$43*Допущения!$C$44*IF(J$4<Допущения!$C$42,0,((J$4-Допущения!$C$42+1)/(36-Допущения!$C$42+1))^Допущения!$C$56) -> 49.481547 | ... AL5: =Допущения!$C$43*Допущения!$C$44*IF(AL$4<Допущения!$C$42,0,((AL$4-Допущения!$C$42+1)/(36-Допущения!$C$42+1))^Допущения!$C$56) -> 600 | AM5: =SUM(C5:N5) -> 471.12402 | AN5: =SUM(O5:Z5) -> 2803.9815 | AO5: =SUM(AA5:AL5) -> 5753.5286 | AP5: =SUM(C5:AL5) -> 9028.6341
A6: rev | B6: Выручка на Ozon, ₽ | C6: =C5*Допущения!$C$45 -> 0 | D6: =D5*Допущения!$C$45 -> 0 | E6: =E5*Допущения!$C$45 -> 0 | F6: =F5*Допущения!$C$45 -> 0 | G6: =G5*Допущения!$C$45 -> 15937.5 | H6: =H5*Допущения!$C$45 -> 36614.76 | I6: =I5*Допущения!$C$45 -> 59561.511 | J6: =J5*Допущения!$C$45 -> 84118.629 | ... AL6: =AL5*Допущения!$C$45 -> 1020000 | AM6: =SUM(C6:N6) -> 800910.83 | AN6: =SUM(O6:Z6) -> 4766768.5 | AO6: =SUM(AA6:AL6) -> 9780998.6 | AP6: =SUM(C6:AL6) -> 15348678
A7: unit_cm | B7: Маржа на единицу, ₽ | C7: =Допущения!$C$45*(1-Допущения!$C$47-Допущения!$C$46-Допущения!$C$49-Допущения!$C$50-Допущения!$C$52)-Допущения!$C$48-Допущения!$C$51 -> -205 | D7: =Допущения!$C$45*(1-Допущения!$C$47-Допущения!$C$46-Допущения!$C$49-Допущения!$C$50-Допущения!$C$52)-Допущения!$C$48-Допущения!$C$51 -> -205 | E7: =Допущения!$C$45*(1-Допущения!$C$47-Допущения!$C$46-Допущения!$C$49-Допущения!$C$50-Допущения!$C$52)-Допущения!$C$48-Допущения!$C$51 -> -205 | F7: =Допущения!$C$45*(1-Допущения!$C$47-Допущения!$C$46-Допущения!$C$49-Допущения!$C$50-Допущения!$C$52)-Допущения!$C$48-Допущения!$C$51 -> -205 | G7: =Допущения!$C$45*(1-Допущения!$C$47-Допущения!$C$46-Допущения!$C$49-Допущения!$C$50-Допущения!$C$52)-Допущения!$C$48-Допущения!$C$51 -> -205 | H7: =Допущения!$C$45*(1-Допущения!$C$47-Допущения!$C$46-Допущения!$C$49-Допущения!$C$50-Допущения!$C$52)-Допущения!$C$48-Допущения!$C$51 -> -205 | I7: =Допущения!$C$45*(1-Допущения!$C$47-Допущения!$C$46-Допущения!$C$49-Допущения!$C$50-Допущения!$C$52)-Допущения!$C$48-Допущения!$C$51 -> -205 | J7: =Допущения!$C$45*(1-Допущения!$C$47-Допущения!$C$46-Допущения!$C$49-Допущения!$C$50-Допущения!$C$52)-Допущения!$C$48-Допущения!$C$51 -> -205 | ... AL7: =Допущения!$C$45*(1-Допущения!$C$47-Допущения!$C$46-Допущения!$C$49-Допущения!$C$50-Допущения!$C$52)-Допущения!$C$48-Допущения!$C$51 -> -205 | AM7: =N7 -> -205 | AN7: =Z7 -> -205 | AO7: =AL7 -> -205
A8: contrib | B8: Маржинальный доход | C8: =C5*C7 -> 0 | D8: =D5*D7 -> 0 | E8: =E5*E7 -> 0 | F8: =F5*F7 -> 0 | G8: =G5*G7 -> -1921.875 | H8: =H5*H7 -> -4415.3093 | I8: =I5*I7 -> -7182.4174 | J8: =J5*J7 -> -10143.717 | ... AL8: =AL5*AL7 -> -123000 | AM8: =SUM(C8:N8) -> -96580.424 | AN8: =SUM(O8:Z8) -> -574816.2 | AO8: =SUM(AA8:AL8) -> -1179473.4 | AP8: =SUM(C8:AL8) -> -1850870
A9: acq | B9: Внешнее привлечение (учтено в ДРР) | C9: =0 -> 0 | D9: =0 -> 0 | E9: =0 -> 0 | F9: =0 -> 0 | G9: =0 -> 0 | H9: =0 -> 0 | I9: =0 -> 0 | J9: =0 -> 0 | ... AL9: =0 -> 0 | AM9: =SUM(C9:N9) -> 0 | AN9: =SUM(O9:Z9) -> 0 | AO9: =SUM(AA9:AL9) -> 0 | AP9: =SUM(C9:AL9) -> 0
A10: sku | B10: Активных SKU | C10: =IF(C$4>=Допущения!$C$42-1,MAX(5,ROUNDUP(Допущения!$C$43*IF(C$4<Допущения!$C$42,0,((C$4-Допущения!$C$42+1)/(36-Допущения!$C$42+1))^1),0)),0) -> 0 | D10: =IF(D$4>=Допущения!$C$42-1,MAX(5,ROUNDUP(Допущения!$C$43*IF(D$4<Допущения!$C$42,0,((D$4-Допущения!$C$42+1)/(36-Допущения!$C$42+1))^1),0)),0) -> 0 | E10: =IF(E$4>=Допущения!$C$42-1,MAX(5,ROUNDUP(Допущения!$C$43*IF(E$4<Допущения!$C$42,0,((E$4-Допущения!$C$42+1)/(36-Допущения!$C$42+1))^1),0)),0) -> 0 | F10: =IF(F$4>=Допущения!$C$42-1,MAX(5,ROUNDUP(Допущения!$C$43*IF(F$4<Допущения!$C$42,0,((F$4-Допущения!$C$42+1)/(36-Допущения!$C$42+1))^1),0)),0) -> 5 | G10: =IF(G$4>=Допущения!$C$42-1,MAX(5,ROUNDUP(Допущения!$C$43*IF(G$4<Допущения!$C$42,0,((G$4-Допущения!$C$42+1)/(36-Допущения!$C$42+1))^1),0)),0) -> 5 | H10: =IF(H$4>=Допущения!$C$42-1,MAX(5,ROUNDUP(Допущения!$C$43*IF(H$4<Допущения!$C$42,0,((H$4-Допущения!$C$42+1)/(36-Допущения!$C$42+1))^1),0)),0) -> 5 | I10: =IF(I$4>=Допущения!$C$42-1,MAX(5,ROUNDUP(Допущения!$C$43*IF(I$4<Допущения!$C$42,0,((I$4-Допущения!$C$42+1)/(36-Допущения!$C$42+1))^1),0)),0) -> 5 | J10: =IF(J$4>=Допущения!$C$42-1,MAX(5,ROUNDUP(Допущения!$C$43*IF(J$4<Допущения!$C$42,0,((J$4-Допущения!$C$42+1)/(36-Допущения!$C$42+1))^1),0)),0) -> 5 | ... AL10: =IF(AL$4>=Допущения!$C$42-1,MAX(5,ROUNDUP(Допущения!$C$43*IF(AL$4<Допущения!$C$42,0,((AL$4-Допущения!$C$42+1)/(36-Допущения!$C$42+1))^1),0)),0) -> 15 | AM10: =N10 -> 5 | AN10: =Z10 -> 10 | AO10: =AL10 -> 15
A11: inv | B11: Запас на складе по себестоимости | C11: =IF(C$4>=Допущения!$C$42-1,MAX(C5*Допущения!$C$53,C10*100)*Допущения!$C$45*Допущения!$C$46,0) -> 0 | D11: =IF(D$4>=Допущения!$C$42-1,MAX(D5*Допущения!$C$53,D10*100)*Допущения!$C$45*Допущения!$C$46,0) -> 0 | E11: =IF(E$4>=Допущения!$C$42-1,MAX(E5*Допущения!$C$53,E10*100)*Допущения!$C$45*Допущения!$C$46,0) -> 0 | F11: =IF(F$4>=Допущения!$C$42-1,MAX(F5*Допущения!$C$53,F10*100)*Допущения!$C$45*Допущения!$C$46,0) -> 255000 | G11: =IF(G$4>=Допущения!$C$42-1,MAX(G5*Допущения!$C$53,G10*100)*Допущения!$C$45*Допущения!$C$46,0) -> 255000 | H11: =IF(H$4>=Допущения!$C$42-1,MAX(H5*Допущения!$C$53,H10*100)*Допущения!$C$45*Допущения!$C$46,0) -> 255000 | I11: =IF(I$4>=Допущения!$C$42-1,MAX(I5*Допущения!$C$53,I10*100)*Допущения!$C$45*Допущения!$C$46,0) -> 255000 | J11: =IF(J$4>=Допущения!$C$42-1,MAX(J5*Допущения!$C$53,J10*100)*Допущения!$C$45*Допущения!$C$46,0) -> 255000 | ... AL11: =IF(AL$4>=Допущения!$C$42-1,MAX(AL5*Допущения!$C$53,AL10*100)*Допущения!$C$45*Допущения!$C$46,0) -> 918000 | AM11: =N11 -> 255000 | AN11: =Z11 -> 522274.36 | AO11: =AL11 -> 918000
A12: fixed | B12: Постоянные расходы (команда) | C12: =Допущения!$C$54 -> 260000 | D12: =Допущения!$C$54 -> 260000 | E12: =Допущения!$C$54 -> 260000 | F12: =Допущения!$C$54 -> 260000 | G12: =Допущения!$C$54 -> 260000 | H12: =Допущения!$C$54 -> 260000 | I12: =Допущения!$C$54 -> 260000 | J12: =Допущения!$C$54 -> 260000 | ... AL12: =Допущения!$C$54 -> 260000 | AM12: =SUM(C12:N12) -> 3120000 | AN12: =SUM(O12:Z12) -> 3120000 | AO12: =SUM(AA12:AL12) -> 3120000 | AP12: =SUM(C12:AL12) -> 9360000
A13: op | B13: Операционная прибыль (маржинальный доход − постоянные − привлечение) | C13: =C8-C12-C9 -> -260000 | D13: =D8-D12-D9 -> -260000 | E13: =E8-E12-E9 -> -260000 | F13: =F8-F12-F9 -> -260000 | G13: =G8-G12-G9 -> -261921.88 | H13: =H8-H12-H9 -> -264415.31 | I13: =I8-I12-I9 -> -267182.42 | J13: =J8-J12-J9 -> -270143.72 | ... AL13: =AL8-AL12-AL9 -> -383000 | AM13: =SUM(C13:N13) -> -3216580.4 | AN13: =SUM(O13:Z13) -> -3694816.2 | AO13: =SUM(AA13:AL13) -> -4299473.4 | AP13: =SUM(C13:AL13) -> -11210870
A14: capex | B14: CAPEX и вложения в оборотку | C14: =IF(C$4<Допущения!$C$42,Допущения!$C$55/(Допущения!$C$42-1),0)+C11-0 -> 150000 | D14: =IF(D$4<Допущения!$C$42,Допущения!$C$55/(Допущения!$C$42-1),0)+D11-C11 -> 150000 | E14: =IF(E$4<Допущения!$C$42,Допущения!$C$55/(Допущения!$C$42-1),0)+E11-D11 -> 150000 | F14: =IF(F$4<Допущения!$C$42,Допущения!$C$55/(Допущения!$C$42-1),0)+F11-E11 -> 405000 | G14: =IF(G$4<Допущения!$C$42,Допущения!$C$55/(Допущения!$C$42-1),0)+G11-F11 -> 0 | H14: =IF(H$4<Допущения!$C$42,Допущения!$C$55/(Допущения!$C$42-1),0)+H11-G11 -> 0 | I14: =IF(I$4<Допущения!$C$42,Допущения!$C$55/(Допущения!$C$42-1),0)+I11-H11 -> 0 | J14: =IF(J$4<Допущения!$C$42,Допущения!$C$55/(Допущения!$C$42-1),0)+J11-I11 -> 0 | K14: =IF(K$4<Допущения!$C$42,Допущения!$C$55/(Допущения!$C$42-1),0)+K11-J11 -> 0 | ... AL14: =IF(AL$4<Допущения!$C$42,Допущения!$C$55/(Допущения!$C$42-1),0)+AL11-AK11 -> 34316.513 | AM14: =SUM(C14:N14) -> 855000 | AN14: =SUM(O14:Z14) -> 267274.36 | AO14: =SUM(AA14:AL14) -> 395725.64 | AP14: =SUM(C14:AL14) -> 1518000
A15: cf | B15: Денежный поток | C15: =C13-C14 -> -410000 | D15: =D13-D14 -> -410000 | E15: =E13-E14 -> -410000 | F15: =F13-F14 -> -665000 | G15: =G13-G14 -> -261921.88 | H15: =H13-H14 -> -264415.31 | I15: =I13-I14 -> -267182.42 | J15: =J13-J14 -> -270143.72 | ... AL15: =AL13-AL14 -> -417316.51 | AM15: =SUM(C15:N15) -> -4071580.4 | AN15: =SUM(O15:Z15) -> -3962090.6 | AO15: =SUM(AA15:AL15) -> -4695199 | AP15: =SUM(C15:AL15) -> -12728870
A16: cum | B16: Накопленный денежный поток | C16: =0+C15 -> -410000 | D16: =C16+D15 -> -820000 | E16: =D16+E15 -> -1230000 | F16: =E16+F15 -> -1895000 | G16: =F16+G15 -> -2156921.9 | H16: =G16+H15 -> -2421337.2 | I16: =H16+I15 -> -2688519.6 | J16: =I16+J15 -> -2958663.3 | K16: =J16+K15 -> -3231921.7 | ... AL16: =AK16+AL15 -> -12728870 | AM16: =N16 -> -4071580.4 | AN16: =Z16 -> -8033671 | AO16: =AL16 -> -12728870
A17: be_flag | B17: служебно: месяц устойчивой опер. прибыли | C17: =IF(AND(C13>0,COUNTIF(C13:AL13,"<=0")=0),C$4,99) -> 99 | D17: =IF(AND(D13>0,COUNTIF(D13:AL13,"<=0")=0),D$4,99) -> 99 | E17: =IF(AND(E13>0,COUNTIF(E13:AL13,"<=0")=0),E$4,99) -> 99 | F17: =IF(AND(F13>0,COUNTIF(F13:AL13,"<=0")=0),F$4,99) -> 99 | G17: =IF(AND(G13>0,COUNTIF(G13:AL13,"<=0")=0),G$4,99) -> 99 | H17: =IF(AND(H13>0,COUNTIF(H13:AL13,"<=0")=0),H$4,99) -> 99 | I17: =IF(AND(I13>0,COUNTIF(I13:AL13,"<=0")=0),I$4,99) -> 99 | J17: =IF(AND(J13>0,COUNTIF(J13:AL13,"<=0")=0),J$4,99) -> 99 | K17: =IF(AND(K13>0,COUNTIF(K13:AL13,"<=0")=0),K$4,99) -> 99 | L17: =IF(AND(L13>0,COUNTIF(L13:AL13,"<=0")=0),L$4,99) -> 99 | M17: =IF(AND(M13>0,COUNTIF(M13:AL13,"<=0")=0),M$4,99) -> 99 | N17: =IF(AND(N13>0,COUNTIF(N13:AL13,"<=0")=0),N$4,99) -> 99 | O17: =IF(AND(O13>0,COUNTIF(O13:AL13,"<=0")=0),O$4,99) -> 99 | P17: =IF(AND(P13>0,COUNTIF(P13:AL13,"<=0")=0),P$4,99) -> 99 | Q17: =IF(AND(Q13>0,COUNTIF(Q13:AL13,"<=0")=0),Q$4,99) -> 99 | R17: =IF(AND(R13>0,COUNTIF(R13:AL13,"<=0")=0),R$4,99) -> 99 | S17: =IF(AND(S13>0,COUNTIF(S13:AL13,"<=0")=0),S$4,99) -> 99 | T17: =IF(AND(T13>0,COUNTIF(T13:AL13,"<=0")=0),T$4,99) -> 99 | U17: =IF(AND(U13>0,COUNTIF(U13:AL13,"<=0")=0),U$4,99) -> 99 | V17: =IF(AND(V13>0,COUNTIF(V13:AL13,"<=0")=0),V$4,99) -> 99 | W17: =IF(AND(W13>0,COUNTIF(W13:AL13,"<=0")=0),W$4,99) -> 99 | X17: =IF(AND(X13>0,COUNTIF(X13:AL13,"<=0")=0),X$4,99) -> 99 | Y17: =IF(AND(Y13>0,COUNTIF(Y13:AL13,"<=0")=0),Y$4,99) -> 99 | Z17: =IF(AND(Z13>0,COUNTIF(Z13:AL13,"<=0")=0),Z$4,99) -> 99 | AA17: =IF(AND(AA13>0,COUNTIF(AA13:AL13,"<=0")=0),AA$4,99) -> 99 | AB17: =IF(AND(AB13>0,COUNTIF(AB13:AL13,"<=0")=0),AB$4,99) -> 99 | AC17: =IF(AND(AC13>0,COUNTIF(AC13:AL13,"<=0")=0),AC$4,99) -> 99 | AD17: =IF(AND(AD13>0,COUNTIF(AD13:AL13,"<=0")=0),AD$4,99) -> 99 | AE17: =IF(AND(AE13>0,COUNTIF(AE13:AL13,"<=0")=0),AE$4,99) -> 99 | AF17: =IF(AND(AF13>0,COUNTIF(AF13:AL13,"<=0")=0),AF$4,99) -> 99 | AG17: =IF(AND(AG13>0,COUNTIF(AG13:AL13,"<=0")=0),AG$4,99) -> 99 | AH17: =IF(AND(AH13>0,COUNTIF(AH13:AL13,"<=0")=0),AH$4,99) -> 99 | AI17: =IF(AND(AI13>0,COUNTIF(AI13:AL13,"<=0")=0),AI$4,99) -> 99 | AJ17: =IF(AND(AJ13>0,COUNTIF(AJ13:AL13,"<=0")=0),AJ$4,99) -> 99 | AK17: =IF(AND(AK13>0,COUNTIF(AK13:AL13,"<=0")=0),AK$4,99) -> 99 | AL17: =IF(AND(AL13>0,COUNTIF(AL13:AL13,"<=0")=0),AL$4,99) -> 99
A18: pb_flag | B18: служебно: месяц окупаемости | C18: =IF(AND(C16>=0,COUNTIF(C16:AL16,"<0")=0),C$4,99) -> 99 | D18: =IF(AND(D16>=0,COUNTIF(D16:AL16,"<0")=0),D$4,99) -> 99 | E18: =IF(AND(E16>=0,COUNTIF(E16:AL16,"<0")=0),E$4,99) -> 99 | F18: =IF(AND(F16>=0,COUNTIF(F16:AL16,"<0")=0),F$4,99) -> 99 | G18: =IF(AND(G16>=0,COUNTIF(G16:AL16,"<0")=0),G$4,99) -> 99 | H18: =IF(AND(H16>=0,COUNTIF(H16:AL16,"<0")=0),H$4,99) -> 99 | I18: =IF(AND(I16>=0,COUNTIF(I16:AL16,"<0")=0),I$4,99) -> 99 | J18: =IF(AND(J16>=0,COUNTIF(J16:AL16,"<0")=0),J$4,99) -> 99 | K18: =IF(AND(K16>=0,COUNTIF(K16:AL16,"<0")=0),K$4,99) -> 99 | L18: =IF(AND(L16>=0,COUNTIF(L16:AL16,"<0")=0),L$4,99) -> 99 | M18: =IF(AND(M16>=0,COUNTIF(M16:AL16,"<0")=0),M$4,99) -> 99 | N18: =IF(AND(N16>=0,COUNTIF(N16:AL16,"<0")=0),N$4,99) -> 99 | O18: =IF(AND(O16>=0,COUNTIF(O16:AL16,"<0")=0),O$4,99) -> 99 | P18: =IF(AND(P16>=0,COUNTIF(P16:AL16,"<0")=0),P$4,99) -> 99 | Q18: =IF(AND(Q16>=0,COUNTIF(Q16:AL16,"<0")=0),Q$4,99) -> 99 | R18: =IF(AND(R16>=0,COUNTIF(R16:AL16,"<0")=0),R$4,99) -> 99 | S18: =IF(AND(S16>=0,COUNTIF(S16:AL16,"<0")=0),S$4,99) -> 99 | T18: =IF(AND(T16>=0,COUNTIF(T16:AL16,"<0")=0),T$4,99) -> 99 | U18: =IF(AND(U16>=0,COUNTIF(U16:AL16,"<0")=0),U$4,99) -> 99 | V18: =IF(AND(V16>=0,COUNTIF(V16:AL16,"<0")=0),V$4,99) -> 99 | W18: =IF(AND(W16>=0,COUNTIF(W16:AL16,"<0")=0),W$4,99) -> 99 | X18: =IF(AND(X16>=0,COUNTIF(X16:AL16,"<0")=0),X$4,99) -> 99 | Y18: =IF(AND(Y16>=0,COUNTIF(Y16:AL16,"<0")=0),Y$4,99) -> 99 | Z18: =IF(AND(Z16>=0,COUNTIF(Z16:AL16,"<0")=0),Z$4,99) -> 99 | AA18: =IF(AND(AA16>=0,COUNTIF(AA16:AL16,"<0")=0),AA$4,99) -> 99 | AB18: =IF(AND(AB16>=0,COUNTIF(AB16:AL16,"<0")=0),AB$4,99) -> 99 | AC18: =IF(AND(AC16>=0,COUNTIF(AC16:AL16,"<0")=0),AC$4,99) -> 99 | AD18: =IF(AND(AD16>=0,COUNTIF(AD16:AL16,"<0")=0),AD$4,99) -> 99 | AE18: =IF(AND(AE16>=0,COUNTIF(AE16:AL16,"<0")=0),AE$4,99) -> 99 | AF18: =IF(AND(AF16>=0,COUNTIF(AF16:AL16,"<0")=0),AF$4,99) -> 99 | AG18: =IF(AND(AG16>=0,COUNTIF(AG16:AL16,"<0")=0),AG$4,99) -> 99 | AH18: =IF(AND(AH16>=0,COUNTIF(AH16:AL16,"<0")=0),AH$4,99) -> 99 | AI18: =IF(AND(AI16>=0,COUNTIF(AI16:AL16,"<0")=0),AI$4,99) -> 99 | AJ18: =IF(AND(AJ16>=0,COUNTIF(AJ16:AL16,"<0")=0),AJ$4,99) -> 99 | AK18: =IF(AND(AK16>=0,COUNTIF(AK16:AL16,"<0")=0),AK$4,99) -> 99 | AL18: =IF(AND(AL16>=0,COUNTIF(AL16:AL16,"<0")=0),AL$4,99) -> 99
A20: Сценарий: Базовый | B20: Месяц → | C20: 1 | D20: 2 | E20: 3 | F20: 4 | G20: 5 | H20: 6 | I20: 7 | J20: 8 | K20: 9 | L20: 10 | M20: 11 | N20: 12 | O20: 13 | P20: 14 | Q20: 15 | R20: 16 | S20: 17 | T20: 18 | U20: 19 | V20: 20 | W20: 21 | X20: 22 | Y20: 23 | Z20: 24 | AA20: 25 | AB20: 26 | AC20: 27 | AD20: 28 | AE20: 29 | AF20: 30 | AG20: 31 | AH20: 32 | AI20: 33 | AJ20: 34 | AK20: 35 | AL20: 36 | AM20: Год 1 | AN20: Год 2 | AO20: Год 3 | AP20: Итого 36 мес
A21: units | B21: Продажи, шт | C21: =Допущения!$D$43*Допущения!$D$44*IF(C$20<Допущения!$D$42,0,((C$20-Допущения!$D$42+1)/(36-Допущения!$D$42+1))^Допущения!$D$56) -> 0 | D21: =Допущения!$D$43*Допущения!$D$44*IF(D$20<Допущения!$D$42,0,((D$20-Допущения!$D$42+1)/(36-Допущения!$D$42+1))^Допущения!$D$56) -> 0 | E21: =Допущения!$D$43*Допущения!$D$44*IF(E$20<Допущения!$D$42,0,((E$20-Допущения!$D$42+1)/(36-Допущения!$D$42+1))^Допущения!$D$56) -> 0 | F21: =Допущения!$D$43*Допущения!$D$44*IF(F$20<Допущения!$D$42,0,((F$20-Допущения!$D$42+1)/(36-Допущения!$D$42+1))^Допущения!$D$56) -> 81.818182 | G21: =Допущения!$D$43*Допущения!$D$44*IF(G$20<Допущения!$D$42,0,((G$20-Допущения!$D$42+1)/(36-Допущения!$D$42+1))^Допущения!$D$56) -> 163.63636 | H21: =Допущения!$D$43*Допущения!$D$44*IF(H$20<Допущения!$D$42,0,((H$20-Допущения!$D$42+1)/(36-Допущения!$D$42+1))^Допущения!$D$56) -> 245.45455 | I21: =Допущения!$D$43*Допущения!$D$44*IF(I$20<Допущения!$D$42,0,((I$20-Допущения!$D$42+1)/(36-Допущения!$D$42+1))^Допущения!$D$56) -> 327.27273 | J21: =Допущения!$D$43*Допущения!$D$44*IF(J$20<Допущения!$D$42,0,((J$20-Допущения!$D$42+1)/(36-Допущения!$D$42+1))^Допущения!$D$56) -> 409.09091 | ... AL21: =Допущения!$D$43*Допущения!$D$44*IF(AL$20<Допущения!$D$42,0,((AL$20-Допущения!$D$42+1)/(36-Допущения!$D$42+1))^Допущения!$D$56) -> 2700 | AM21: =SUM(C21:N21) -> 3681.8182 | AN21: =SUM(O21:Z21) -> 15218.182 | AO21: =SUM(AA21:AL21) -> 27000 | AP21: =SUM(C21:AL21) -> 45900
A22: rev | B22: Выручка на Ozon, ₽ | C22: =C21*Допущения!$D$45 -> 0 | D22: =D21*Допущения!$D$45 -> 0 | E22: =E21*Допущения!$D$45 -> 0 | F22: =F21*Допущения!$D$45 -> 155454.55 | G22: =G21*Допущения!$D$45 -> 310909.09 | H22: =H21*Допущения!$D$45 -> 466363.64 | I22: =I21*Допущения!$D$45 -> 621818.18 | J22: =J21*Допущения!$D$45 -> 777272.73 | ... AL22: =AL21*Допущения!$D$45 -> 5130000 | AM22: =SUM(C22:N22) -> 6995454.5 | AN22: =SUM(O22:Z22) -> 28914545 | AO22: =SUM(AA22:AL22) -> 51300000 | AP22: =SUM(C22:AL22) -> 87210000
A23: unit_cm | B23: Маржа на единицу, ₽ | C23: =Допущения!$D$45*(1-Допущения!$D$47-Допущения!$D$46-Допущения!$D$49-Допущения!$D$50-Допущения!$D$52)-Допущения!$D$48-Допущения!$D$51 -> 95 | D23: =Допущения!$D$45*(1-Допущения!$D$47-Допущения!$D$46-Допущения!$D$49-Допущения!$D$50-Допущения!$D$52)-Допущения!$D$48-Допущения!$D$51 -> 95 | E23: =Допущения!$D$45*(1-Допущения!$D$47-Допущения!$D$46-Допущения!$D$49-Допущения!$D$50-Допущения!$D$52)-Допущения!$D$48-Допущения!$D$51 -> 95 | F23: =Допущения!$D$45*(1-Допущения!$D$47-Допущения!$D$46-Допущения!$D$49-Допущения!$D$50-Допущения!$D$52)-Допущения!$D$48-Допущения!$D$51 -> 95 | G23: =Допущения!$D$45*(1-Допущения!$D$47-Допущения!$D$46-Допущения!$D$49-Допущения!$D$50-Допущения!$D$52)-Допущения!$D$48-Допущения!$D$51 -> 95 | H23: =Допущения!$D$45*(1-Допущения!$D$47-Допущения!$D$46-Допущения!$D$49-Допущения!$D$50-Допущения!$D$52)-Допущения!$D$48-Допущения!$D$51 -> 95 | I23: =Допущения!$D$45*(1-Допущения!$D$47-Допущения!$D$46-Допущения!$D$49-Допущения!$D$50-Допущения!$D$52)-Допущения!$D$48-Допущения!$D$51 -> 95 | J23: =Допущения!$D$45*(1-Допущения!$D$47-Допущения!$D$46-Допущения!$D$49-Допущения!$D$50-Допущения!$D$52)-Допущения!$D$48-Допущения!$D$51 -> 95 | ... AL23: =Допущения!$D$45*(1-Допущения!$D$47-Допущения!$D$46-Допущения!$D$49-Допущения!$D$50-Допущения!$D$52)-Допущения!$D$48-Допущения!$D$51 -> 95 | AM23: =N23 -> 95 | AN23: =Z23 -> 95 | AO23: =AL23 -> 95
A24: contrib | B24: Маржинальный доход | C24: =C21*C23 -> 0 | D24: =D21*D23 -> 0 | E24: =E21*E23 -> 0 | F24: =F21*F23 -> 7772.7273 | G24: =G21*G23 -> 15545.455 | H24: =H21*H23 -> 23318.182 | I24: =I21*I23 -> 31090.909 | J24: =J21*J23 -> 38863.636 | ... AL24: =AL21*AL23 -> 256500 | AM24: =SUM(C24:N24) -> 349772.73 | AN24: =SUM(O24:Z24) -> 1445727.3 | AO24: =SUM(AA24:AL24) -> 2565000 | AP24: =SUM(C24:AL24) -> 4360500
A25: acq | B25: Внешнее привлечение (учтено в ДРР) | C25: =0 -> 0 | D25: =0 -> 0 | E25: =0 -> 0 | F25: =0 -> 0 | G25: =0 -> 0 | H25: =0 -> 0 | I25: =0 -> 0 | J25: =0 -> 0 | ... AL25: =0 -> 0 | AM25: =SUM(C25:N25) -> 0 | AN25: =SUM(O25:Z25) -> 0 | AO25: =SUM(AA25:AL25) -> 0 | AP25: =SUM(C25:AL25) -> 0
A26: sku | B26: Активных SKU | C26: =IF(C$20>=Допущения!$D$42-1,MAX(5,ROUNDUP(Допущения!$D$43*IF(C$20<Допущения!$D$42,0,((C$20-Допущения!$D$42+1)/(36-Допущения!$D$42+1))^1),0)),0) -> 0 | D26: =IF(D$20>=Допущения!$D$42-1,MAX(5,ROUNDUP(Допущения!$D$43*IF(D$20<Допущения!$D$42,0,((D$20-Допущения!$D$42+1)/(36-Допущения!$D$42+1))^1),0)),0) -> 0 | E26: =IF(E$20>=Допущения!$D$42-1,MAX(5,ROUNDUP(Допущения!$D$43*IF(E$20<Допущения!$D$42,0,((E$20-Допущения!$D$42+1)/(36-Допущения!$D$42+1))^1),0)),0) -> 5 | F26: =IF(F$20>=Допущения!$D$42-1,MAX(5,ROUNDUP(Допущения!$D$43*IF(F$20<Допущения!$D$42,0,((F$20-Допущения!$D$42+1)/(36-Допущения!$D$42+1))^1),0)),0) -> 5 | G26: =IF(G$20>=Допущения!$D$42-1,MAX(5,ROUNDUP(Допущения!$D$43*IF(G$20<Допущения!$D$42,0,((G$20-Допущения!$D$42+1)/(36-Допущения!$D$42+1))^1),0)),0) -> 5 | H26: =IF(H$20>=Допущения!$D$42-1,MAX(5,ROUNDUP(Допущения!$D$43*IF(H$20<Допущения!$D$42,0,((H$20-Допущения!$D$42+1)/(36-Допущения!$D$42+1))^1),0)),0) -> 5 | I26: =IF(I$20>=Допущения!$D$42-1,MAX(5,ROUNDUP(Допущения!$D$43*IF(I$20<Допущения!$D$42,0,((I$20-Допущения!$D$42+1)/(36-Допущения!$D$42+1))^1),0)),0) -> 5 | J26: =IF(J$20>=Допущения!$D$42-1,MAX(5,ROUNDUP(Допущения!$D$43*IF(J$20<Допущения!$D$42,0,((J$20-Допущения!$D$42+1)/(36-Допущения!$D$42+1))^1),0)),0) -> 5 | ... AL26: =IF(AL$20>=Допущения!$D$42-1,MAX(5,ROUNDUP(Допущения!$D$43*IF(AL$20<Допущения!$D$42,0,((AL$20-Допущения!$D$42+1)/(36-Допущения!$D$42+1))^1),0)),0) -> 30 | AM26: =N26 -> 9 | AN26: =Z26 -> 20 | AO26: =AL26 -> 30
A27: inv | B27: Запас на складе по себестоимости | C27: =IF(C$20>=Допущения!$D$42-1,MAX(C21*Допущения!$D$53,C26*100)*Допущения!$D$45*Допущения!$D$46,0) -> 0 | D27: =IF(D$20>=Допущения!$D$42-1,MAX(D21*Допущения!$D$53,D26*100)*Допущения!$D$45*Допущения!$D$46,0) -> 0 | E27: =IF(E$20>=Допущения!$D$42-1,MAX(E21*Допущения!$D$53,E26*100)*Допущения!$D$45*Допущения!$D$46,0) -> 247000 | F27: =IF(F$20>=Допущения!$D$42-1,MAX(F21*Допущения!$D$53,F26*100)*Допущения!$D$45*Допущения!$D$46,0) -> 247000 | G27: =IF(G$20>=Допущения!$D$42-1,MAX(G21*Допущения!$D$53,G26*100)*Допущения!$D$45*Допущения!$D$46,0) -> 247000 | H27: =IF(H$20>=Допущения!$D$42-1,MAX(H21*Допущения!$D$53,H26*100)*Допущения!$D$45*Допущения!$D$46,0) -> 303136.36 | I27: =IF(I$20>=Допущения!$D$42-1,MAX(I21*Допущения!$D$53,I26*100)*Допущения!$D$45*Допущения!$D$46,0) -> 404181.82 | J27: =IF(J$20>=Допущения!$D$42-1,MAX(J21*Допущения!$D$53,J26*100)*Допущения!$D$45*Допущения!$D$46,0) -> 505227.27 | ... AL27: =IF(AL$20>=Допущения!$D$42-1,MAX(AL21*Допущения!$D$53,AL26*100)*Допущения!$D$45*Допущения!$D$46,0) -> 3334500 | AM27: =N27 -> 909409.09 | AN27: =Z27 -> 2121954.5 | AO27: =AL27 -> 3334500
A28: fixed | B28: Постоянные расходы (команда) | C28: =Допущения!$D$54 -> 220000 | D28: =Допущения!$D$54 -> 220000 | E28: =Допущения!$D$54 -> 220000 | F28: =Допущения!$D$54 -> 220000 | G28: =Допущения!$D$54 -> 220000 | H28: =Допущения!$D$54 -> 220000 | I28: =Допущения!$D$54 -> 220000 | J28: =Допущения!$D$54 -> 220000 | ... AL28: =Допущения!$D$54 -> 220000 | AM28: =SUM(C28:N28) -> 2640000 | AN28: =SUM(O28:Z28) -> 2640000 | AO28: =SUM(AA28:AL28) -> 2640000 | AP28: =SUM(C28:AL28) -> 7920000
A29: op | B29: Операционная прибыль (маржинальный доход − постоянные − привлечение) | C29: =C24-C28-C25 -> -220000 | D29: =D24-D28-D25 -> -220000 | E29: =E24-E28-E25 -> -220000 | F29: =F24-F28-F25 -> -212227.27 | G29: =G24-G28-G25 -> -204454.55 | H29: =H24-H28-H25 -> -196681.82 | I29: =I24-I28-I25 -> -188909.09 | J29: =J24-J28-J25 -> -181136.36 | ... AL29: =AL24-AL28-AL25 -> 36500 | AM29: =SUM(C29:N29) -> -2290227.3 | AN29: =SUM(O29:Z29) -> -1194272.7 | AO29: =SUM(AA29:AL29) -> -75000 | AP29: =SUM(C29:AL29) -> -3559500
A30: capex | B30: CAPEX и вложения в оборотку | C30: =IF(C$20<Допущения!$D$42,Допущения!$D$55/(Допущения!$D$42-1),0)+C27-0 -> 133333.33 | D30: =IF(D$20<Допущения!$D$42,Допущения!$D$55/(Допущения!$D$42-1),0)+D27-C27 -> 133333.33 | E30: =IF(E$20<Допущения!$D$42,Допущения!$D$55/(Допущения!$D$42-1),0)+E27-D27 -> 380333.33 | F30: =IF(F$20<Допущения!$D$42,Допущения!$D$55/(Допущения!$D$42-1),0)+F27-E27 -> 0 | G30: =IF(G$20<Допущения!$D$42,Допущения!$D$55/(Допущения!$D$42-1),0)+G27-F27 -> 0 | H30: =IF(H$20<Допущения!$D$42,Допущения!$D$55/(Допущения!$D$42-1),0)+H27-G27 -> 56136.364 | I30: =IF(I$20<Допущения!$D$42,Допущения!$D$55/(Допущения!$D$42-1),0)+I27-H27 -> 101045.45 | J30: =IF(J$20<Допущения!$D$42,Допущения!$D$55/(Допущения!$D$42-1),0)+J27-I27 -> 101045.45 | K30: =IF(K$20<Допущения!$D$42,Допущения!$D$55/(Допущения!$D$42-1),0)+K27-J27 -> 101045.45 | ... AL30: =IF(AL$20<Допущения!$D$42,Допущения!$D$55/(Допущения!$D$42-1),0)+AL27-AK27 -> 101045.45 | AM30: =SUM(C30:N30) -> 1309409.1 | AN30: =SUM(O30:Z30) -> 1212545.5 | AO30: =SUM(AA30:AL30) -> 1212545.5 | AP30: =SUM(C30:AL30) -> 3734500
A31: cf | B31: Денежный поток | C31: =C29-C30 -> -353333.33 | D31: =D29-D30 -> -353333.33 | E31: =E29-E30 -> -600333.33 | F31: =F29-F30 -> -212227.27 | G31: =G29-G30 -> -204454.55 | H31: =H29-H30 -> -252818.18 | I31: =I29-I30 -> -289954.55 | J31: =J29-J30 -> -282181.82 | ... AL31: =AL29-AL30 -> -64545.455 | AM31: =SUM(C31:N31) -> -3599636.4 | AN31: =SUM(O31:Z31) -> -2406818.2 | AO31: =SUM(AA31:AL31) -> -1287545.5 | AP31: =SUM(C31:AL31) -> -7294000
A32: cum | B32: Накопленный денежный поток | C32: =0+C31 -> -353333.33 | D32: =C32+D31 -> -706666.67 | E32: =D32+E31 -> -1307000 | F32: =E32+F31 -> -1519227.3 | G32: =F32+G31 -> -1723681.8 | H32: =G32+H31 -> -1976500 | I32: =H32+I31 -> -2266454.5 | J32: =I32+J31 -> -2548636.4 | K32: =J32+K31 -> -2823045.5 | ... AL32: =AK32+AL31 -> -7294000 | AM32: =N32 -> -3599636.4 | AN32: =Z32 -> -6006454.5 | AO32: =AL32 -> -7294000
A33: be_flag | B33: служебно: месяц устойчивой опер. прибыли | C33: =IF(AND(C29>0,COUNTIF(C29:AL29,"<=0")=0),C$20,99) -> 99 | D33: =IF(AND(D29>0,COUNTIF(D29:AL29,"<=0")=0),D$20,99) -> 99 | E33: =IF(AND(E29>0,COUNTIF(E29:AL29,"<=0")=0),E$20,99) -> 99 | F33: =IF(AND(F29>0,COUNTIF(F29:AL29,"<=0")=0),F$20,99) -> 99 | G33: =IF(AND(G29>0,COUNTIF(G29:AL29,"<=0")=0),G$20,99) -> 99 | H33: =IF(AND(H29>0,COUNTIF(H29:AL29,"<=0")=0),H$20,99) -> 99 | I33: =IF(AND(I29>0,COUNTIF(I29:AL29,"<=0")=0),I$20,99) -> 99 | J33: =IF(AND(J29>0,COUNTIF(J29:AL29,"<=0")=0),J$20,99) -> 99 | K33: =IF(AND(K29>0,COUNTIF(K29:AL29,"<=0")=0),K$20,99) -> 99 | L33: =IF(AND(L29>0,COUNTIF(L29:AL29,"<=0")=0),L$20,99) -> 99 | M33: =IF(AND(M29>0,COUNTIF(M29:AL29,"<=0")=0),M$20,99) -> 99 | N33: =IF(AND(N29>0,COUNTIF(N29:AL29,"<=0")=0),N$20,99) -> 99 | O33: =IF(AND(O29>0,COUNTIF(O29:AL29,"<=0")=0),O$20,99) -> 99 | P33: =IF(AND(P29>0,COUNTIF(P29:AL29,"<=0")=0),P$20,99) -> 99 | Q33: =IF(AND(Q29>0,COUNTIF(Q29:AL29,"<=0")=0),Q$20,99) -> 99 | R33: =IF(AND(R29>0,COUNTIF(R29:AL29,"<=0")=0),R$20,99) -> 99 | S33: =IF(AND(S29>0,COUNTIF(S29:AL29,"<=0")=0),S$20,99) -> 99 | T33: =IF(AND(T29>0,COUNTIF(T29:AL29,"<=0")=0),T$20,99) -> 99 | U33: =IF(AND(U29>0,COUNTIF(U29:AL29,"<=0")=0),U$20,99) -> 99 | V33: =IF(AND(V29>0,COUNTIF(V29:AL29,"<=0")=0),V$20,99) -> 99 | W33: =IF(AND(W29>0,COUNTIF(W29:AL29,"<=0")=0),W$20,99) -> 99 | X33: =IF(AND(X29>0,COUNTIF(X29:AL29,"<=0")=0),X$20,99) -> 99 | Y33: =IF(AND(Y29>0,COUNTIF(Y29:AL29,"<=0")=0),Y$20,99) -> 99 | Z33: =IF(AND(Z29>0,COUNTIF(Z29:AL29,"<=0")=0),Z$20,99) -> 99 | AA33: =IF(AND(AA29>0,COUNTIF(AA29:AL29,"<=0")=0),AA$20,99) -> 99 | AB33: =IF(AND(AB29>0,COUNTIF(AB29:AL29,"<=0")=0),AB$20,99) -> 99 | AC33: =IF(AND(AC29>0,COUNTIF(AC29:AL29,"<=0")=0),AC$20,99) -> 99 | AD33: =IF(AND(AD29>0,COUNTIF(AD29:AL29,"<=0")=0),AD$20,99) -> 99 | AE33: =IF(AND(AE29>0,COUNTIF(AE29:AL29,"<=0")=0),AE$20,99) -> 99 | AF33: =IF(AND(AF29>0,COUNTIF(AF29:AL29,"<=0")=0),AF$20,99) -> 99 | AG33: =IF(AND(AG29>0,COUNTIF(AG29:AL29,"<=0")=0),AG$20,99) -> 99 | AH33: =IF(AND(AH29>0,COUNTIF(AH29:AL29,"<=0")=0),AH$20,99) -> 32 | AI33: =IF(AND(AI29>0,COUNTIF(AI29:AL29,"<=0")=0),AI$20,99) -> 33 | AJ33: =IF(AND(AJ29>0,COUNTIF(AJ29:AL29,"<=0")=0),AJ$20,99) -> 34 | AK33: =IF(AND(AK29>0,COUNTIF(AK29:AL29,"<=0")=0),AK$20,99) -> 35 | AL33: =IF(AND(AL29>0,COUNTIF(AL29:AL29,"<=0")=0),AL$20,99) -> 36
A34: pb_flag | B34: служебно: месяц окупаемости | C34: =IF(AND(C32>=0,COUNTIF(C32:AL32,"<0")=0),C$20,99) -> 99 | D34: =IF(AND(D32>=0,COUNTIF(D32:AL32,"<0")=0),D$20,99) -> 99 | E34: =IF(AND(E32>=0,COUNTIF(E32:AL32,"<0")=0),E$20,99) -> 99 | F34: =IF(AND(F32>=0,COUNTIF(F32:AL32,"<0")=0),F$20,99) -> 99 | G34: =IF(AND(G32>=0,COUNTIF(G32:AL32,"<0")=0),G$20,99) -> 99 | H34: =IF(AND(H32>=0,COUNTIF(H32:AL32,"<0")=0),H$20,99) -> 99 | I34: =IF(AND(I32>=0,COUNTIF(I32:AL32,"<0")=0),I$20,99) -> 99 | J34: =IF(AND(J32>=0,COUNTIF(J32:AL32,"<0")=0),J$20,99) -> 99 | K34: =IF(AND(K32>=0,COUNTIF(K32:AL32,"<0")=0),K$20,99) -> 99 | L34: =IF(AND(L32>=0,COUNTIF(L32:AL32,"<0")=0),L$20,99) -> 99 | M34: =IF(AND(M32>=0,COUNTIF(M32:AL32,"<0")=0),M$20,99) -> 99 | N34: =IF(AND(N32>=0,COUNTIF(N32:AL32,"<0")=0),N$20,99) -> 99 | O34: =IF(AND(O32>=0,COUNTIF(O32:AL32,"<0")=0),O$20,99) -> 99 | P34: =IF(AND(P32>=0,COUNTIF(P32:AL32,"<0")=0),P$20,99) -> 99 | Q34: =IF(AND(Q32>=0,COUNTIF(Q32:AL32,"<0")=0),Q$20,99) -> 99 | R34: =IF(AND(R32>=0,COUNTIF(R32:AL32,"<0")=0),R$20,99) -> 99 | S34: =IF(AND(S32>=0,COUNTIF(S32:AL32,"<0")=0),S$20,99) -> 99 | T34: =IF(AND(T32>=0,COUNTIF(T32:AL32,"<0")=0),T$20,99) -> 99 | U34: =IF(AND(U32>=0,COUNTIF(U32:AL32,"<0")=0),U$20,99) -> 99 | V34: =IF(AND(V32>=0,COUNTIF(V32:AL32,"<0")=0),V$20,99) -> 99 | W34: =IF(AND(W32>=0,COUNTIF(W32:AL32,"<0")=0),W$20,99) -> 99 | X34: =IF(AND(X32>=0,COUNTIF(X32:AL32,"<0")=0),X$20,99) -> 99 | Y34: =IF(AND(Y32>=0,COUNTIF(Y32:AL32,"<0")=0),Y$20,99) -> 99 | Z34: =IF(AND(Z32>=0,COUNTIF(Z32:AL32,"<0")=0),Z$20,99) -> 99 | AA34: =IF(AND(AA32>=0,COUNTIF(AA32:AL32,"<0")=0),AA$20,99) -> 99 | AB34: =IF(AND(AB32>=0,COUNTIF(AB32:AL32,"<0")=0),AB$20,99) -> 99 | AC34: =IF(AND(AC32>=0,COUNTIF(AC32:AL32,"<0")=0),AC$20,99) -> 99 | AD34: =IF(AND(AD32>=0,COUNTIF(AD32:AL32,"<0")=0),AD$20,99) -> 99 | AE34: =IF(AND(AE32>=0,COUNTIF(AE32:AL32,"<0")=0),AE$20,99) -> 99 | AF34: =IF(AND(AF32>=0,COUNTIF(AF32:AL32,"<0")=0),AF$20,99) -> 99 | AG34: =IF(AND(AG32>=0,COUNTIF(AG32:AL32,"<0")=0),AG$20,99) -> 99 | AH34: =IF(AND(AH32>=0,COUNTIF(AH32:AL32,"<0")=0),AH$20,99) -> 99 | AI34: =IF(AND(AI32>=0,COUNTIF(AI32:AL32,"<0")=0),AI$20,99) -> 99 | AJ34: =IF(AND(AJ32>=0,COUNTIF(AJ32:AL32,"<0")=0),AJ$20,99) -> 99 | AK34: =IF(AND(AK32>=0,COUNTIF(AK32:AL32,"<0")=0),AK$20,99) -> 99 | AL34: =IF(AND(AL32>=0,COUNTIF(AL32:AL32,"<0")=0),AL$20,99) -> 99
A36: Сценарий: Оптимистичный | B36: Месяц → | C36: 1 | D36: 2 | E36: 3 | F36: 4 | G36: 5 | H36: 6 | I36: 7 | J36: 8 | K36: 9 | L36: 10 | M36: 11 | N36: 12 | O36: 13 | P36: 14 | Q36: 15 | R36: 16 | S36: 17 | T36: 18 | U36: 19 | V36: 20 | W36: 21 | X36: 22 | Y36: 23 | Z36: 24 | AA36: 25 | AB36: 26 | AC36: 27 | AD36: 28 | AE36: 29 | AF36: 30 | AG36: 31 | AH36: 32 | AI36: 33 | AJ36: 34 | AK36: 35 | AL36: 36 | AM36: Год 1 | AN36: Год 2 | AO36: Год 3 | AP36: Итого 36 мес
A37: units | B37: Продажи, шт | C37: =Допущения!$E$43*Допущения!$E$44*IF(C$36<Допущения!$E$42,0,((C$36-Допущения!$E$42+1)/(36-Допущения!$E$42+1))^Допущения!$E$56) -> 0 | D37: =Допущения!$E$43*Допущения!$E$44*IF(D$36<Допущения!$E$42,0,((D$36-Допущения!$E$42+1)/(36-Допущения!$E$42+1))^Допущения!$E$56) -> 0 | E37: =Допущения!$E$43*Допущения!$E$44*IF(E$36<Допущения!$E$42,0,((E$36-Допущения!$E$42+1)/(36-Допущения!$E$42+1))^Допущения!$E$56) -> 334.77958 | F37: =Допущения!$E$43*Допущения!$E$44*IF(F$36<Допущения!$E$42,0,((F$36-Допущения!$E$42+1)/(36-Допущения!$E$42+1))^Допущения!$E$56) -> 624.72079 | G37: =Допущения!$E$43*Допущения!$E$44*IF(G$36<Допущения!$E$42,0,((G$36-Допущения!$E$42+1)/(36-Допущения!$E$42+1))^Допущения!$E$56) -> 899.84579 | H37: =Допущения!$E$43*Допущения!$E$44*IF(H$36<Допущения!$E$42,0,((H$36-Допущения!$E$42+1)/(36-Допущения!$E$42+1))^Допущения!$E$56) -> 1165.7702 | I37: =Допущения!$E$43*Допущения!$E$44*IF(I$36<Допущения!$E$42,0,((I$36-Допущения!$E$42+1)/(36-Допущения!$E$42+1))^Допущения!$E$56) -> 1425.0561 | J37: =Допущения!$E$43*Допущения!$E$44*IF(J$36<Допущения!$E$42,0,((J$36-Допущения!$E$42+1)/(36-Допущения!$E$42+1))^Допущения!$E$56) -> 1679.1716 | ... AL37: =Допущения!$E$43*Допущения!$E$44*IF(AL$36<Допущения!$E$42,0,((AL$36-Допущения!$E$42+1)/(36-Допущения!$E$42+1))^Допущения!$E$56) -> 8000 | AM37: =SUM(C37:N37) -> 15311.737 | AN37: =SUM(O37:Z37) -> 49981.13 | AO37: =SUM(AA37:AL37) -> 81848.797 | AP37: =SUM(C37:AL37) -> 147141.66
A38: rev | B38: Выручка на Ozon, ₽ | C38: =C37*Допущения!$E$45 -> 0 | D38: =D37*Допущения!$E$45 -> 0 | E38: =E37*Допущения!$E$45 -> 736515.08 | F38: =F37*Допущения!$E$45 -> 1374385.7 | G38: =G37*Допущения!$E$45 -> 1979660.7 | H38: =H37*Допущения!$E$45 -> 2564694.5 | I38: =I37*Допущения!$E$45 -> 3135123.4 | J38: =J37*Допущения!$E$45 -> 3694177.6 | ... AL38: =AL37*Допущения!$E$45 -> 17600000 | AM38: =SUM(C38:N38) -> 33685821 | AN38: =SUM(O38:Z38) -> 1.0995849e+08 | AO38: =SUM(AA38:AL38) -> 1.8006735e+08 | AP38: =SUM(C38:AL38) -> 3.2371166e+08
A39: unit_cm | B39: Маржа на единицу, ₽ | C39: =Допущения!$E$45*(1-Допущения!$E$47-Допущения!$E$46-Допущения!$E$49-Допущения!$E$50-Допущения!$E$52)-Допущения!$E$48-Допущения!$E$51 -> 475 | D39: =Допущения!$E$45*(1-Допущения!$E$47-Допущения!$E$46-Допущения!$E$49-Допущения!$E$50-Допущения!$E$52)-Допущения!$E$48-Допущения!$E$51 -> 475 | E39: =Допущения!$E$45*(1-Допущения!$E$47-Допущения!$E$46-Допущения!$E$49-Допущения!$E$50-Допущения!$E$52)-Допущения!$E$48-Допущения!$E$51 -> 475 | F39: =Допущения!$E$45*(1-Допущения!$E$47-Допущения!$E$46-Допущения!$E$49-Допущения!$E$50-Допущения!$E$52)-Допущения!$E$48-Допущения!$E$51 -> 475 | G39: =Допущения!$E$45*(1-Допущения!$E$47-Допущения!$E$46-Допущения!$E$49-Допущения!$E$50-Допущения!$E$52)-Допущения!$E$48-Допущения!$E$51 -> 475 | H39: =Допущения!$E$45*(1-Допущения!$E$47-Допущения!$E$46-Допущения!$E$49-Допущения!$E$50-Допущения!$E$52)-Допущения!$E$48-Допущения!$E$51 -> 475 | I39: =Допущения!$E$45*(1-Допущения!$E$47-Допущения!$E$46-Допущения!$E$49-Допущения!$E$50-Допущения!$E$52)-Допущения!$E$48-Допущения!$E$51 -> 475 | J39: =Допущения!$E$45*(1-Допущения!$E$47-Допущения!$E$46-Допущения!$E$49-Допущения!$E$50-Допущения!$E$52)-Допущения!$E$48-Допущения!$E$51 -> 475 | ... AL39: =Допущения!$E$45*(1-Допущения!$E$47-Допущения!$E$46-Допущения!$E$49-Допущения!$E$50-Допущения!$E$52)-Допущения!$E$48-Допущения!$E$51 -> 475 | AM39: =N39 -> 475 | AN39: =Z39 -> 475 | AO39: =AL39 -> 475
A40: contrib | B40: Маржинальный доход | C40: =C37*C39 -> 0 | D40: =D37*D39 -> 0 | E40: =E37*E39 -> 159020.3 | F40: =F37*F39 -> 296742.37 | G40: =G37*G39 -> 427426.75 | H40: =H37*H39 -> 553740.85 | I40: =I37*I39 -> 676901.65 | J40: =J37*J39 -> 797606.52 | ... AL40: =AL37*AL39 -> 3800000 | AM40: =SUM(C40:N40) -> 7273075 | AN40: =SUM(O40:Z40) -> 23741037 | AO40: =SUM(AA40:AL40) -> 38878179 | AP40: =SUM(C40:AL40) -> 69892291
A41: acq | B41: Внешнее привлечение (учтено в ДРР) | C41: =0 -> 0 | D41: =0 -> 0 | E41: =0 -> 0 | F41: =0 -> 0 | G41: =0 -> 0 | H41: =0 -> 0 | I41: =0 -> 0 | J41: =0 -> 0 | ... AL41: =0 -> 0 | AM41: =SUM(C41:N41) -> 0 | AN41: =SUM(O41:Z41) -> 0 | AO41: =SUM(AA41:AL41) -> 0 | AP41: =SUM(C41:AL41) -> 0
A42: sku | B42: Активных SKU | C42: =IF(C$36>=Допущения!$E$42-1,MAX(5,ROUNDUP(Допущения!$E$43*IF(C$36<Допущения!$E$42,0,((C$36-Допущения!$E$42+1)/(36-Допущения!$E$42+1))^1),0)),0) -> 0 | D42: =IF(D$36>=Допущения!$E$42-1,MAX(5,ROUNDUP(Допущения!$E$43*IF(D$36<Допущения!$E$42,0,((D$36-Допущения!$E$42+1)/(36-Допущения!$E$42+1))^1),0)),0) -> 5 | E42: =IF(E$36>=Допущения!$E$42-1,MAX(5,ROUNDUP(Допущения!$E$43*IF(E$36<Допущения!$E$42,0,((E$36-Допущения!$E$42+1)/(36-Допущения!$E$42+1))^1),0)),0) -> 5 | F42: =IF(F$36>=Допущения!$E$42-1,MAX(5,ROUNDUP(Допущения!$E$43*IF(F$36<Допущения!$E$42,0,((F$36-Допущения!$E$42+1)/(36-Допущения!$E$42+1))^1),0)),0) -> 5 | G42: =IF(G$36>=Допущения!$E$42-1,MAX(5,ROUNDUP(Допущения!$E$43*IF(G$36<Допущения!$E$42,0,((G$36-Допущения!$E$42+1)/(36-Допущения!$E$42+1))^1),0)),0) -> 5 | H42: =IF(H$36>=Допущения!$E$42-1,MAX(5,ROUNDUP(Допущения!$E$43*IF(H$36<Допущения!$E$42,0,((H$36-Допущения!$E$42+1)/(36-Допущения!$E$42+1))^1),0)),0) -> 6 | I42: =IF(I$36>=Допущения!$E$42-1,MAX(5,ROUNDUP(Допущения!$E$43*IF(I$36<Допущения!$E$42,0,((I$36-Допущения!$E$42+1)/(36-Допущения!$E$42+1))^1),0)),0) -> 8 | J42: =IF(J$36>=Допущения!$E$42-1,MAX(5,ROUNDUP(Допущения!$E$43*IF(J$36<Допущения!$E$42,0,((J$36-Допущения!$E$42+1)/(36-Допущения!$E$42+1))^1),0)),0) -> 9 | ... AL42: =IF(AL$36>=Допущения!$E$42-1,MAX(5,ROUNDUP(Допущения!$E$43*IF(AL$36<Допущения!$E$42,0,((AL$36-Допущения!$E$42+1)/(36-Допущения!$E$42+1))^1),0)),0) -> 50 | AM42: =N42 -> 15 | AN42: =Z42 -> 33 | AO42: =AL42 -> 50
A43: inv | B43: Запас на складе по себестоимости | C43: =IF(C$36>=Допущения!$E$42-1,MAX(C37*Допущения!$E$53,C42*100)*Допущения!$E$45*Допущения!$E$46,0) -> 0 | D43: =IF(D$36>=Допущения!$E$42-1,MAX(D37*Допущения!$E$53,D42*100)*Допущения!$E$45*Допущения!$E$46,0) -> 253000 | E43: =IF(E$36>=Допущения!$E$42-1,MAX(E37*Допущения!$E$53,E42*100)*Допущения!$E$45*Допущения!$E$46,0) -> 338796.94 | F43: =IF(F$36>=Допущения!$E$42-1,MAX(F37*Допущения!$E$53,F42*100)*Допущения!$E$45*Допущения!$E$46,0) -> 632217.44 | G43: =IF(G$36>=Допущения!$E$42-1,MAX(G37*Допущения!$E$53,G42*100)*Допущения!$E$45*Допущения!$E$46,0) -> 910643.94 | H43: =IF(H$36>=Допущения!$E$42-1,MAX(H37*Допущения!$E$53,H42*100)*Допущения!$E$45*Допущения!$E$46,0) -> 1179759.5 | I43: =IF(I$36>=Допущения!$E$42-1,MAX(I37*Допущения!$E$53,I42*100)*Допущения!$E$45*Допущения!$E$46,0) -> 1442156.8 | J43: =IF(J$36>=Допущения!$E$42-1,MAX(J37*Допущения!$E$53,J42*100)*Допущения!$E$45*Допущения!$E$46,0) -> 1699321.7 | ... AL43: =IF(AL$36>=Допущения!$E$42-1,MAX(AL37*Допущения!$E$53,AL42*100)*Допущения!$E$45*Допущения!$E$46,0) -> 8096000 | AM43: =N43 -> 2691159.7 | AN43: =Z43 -> 5471669.9 | AO43: =AL43 -> 8096000
A44: fixed | B44: Постоянные расходы (команда) | C44: =Допущения!$E$54 -> 180000 | D44: =Допущения!$E$54 -> 180000 | E44: =Допущения!$E$54 -> 180000 | F44: =Допущения!$E$54 -> 180000 | G44: =Допущения!$E$54 -> 180000 | H44: =Допущения!$E$54 -> 180000 | I44: =Допущения!$E$54 -> 180000 | J44: =Допущения!$E$54 -> 180000 | ... AL44: =Допущения!$E$54 -> 180000 | AM44: =SUM(C44:N44) -> 2160000 | AN44: =SUM(O44:Z44) -> 2160000 | AO44: =SUM(AA44:AL44) -> 2160000 | AP44: =SUM(C44:AL44) -> 6480000
A45: op | B45: Операционная прибыль (маржинальный доход − постоянные − привлечение) | C45: =C40-C44-C41 -> -180000 | D45: =D40-D44-D41 -> -180000 | E45: =E40-E44-E41 -> -20979.699 | F45: =F40-F44-F41 -> 116742.37 | G45: =G40-G44-G41 -> 247426.75 | H45: =H40-H44-H41 -> 373740.85 | I45: =I40-I44-I41 -> 496901.65 | J45: =J40-J44-J41 -> 617606.52 | ... AL45: =AL40-AL44-AL41 -> 3620000 | AM45: =SUM(C45:N45) -> 5113075 | AN45: =SUM(O45:Z45) -> 21581037 | AO45: =SUM(AA45:AL45) -> 36718179 | AP45: =SUM(C45:AL45) -> 63412291
A46: capex | B46: CAPEX и вложения в оборотку | C46: =IF(C$36<Допущения!$E$42,Допущения!$E$55/(Допущения!$E$42-1),0)+C43-0 -> 150000 | D46: =IF(D$36<Допущения!$E$42,Допущения!$E$55/(Допущения!$E$42-1),0)+D43-C43 -> 403000 | E46: =IF(E$36<Допущения!$E$42,Допущения!$E$55/(Допущения!$E$42-1),0)+E43-D43 -> 85796.936 | F46: =IF(F$36<Допущения!$E$42,Допущения!$E$55/(Допущения!$E$42-1),0)+F43-E43 -> 293420.5 | G46: =IF(G$36<Допущения!$E$42,Допущения!$E$55/(Допущения!$E$42-1),0)+G43-F43 -> 278426.51 | H46: =IF(H$36<Допущения!$E$42,Допущения!$E$55/(Допущения!$E$42-1),0)+H43-G43 -> 269115.51 | I46: =IF(I$36<Допущения!$E$42,Допущения!$E$55/(Допущения!$E$42-1),0)+I43-H43 -> 262397.33 | J46: =IF(J$36<Допущения!$E$42,Допущения!$E$55/(Допущения!$E$42-1),0)+J43-I43 -> 257164.9 | K46: =IF(K$36<Допущения!$E$42,Допущения!$E$55/(Допущения!$E$42-1),0)+K43-J43 -> 252893.61 | ... AL46: =IF(AL$36<Допущения!$E$42,Допущения!$E$55/(Допущения!$E$42-1),0)+AL43-AK43 -> 214624.49 | AM46: =SUM(C46:N46) -> 2991159.7 | AN46: =SUM(O46:Z46) -> 2780510.2 | AO46: =SUM(AA46:AL46) -> 2624330.1 | AP46: =SUM(C46:AL46) -> 8396000
A47: cf | B47: Денежный поток | C47: =C45-C46 -> -330000 | D47: =D45-D46 -> -583000 | E47: =E45-E46 -> -106776.64 | F47: =F45-F46 -> -176678.13 | G47: =G45-G46 -> -30999.754 | H47: =H45-H46 -> 104625.34 | I47: =I45-I46 -> 234504.32 | J47: =J45-J46 -> 360441.62 | ... AL47: =AL45-AL46 -> 3405375.5 | AM47: =SUM(C47:N47) -> 2121915.3 | AN47: =SUM(O47:Z47) -> 18800527 | AO47: =SUM(AA47:AL47) -> 34093848 | AP47: =SUM(C47:AL47) -> 55016291
A48: cum | B48: Накопленный денежный поток | C48: =0+C47 -> -330000 | D48: =C48+D47 -> -913000 | E48: =D48+E47 -> -1019776.6 | F48: =E48+F47 -> -1196454.8 | G48: =F48+G47 -> -1227454.5 | H48: =G48+H47 -> -1122829.2 | I48: =H48+I47 -> -888324.85 | J48: =I48+J47 -> -527883.23 | K48: =J48+K47 -> -44470.253 | ... AL48: =AK48+AL47 -> 55016291 | AM48: =N48 -> 2121915.3 | AN48: =Z48 -> 20922442 | AO48: =AL48 -> 55016291
A49: be_flag | B49: служебно: месяц устойчивой опер. прибыли | C49: =IF(AND(C45>0,COUNTIF(C45:AL45,"<=0")=0),C$36,99) -> 99 | D49: =IF(AND(D45>0,COUNTIF(D45:AL45,"<=0")=0),D$36,99) -> 99 | E49: =IF(AND(E45>0,COUNTIF(E45:AL45,"<=0")=0),E$36,99) -> 99 | F49: =IF(AND(F45>0,COUNTIF(F45:AL45,"<=0")=0),F$36,99) -> 4 | G49: =IF(AND(G45>0,COUNTIF(G45:AL45,"<=0")=0),G$36,99) -> 5 | H49: =IF(AND(H45>0,COUNTIF(H45:AL45,"<=0")=0),H$36,99) -> 6 | I49: =IF(AND(I45>0,COUNTIF(I45:AL45,"<=0")=0),I$36,99) -> 7 | J49: =IF(AND(J45>0,COUNTIF(J45:AL45,"<=0")=0),J$36,99) -> 8 | K49: =IF(AND(K45>0,COUNTIF(K45:AL45,"<=0")=0),K$36,99) -> 9 | L49: =IF(AND(L45>0,COUNTIF(L45:AL45,"<=0")=0),L$36,99) -> 10 | M49: =IF(AND(M45>0,COUNTIF(M45:AL45,"<=0")=0),M$36,99) -> 11 | N49: =IF(AND(N45>0,COUNTIF(N45:AL45,"<=0")=0),N$36,99) -> 12 | O49: =IF(AND(O45>0,COUNTIF(O45:AL45,"<=0")=0),O$36,99) -> 13 | P49: =IF(AND(P45>0,COUNTIF(P45:AL45,"<=0")=0),P$36,99) -> 14 | Q49: =IF(AND(Q45>0,COUNTIF(Q45:AL45,"<=0")=0),Q$36,99) -> 15 | R49: =IF(AND(R45>0,COUNTIF(R45:AL45,"<=0")=0),R$36,99) -> 16 | S49: =IF(AND(S45>0,COUNTIF(S45:AL45,"<=0")=0),S$36,99) -> 17 | T49: =IF(AND(T45>0,COUNTIF(T45:AL45,"<=0")=0),T$36,99) -> 18 | U49: =IF(AND(U45>0,COUNTIF(U45:AL45,"<=0")=0),U$36,99) -> 19 | V49: =IF(AND(V45>0,COUNTIF(V45:AL45,"<=0")=0),V$36,99) -> 20 | W49: =IF(AND(W45>0,COUNTIF(W45:AL45,"<=0")=0),W$36,99) -> 21 | X49: =IF(AND(X45>0,COUNTIF(X45:AL45,"<=0")=0),X$36,99) -> 22 | Y49: =IF(AND(Y45>0,COUNTIF(Y45:AL45,"<=0")=0),Y$36,99) -> 23 | Z49: =IF(AND(Z45>0,COUNTIF(Z45:AL45,"<=0")=0),Z$36,99) -> 24 | AA49: =IF(AND(AA45>0,COUNTIF(AA45:AL45,"<=0")=0),AA$36,99) -> 25 | AB49: =IF(AND(AB45>0,COUNTIF(AB45:AL45,"<=0")=0),AB$36,99) -> 26 | AC49: =IF(AND(AC45>0,COUNTIF(AC45:AL45,"<=0")=0),AC$36,99) -> 27 | AD49: =IF(AND(AD45>0,COUNTIF(AD45:AL45,"<=0")=0),AD$36,99) -> 28 | AE49: =IF(AND(AE45>0,COUNTIF(AE45:AL45,"<=0")=0),AE$36,99) -> 29 | AF49: =IF(AND(AF45>0,COUNTIF(AF45:AL45,"<=0")=0),AF$36,99) -> 30 | AG49: =IF(AND(AG45>0,COUNTIF(AG45:AL45,"<=0")=0),AG$36,99) -> 31 | AH49: =IF(AND(AH45>0,COUNTIF(AH45:AL45,"<=0")=0),AH$36,99) -> 32 | AI49: =IF(AND(AI45>0,COUNTIF(AI45:AL45,"<=0")=0),AI$36,99) -> 33 | AJ49: =IF(AND(AJ45>0,COUNTIF(AJ45:AL45,"<=0")=0),AJ$36,99) -> 34 | AK49: =IF(AND(AK45>0,COUNTIF(AK45:AL45,"<=0")=0),AK$36,99) -> 35 | AL49: =IF(AND(AL45>0,COUNTIF(AL45:AL45,"<=0")=0),AL$36,99) -> 36
A50: pb_flag | B50: служебно: месяц окупаемости | C50: =IF(AND(C48>=0,COUNTIF(C48:AL48,"<0")=0),C$36,99) -> 99 | D50: =IF(AND(D48>=0,COUNTIF(D48:AL48,"<0")=0),D$36,99) -> 99 | E50: =IF(AND(E48>=0,COUNTIF(E48:AL48,"<0")=0),E$36,99) -> 99 | F50: =IF(AND(F48>=0,COUNTIF(F48:AL48,"<0")=0),F$36,99) -> 99 | G50: =IF(AND(G48>=0,COUNTIF(G48:AL48,"<0")=0),G$36,99) -> 99 | H50: =IF(AND(H48>=0,COUNTIF(H48:AL48,"<0")=0),H$36,99) -> 99 | I50: =IF(AND(I48>=0,COUNTIF(I48:AL48,"<0")=0),I$36,99) -> 99 | J50: =IF(AND(J48>=0,COUNTIF(J48:AL48,"<0")=0),J$36,99) -> 99 | K50: =IF(AND(K48>=0,COUNTIF(K48:AL48,"<0")=0),K$36,99) -> 99 | L50: =IF(AND(L48>=0,COUNTIF(L48:AL48,"<0")=0),L$36,99) -> 10 | M50: =IF(AND(M48>=0,COUNTIF(M48:AL48,"<0")=0),M$36,99) -> 11 | N50: =IF(AND(N48>=0,COUNTIF(N48:AL48,"<0")=0),N$36,99) -> 12 | O50: =IF(AND(O48>=0,COUNTIF(O48:AL48,"<0")=0),O$36,99) -> 13 | P50: =IF(AND(P48>=0,COUNTIF(P48:AL48,"<0")=0),P$36,99) -> 14 | Q50: =IF(AND(Q48>=0,COUNTIF(Q48:AL48,"<0")=0),Q$36,99) -> 15 | R50: =IF(AND(R48>=0,COUNTIF(R48:AL48,"<0")=0),R$36,99) -> 16 | S50: =IF(AND(S48>=0,COUNTIF(S48:AL48,"<0")=0),S$36,99) -> 17 | T50: =IF(AND(T48>=0,COUNTIF(T48:AL48,"<0")=0),T$36,99) -> 18 | U50: =IF(AND(U48>=0,COUNTIF(U48:AL48,"<0")=0),U$36,99) -> 19 | V50: =IF(AND(V48>=0,COUNTIF(V48:AL48,"<0")=0),V$36,99) -> 20 | W50: =IF(AND(W48>=0,COUNTIF(W48:AL48,"<0")=0),W$36,99) -> 21 | X50: =IF(AND(X48>=0,COUNTIF(X48:AL48,"<0")=0),X$36,99) -> 22 | Y50: =IF(AND(Y48>=0,COUNTIF(Y48:AL48,"<0")=0),Y$36,99) -> 23 | Z50: =IF(AND(Z48>=0,COUNTIF(Z48:AL48,"<0")=0),Z$36,99) -> 24 | AA50: =IF(AND(AA48>=0,COUNTIF(AA48:AL48,"<0")=0),AA$36,99) -> 25 | AB50: =IF(AND(AB48>=0,COUNTIF(AB48:AL48,"<0")=0),AB$36,99) -> 26 | AC50: =IF(AND(AC48>=0,COUNTIF(AC48:AL48,"<0")=0),AC$36,99) -> 27 | AD50: =IF(AND(AD48>=0,COUNTIF(AD48:AL48,"<0")=0),AD$36,99) -> 28 | AE50: =IF(AND(AE48>=0,COUNTIF(AE48:AL48,"<0")=0),AE$36,99) -> 29 | AF50: =IF(AND(AF48>=0,COUNTIF(AF48:AL48,"<0")=0),AF$36,99) -> 30 | AG50: =IF(AND(AG48>=0,COUNTIF(AG48:AL48,"<0")=0),AG$36,99) -> 31 | AH50: =IF(AND(AH48>=0,COUNTIF(AH48:AL48,"<0")=0),AH$36,99) -> 32 | AI50: =IF(AND(AI48>=0,COUNTIF(AI48:AL48,"<0")=0),AI$36,99) -> 33 | AJ50: =IF(AND(AJ48>=0,COUNTIF(AJ48:AL48,"<0")=0),AJ$36,99) -> 34 | AK50: =IF(AND(AK48>=0,COUNTIF(AK48:AL48,"<0")=0),AK$36,99) -> 35 | AL50: =IF(AND(AL48>=0,COUNTIF(AL48:AL48,"<0")=0),AL$36,99) -> 36

Sheet C_обучение_профи
A1: C. Обучение профессионалов: ДПО/НМО для медсестёр и педиатров + «первая помощь детям» для педагогов (лицензия НГУ, доля выручки)
A4: Сценарий: Осторожный | B4: Месяц → | C4: 1 | D4: 2 | E4: 3 | F4: 4 | G4: 5 | H4: 6 | I4: 7 | J4: 8 | K4: 9 | L4: 10 | M4: 11 | N4: 12 | O4: 13 | P4: 14 | Q4: 15 | R4: 16 | S4: 17 | T4: 18 | U4: 19 | V4: 20 | W4: 21 | X4: 22 | Y4: 23 | Z4: 24 | AA4: 25 | AB4: 26 | AC4: 27 | AD4: 28 | AE4: 29 | AF4: 30 | AG4: 31 | AH4: 32 | AI4: 33 | AJ4: 34 | AK4: 35 | AL4: 36 | AM4: Год 1 | AN4: Год 2 | AO4: Год 3 | AP4: Итого 36 мес
A5: n_pro | B5: Продажи медработникам, шт | C5: =Допущения!$C$61*IF(C$4<Допущения!$C$58,0,((C$4-Допущения!$C$58+1)/(36-Допущения!$C$58+1))^Допущения!$C$67) -> 0 | D5: =Допущения!$C$61*IF(D$4<Допущения!$C$58,0,((D$4-Допущения!$C$58+1)/(36-Допущения!$C$58+1))^Допущения!$C$67) -> 0 | E5: =Допущения!$C$61*IF(E$4<Допущения!$C$58,0,((E$4-Допущения!$C$58+1)/(36-Допущения!$C$58+1))^Допущения!$C$67) -> 0 | F5: =Допущения!$C$61*IF(F$4<Допущения!$C$58,0,((F$4-Допущения!$C$58+1)/(36-Допущения!$C$58+1))^Допущения!$C$67) -> 0 | G5: =Допущения!$C$61*IF(G$4<Допущения!$C$58,0,((G$4-Допущения!$C$58+1)/(36-Допущения!$C$58+1))^Допущения!$C$67) -> 0 | H5: =Допущения!$C$61*IF(H$4<Допущения!$C$58,0,((H$4-Допущения!$C$58+1)/(36-Допущения!$C$58+1))^Допущения!$C$67) -> 0 | I5: =Допущения!$C$61*IF(I$4<Допущения!$C$58,0,((I$4-Допущения!$C$58+1)/(36-Допущения!$C$58+1))^Допущения!$C$67) -> 0 | J5: =Допущения!$C$61*IF(J$4<Допущения!$C$58,0,((J$4-Допущения!$C$58+1)/(36-Допущения!$C$58+1))^Допущения!$C$67) -> 0 | ... AL5: =Допущения!$C$61*IF(AL$4<Допущения!$C$58,0,((AL$4-Допущения!$C$58+1)/(36-Допущения!$C$58+1))^Допущения!$C$67) -> 60 | AM5: =SUM(C5:N5) -> 6.3110204 | AN5: =SUM(O5:Z5) -> 190.07415 | AO5: =SUM(AA5:AL5) -> 538.16746 | AP5: =SUM(C5:AL5) -> 734.55263
A6: n_ped | B6: Продажи педагогам, шт | C6: =Допущения!$C$63*IF(C$4<Допущения!$C$58,0,((C$4-Допущения!$C$58+1)/(36-Допущения!$C$58+1))^Допущения!$C$67) -> 0 | D6: =Допущения!$C$63*IF(D$4<Допущения!$C$58,0,((D$4-Допущения!$C$58+1)/(36-Допущения!$C$58+1))^Допущения!$C$67) -> 0 | E6: =Допущения!$C$63*IF(E$4<Допущения!$C$58,0,((E$4-Допущения!$C$58+1)/(36-Допущения!$C$58+1))^Допущения!$C$67) -> 0 | F6: =Допущения!$C$63*IF(F$4<Допущения!$C$58,0,((F$4-Допущения!$C$58+1)/(36-Допущения!$C$58+1))^Допущения!$C$67) -> 0 | G6: =Допущения!$C$63*IF(G$4<Допущения!$C$58,0,((G$4-Допущения!$C$58+1)/(36-Допущения!$C$58+1))^Допущения!$C$67) -> 0 | H6: =Допущения!$C$63*IF(H$4<Допущения!$C$58,0,((H$4-Допущения!$C$58+1)/(36-Допущения!$C$58+1))^Допущения!$C$67) -> 0 | I6: =Допущения!$C$63*IF(I$4<Допущения!$C$58,0,((I$4-Допущения!$C$58+1)/(36-Допущения!$C$58+1))^Допущения!$C$67) -> 0 | J6: =Допущения!$C$63*IF(J$4<Допущения!$C$58,0,((J$4-Допущения!$C$58+1)/(36-Допущения!$C$58+1))^Допущения!$C$67) -> 0 | ... AL6: =Допущения!$C$63*IF(AL$4<Допущения!$C$58,0,((AL$4-Допущения!$C$58+1)/(36-Допущения!$C$58+1))^Допущения!$C$67) -> 200 | AM6: =SUM(C6:N6) -> 21.036735 | AN6: =SUM(O6:Z6) -> 633.58051 | AO6: =SUM(AA6:AL6) -> 1793.8915 | AP6: =SUM(C6:AL6) -> 2448.5088
A7: gross | B7: Валовая выручка программ (вся, вкл. долю НГУ) | C7: =C5*Допущения!$C$60+C6*Допущения!$C$62 -> 0 | D7: =D5*Допущения!$C$60+D6*Допущения!$C$62 -> 0 | E7: =E5*Допущения!$C$60+E6*Допущения!$C$62 -> 0 | F7: =F5*Допущения!$C$60+F6*Допущения!$C$62 -> 0 | G7: =G5*Допущения!$C$60+G6*Допущения!$C$62 -> 0 | H7: =H5*Допущения!$C$60+H6*Допущения!$C$62 -> 0 | I7: =I5*Допущения!$C$60+I6*Допущения!$C$62 -> 0 | J7: =J5*Допущения!$C$60+J6*Допущения!$C$62 -> 0 | ... AL7: =AL5*Допущения!$C$60+AL6*Допущения!$C$62 -> 390000 | AM7: =SUM(C7:N7) -> 41021.632 | AN7: =SUM(O7:Z7) -> 1235482 | AO7: =SUM(AA7:AL7) -> 3498088.5 | AP7: =SUM(C7:AL7) -> 4774592.1
A8: rev | B8: Выручка владельца (его доля) | C8: =C7*Допущения!$C$59 -> 0 | D8: =D7*Допущения!$C$59 -> 0 | E8: =E7*Допущения!$C$59 -> 0 | F8: =F7*Допущения!$C$59 -> 0 | G8: =G7*Допущения!$C$59 -> 0 | H8: =H7*Допущения!$C$59 -> 0 | I8: =I7*Допущения!$C$59 -> 0 | J8: =J7*Допущения!$C$59 -> 0 | ... AL8: =AL7*Допущения!$C$59 -> 136500 | AM8: =SUM(C8:N8) -> 14357.571 | AN8: =SUM(O8:Z8) -> 432418.7 | AO8: =SUM(AA8:AL8) -> 1224331 | AP8: =SUM(C8:AL8) -> 1671107.2
A9: contrib | B9: Маржинальный доход (доля − налог) | C9: =C8*(1-Допущения!$C$14) -> 0 | D9: =D8*(1-Допущения!$C$14) -> 0 | E9: =E8*(1-Допущения!$C$14) -> 0 | F9: =F8*(1-Допущения!$C$14) -> 0 | G9: =G8*(1-Допущения!$C$14) -> 0 | H9: =H8*(1-Допущения!$C$14) -> 0 | I9: =I8*(1-Допущения!$C$14) -> 0 | J9: =J8*(1-Допущения!$C$14) -> 0 | ... AL9: =AL8*(1-Допущения!$C$14) -> 128310 | AM9: =SUM(C9:N9) -> 13496.117 | AN9: =SUM(O9:Z9) -> 406473.58 | AO9: =SUM(AA9:AL9) -> 1150871.1 | AP9: =SUM(C9:AL9) -> 1570840.8
A10: acq | B10: Маркетинг и продажи | C10: =C7*Допущения!$C$64 -> 0 | D10: =D7*Допущения!$C$64 -> 0 | E10: =E7*Допущения!$C$64 -> 0 | F10: =F7*Допущения!$C$64 -> 0 | G10: =G7*Допущения!$C$64 -> 0 | H10: =H7*Допущения!$C$64 -> 0 | I10: =I7*Допущения!$C$64 -> 0 | J10: =J7*Допущения!$C$64 -> 0 | ... AL10: =AL7*Допущения!$C$64 -> 136500 | AM10: =SUM(C10:N10) -> 14357.571 | AN10: =SUM(O10:Z10) -> 432418.7 | AO10: =SUM(AA10:AL10) -> 1224331 | AP10: =SUM(C10:AL10) -> 1671107.2
A11: fixed | B11: Постоянные расходы (команда) | C11: =IF(C$4>=2,Допущения!$C$65,0) -> 0 | D11: =IF(D$4>=2,Допущения!$C$65,0) -> 200000 | E11: =IF(E$4>=2,Допущения!$C$65,0) -> 200000 | F11: =IF(F$4>=2,Допущения!$C$65,0) -> 200000 | G11: =IF(G$4>=2,Допущения!$C$65,0) -> 200000 | H11: =IF(H$4>=2,Допущения!$C$65,0) -> 200000 | I11: =IF(I$4>=2,Допущения!$C$65,0) -> 200000 | J11: =IF(J$4>=2,Допущения!$C$65,0) -> 200000 | ... AL11: =IF(AL$4>=2,Допущения!$C$65,0) -> 200000 | AM11: =SUM(C11:N11) -> 2200000 | AN11: =SUM(O11:Z11) -> 2400000 | AO11: =SUM(AA11:AL11) -> 2400000 | AP11: =SUM(C11:AL11) -> 7000000
A12: op | B12: Операционная прибыль (маржинальный доход − постоянные − привлечение) | C12: =C9-C11-C10 -> 0 | D12: =D9-D11-D10 -> -200000 | E12: =E9-E11-E10 -> -200000 | F12: =F9-F11-F10 -> -200000 | G12: =G9-G11-G10 -> -200000 | H12: =H9-H11-H10 -> -200000 | I12: =I9-I11-I10 -> -200000 | J12: =J9-J11-J10 -> -200000 | ... AL12: =AL9-AL11-AL10 -> -208190 | AM12: =SUM(C12:N12) -> -2200861.5 | AN12: =SUM(O12:Z12) -> -2425945.1 | AO12: =SUM(AA12:AL12) -> -2473459.9 | AP12: =SUM(C12:AL12) -> -7100266.4
A13: capex | B13: CAPEX и вложения в оборотку | C13: =IF(AND(C$4>=MAX(1,Допущения!$C$58-4),C$4<Допущения!$C$58),Допущения!$C$66/(Допущения!$C$58-MAX(1,Допущения!$C$58-4)),0) -> 0 | D13: =IF(AND(D$4>=MAX(1,Допущения!$C$58-4),D$4<Допущения!$C$58),Допущения!$C$66/(Допущения!$C$58-MAX(1,Допущения!$C$58-4)),0) -> 0 | E13: =IF(AND(E$4>=MAX(1,Допущения!$C$58-4),E$4<Допущения!$C$58),Допущения!$C$66/(Допущения!$C$58-MAX(1,Допущения!$C$58-4)),0) -> 0 | F13: =IF(AND(F$4>=MAX(1,Допущения!$C$58-4),F$4<Допущения!$C$58),Допущения!$C$66/(Допущения!$C$58-MAX(1,Допущения!$C$58-4)),0) -> 0 | G13: =IF(AND(G$4>=MAX(1,Допущения!$C$58-4),G$4<Допущения!$C$58),Допущения!$C$66/(Допущения!$C$58-MAX(1,Допущения!$C$58-4)),0) -> 0 | H13: =IF(AND(H$4>=MAX(1,Допущения!$C$58-4),H$4<Допущения!$C$58),Допущения!$C$66/(Допущения!$C$58-MAX(1,Допущения!$C$58-4)),0) -> 375000 | I13: =IF(AND(I$4>=MAX(1,Допущения!$C$58-4),I$4<Допущения!$C$58),Допущения!$C$66/(Допущения!$C$58-MAX(1,Допущения!$C$58-4)),0) -> 375000 | J13: =IF(AND(J$4>=MAX(1,Допущения!$C$58-4),J$4<Допущения!$C$58),Допущения!$C$66/(Допущения!$C$58-MAX(1,Допущения!$C$58-4)),0) -> 375000 | ... AL13: =IF(AND(AL$4>=MAX(1,Допущения!$C$58-4),AL$4<Допущения!$C$58),Допущения!$C$66/(Допущения!$C$58-MAX(1,Допущения!$C$58-4)),0) -> 0 | AM13: =SUM(C13:N13) -> 1500000 | AN13: =SUM(O13:Z13) -> 0 | AO13: =SUM(AA13:AL13) -> 0 | AP13: =SUM(C13:AL13) -> 1500000
A14: cf | B14: Денежный поток | C14: =C12-C13 -> 0 | D14: =D12-D13 -> -200000 | E14: =E12-E13 -> -200000 | F14: =F12-F13 -> -200000 | G14: =G12-G13 -> -200000 | H14: =H12-H13 -> -575000 | I14: =I12-I13 -> -575000 | J14: =J12-J13 -> -575000 | ... AL14: =AL12-AL13 -> -208190 | AM14: =SUM(C14:N14) -> -3700861.5 | AN14: =SUM(O14:Z14) -> -2425945.1 | AO14: =SUM(AA14:AL14) -> -2473459.9 | AP14: =SUM(C14:AL14) -> -8600266.4
A15: cum | B15: Накопленный денежный поток | C15: =0+C14 -> 0 | D15: =C15+D14 -> -200000 | E15: =D15+E14 -> -400000 | F15: =E15+F14 -> -600000 | G15: =F15+G14 -> -800000 | H15: =G15+H14 -> -1375000 | I15: =H15+I14 -> -1950000 | J15: =I15+J14 -> -2525000 | K15: =J15+K14 -> -3100000 | ... AL15: =AK15+AL14 -> -8600266.4 | AM15: =N15 -> -3700861.5 | AN15: =Z15 -> -6126806.6 | AO15: =AL15 -> -8600266.4
A16: be_flag | B16: служебно: месяц устойчивой опер. прибыли | C16: =IF(AND(C12>0,COUNTIF(C12:AL12,"<=0")=0),C$4,99) -> 99 | D16: =IF(AND(D12>0,COUNTIF(D12:AL12,"<=0")=0),D$4,99) -> 99 | E16: =IF(AND(E12>0,COUNTIF(E12:AL12,"<=0")=0),E$4,99) -> 99 | F16: =IF(AND(F12>0,COUNTIF(F12:AL12,"<=0")=0),F$4,99) -> 99 | G16: =IF(AND(G12>0,COUNTIF(G12:AL12,"<=0")=0),G$4,99) -> 99 | H16: =IF(AND(H12>0,COUNTIF(H12:AL12,"<=0")=0),H$4,99) -> 99 | I16: =IF(AND(I12>0,COUNTIF(I12:AL12,"<=0")=0),I$4,99) -> 99 | J16: =IF(AND(J12>0,COUNTIF(J12:AL12,"<=0")=0),J$4,99) -> 99 | K16: =IF(AND(K12>0,COUNTIF(K12:AL12,"<=0")=0),K$4,99) -> 99 | L16: =IF(AND(L12>0,COUNTIF(L12:AL12,"<=0")=0),L$4,99) -> 99 | M16: =IF(AND(M12>0,COUNTIF(M12:AL12,"<=0")=0),M$4,99) -> 99 | N16: =IF(AND(N12>0,COUNTIF(N12:AL12,"<=0")=0),N$4,99) -> 99 | O16: =IF(AND(O12>0,COUNTIF(O12:AL12,"<=0")=0),O$4,99) -> 99 | P16: =IF(AND(P12>0,COUNTIF(P12:AL12,"<=0")=0),P$4,99) -> 99 | Q16: =IF(AND(Q12>0,COUNTIF(Q12:AL12,"<=0")=0),Q$4,99) -> 99 | R16: =IF(AND(R12>0,COUNTIF(R12:AL12,"<=0")=0),R$4,99) -> 99 | S16: =IF(AND(S12>0,COUNTIF(S12:AL12,"<=0")=0),S$4,99) -> 99 | T16: =IF(AND(T12>0,COUNTIF(T12:AL12,"<=0")=0),T$4,99) -> 99 | U16: =IF(AND(U12>0,COUNTIF(U12:AL12,"<=0")=0),U$4,99) -> 99 | V16: =IF(AND(V12>0,COUNTIF(V12:AL12,"<=0")=0),V$4,99) -> 99 | W16: =IF(AND(W12>0,COUNTIF(W12:AL12,"<=0")=0),W$4,99) -> 99 | X16: =IF(AND(X12>0,COUNTIF(X12:AL12,"<=0")=0),X$4,99) -> 99 | Y16: =IF(AND(Y12>0,COUNTIF(Y12:AL12,"<=0")=0),Y$4,99) -> 99 | Z16: =IF(AND(Z12>0,COUNTIF(Z12:AL12,"<=0")=0),Z$4,99) -> 99 | AA16: =IF(AND(AA12>0,COUNTIF(AA12:AL12,"<=0")=0),AA$4,99) -> 99 | AB16: =IF(AND(AB12>0,COUNTIF(AB12:AL12,"<=0")=0),AB$4,99) -> 99 | AC16: =IF(AND(AC12>0,COUNTIF(AC12:AL12,"<=0")=0),AC$4,99) -> 99 | AD16: =IF(AND(AD12>0,COUNTIF(AD12:AL12,"<=0")=0),AD$4,99) -> 99 | AE16: =IF(AND(AE12>0,COUNTIF(AE12:AL12,"<=0")=0),AE$4,99) -> 99 | AF16: =IF(AND(AF12>0,COUNTIF(AF12:AL12,"<=0")=0),AF$4,99) -> 99 | AG16: =IF(AND(AG12>0,COUNTIF(AG12:AL12,"<=0")=0),AG$4,99) -> 99 | AH16: =IF(AND(AH12>0,COUNTIF(AH12:AL12,"<=0")=0),AH$4,99) -> 99 | AI16: =IF(AND(AI12>0,COUNTIF(AI12:AL12,"<=0")=0),AI$4,99) -> 99 | AJ16: =IF(AND(AJ12>0,COUNTIF(AJ12:AL12,"<=0")=0),AJ$4,99) -> 99 | AK16: =IF(AND(AK12>0,COUNTIF(AK12:AL12,"<=0")=0),AK$4,99) -> 99 | AL16: =IF(AND(AL12>0,COUNTIF(AL12:AL12,"<=0")=0),AL$4,99) -> 99
A17: pb_flag | B17: служебно: месяц окупаемости | C17: =IF(AND(C15>=0,COUNTIF(C15:AL15,"<0")=0),C$4,99) -> 99 | D17: =IF(AND(D15>=0,COUNTIF(D15:AL15,"<0")=0),D$4,99) -> 99 | E17: =IF(AND(E15>=0,COUNTIF(E15:AL15,"<0")=0),E$4,99) -> 99 | F17: =IF(AND(F15>=0,COUNTIF(F15:AL15,"<0")=0),F$4,99) -> 99 | G17: =IF(AND(G15>=0,COUNTIF(G15:AL15,"<0")=0),G$4,99) -> 99 | H17: =IF(AND(H15>=0,COUNTIF(H15:AL15,"<0")=0),H$4,99) -> 99 | I17: =IF(AND(I15>=0,COUNTIF(I15:AL15,"<0")=0),I$4,99) -> 99 | J17: =IF(AND(J15>=0,COUNTIF(J15:AL15,"<0")=0),J$4,99) -> 99 | K17: =IF(AND(K15>=0,COUNTIF(K15:AL15,"<0")=0),K$4,99) -> 99 | L17: =IF(AND(L15>=0,COUNTIF(L15:AL15,"<0")=0),L$4,99) -> 99 | M17: =IF(AND(M15>=0,COUNTIF(M15:AL15,"<0")=0),M$4,99) -> 99 | N17: =IF(AND(N15>=0,COUNTIF(N15:AL15,"<0")=0),N$4,99) -> 99 | O17: =IF(AND(O15>=0,COUNTIF(O15:AL15,"<0")=0),O$4,99) -> 99 | P17: =IF(AND(P15>=0,COUNTIF(P15:AL15,"<0")=0),P$4,99) -> 99 | Q17: =IF(AND(Q15>=0,COUNTIF(Q15:AL15,"<0")=0),Q$4,99) -> 99 | R17: =IF(AND(R15>=0,COUNTIF(R15:AL15,"<0")=0),R$4,99) -> 99 | S17: =IF(AND(S15>=0,COUNTIF(S15:AL15,"<0")=0),S$4,99) -> 99 | T17: =IF(AND(T15>=0,COUNTIF(T15:AL15,"<0")=0),T$4,99) -> 99 | U17: =IF(AND(U15>=0,COUNTIF(U15:AL15,"<0")=0),U$4,99) -> 99 | V17: =IF(AND(V15>=0,COUNTIF(V15:AL15,"<0")=0),V$4,99) -> 99 | W17: =IF(AND(W15>=0,COUNTIF(W15:AL15,"<0")=0),W$4,99) -> 99 | X17: =IF(AND(X15>=0,COUNTIF(X15:AL15,"<0")=0),X$4,99) -> 99 | Y17: =IF(AND(Y15>=0,COUNTIF(Y15:AL15,"<0")=0),Y$4,99) -> 99 | Z17: =IF(AND(Z15>=0,COUNTIF(Z15:AL15,"<0")=0),Z$4,99) -> 99 | AA17: =IF(AND(AA15>=0,COUNTIF(AA15:AL15,"<0")=0),AA$4,99) -> 99 | AB17: =IF(AND(AB15>=0,COUNTIF(AB15:AL15,"<0")=0),AB$4,99) -> 99 | AC17: =IF(AND(AC15>=0,COUNTIF(AC15:AL15,"<0")=0),AC$4,99) -> 99 | AD17: =IF(AND(AD15>=0,COUNTIF(AD15:AL15,"<0")=0),AD$4,99) -> 99 | AE17: =IF(AND(AE15>=0,COUNTIF(AE15:AL15,"<0")=0),AE$4,99) -> 99 | AF17: =IF(AND(AF15>=0,COUNTIF(AF15:AL15,"<0")=0),AF$4,99) -> 99 | AG17: =IF(AND(AG15>=0,COUNTIF(AG15:AL15,"<0")=0),AG$4,99) -> 99 | AH17: =IF(AND(AH15>=0,COUNTIF(AH15:AL15,"<0")=0),AH$4,99) -> 99 | AI17: =IF(AND(AI15>=0,COUNTIF(AI15:AL15,"<0")=0),AI$4,99) -> 99 | AJ17: =IF(AND(AJ15>=0,COUNTIF(AJ15:AL15,"<0")=0),AJ$4,99) -> 99 | AK17: =IF(AND(AK15>=0,COUNTIF(AK15:AL15,"<0")=0),AK$4,99) -> 99 | AL17: =IF(AND(AL15>=0,COUNTIF(AL15:AL15,"<0")=0),AL$4,99) -> 99
A19: Сценарий: Базовый | B19: Месяц → | C19: 1 | D19: 2 | E19: 3 | F19: 4 | G19: 5 | H19: 6 | I19: 7 | J19: 8 | K19: 9 | L19: 10 | M19: 11 | N19: 12 | O19: 13 | P19: 14 | Q19: 15 | R19: 16 | S19: 17 | T19: 18 | U19: 19 | V19: 20 | W19: 21 | X19: 22 | Y19: 23 | Z19: 24 | AA19: 25 | AB19: 26 | AC19: 27 | AD19: 28 | AE19: 29 | AF19: 30 | AG19: 31 | AH19: 32 | AI19: 33 | AJ19: 34 | AK19: 35 | AL19: 36 | AM19: Год 1 | AN19: Год 2 | AO19: Год 3 | AP19: Итого 36 мес
A20: n_pro | B20: Продажи медработникам, шт | C20: =Допущения!$D$61*IF(C$19<Допущения!$D$58,0,((C$19-Допущения!$D$58+1)/(36-Допущения!$D$58+1))^Допущения!$D$67) -> 0 | D20: =Допущения!$D$61*IF(D$19<Допущения!$D$58,0,((D$19-Допущения!$D$58+1)/(36-Допущения!$D$58+1))^Допущения!$D$67) -> 0 | E20: =Допущения!$D$61*IF(E$19<Допущения!$D$58,0,((E$19-Допущения!$D$58+1)/(36-Допущения!$D$58+1))^Допущения!$D$67) -> 0 | F20: =Допущения!$D$61*IF(F$19<Допущения!$D$58,0,((F$19-Допущения!$D$58+1)/(36-Допущения!$D$58+1))^Допущения!$D$67) -> 0 | G20: =Допущения!$D$61*IF(G$19<Допущения!$D$58,0,((G$19-Допущения!$D$58+1)/(36-Допущения!$D$58+1))^Допущения!$D$67) -> 0 | H20: =Допущения!$D$61*IF(H$19<Допущения!$D$58,0,((H$19-Допущения!$D$58+1)/(36-Допущения!$D$58+1))^Допущения!$D$67) -> 0 | I20: =Допущения!$D$61*IF(I$19<Допущения!$D$58,0,((I$19-Допущения!$D$58+1)/(36-Допущения!$D$58+1))^Допущения!$D$67) -> 3.3766379 | J20: =Допущения!$D$61*IF(J$19<Допущения!$D$58,0,((J$19-Допущения!$D$58+1)/(36-Допущения!$D$58+1))^Допущения!$D$67) -> 7.7574768 | ... AL20: =Допущения!$D$61*IF(AL$19<Допущения!$D$58,0,((AL$19-Допущения!$D$58+1)/(36-Допущения!$D$58+1))^Допущения!$D$67) -> 200 | AM20: =SUM(C20:N20) -> 93.860687 | AN20: =SUM(O20:Z20) -> 847.19351 | AO20: =SUM(AA20:AL20) -> 1886.7002 | AP20: =SUM(C20:AL20) -> 2827.7544
A21: n_ped | B21: Продажи педагогам, шт | C21: =Допущения!$D$63*IF(C$19<Допущения!$D$58,0,((C$19-Допущения!$D$58+1)/(36-Допущения!$D$58+1))^Допущения!$D$67) -> 0 | D21: =Допущения!$D$63*IF(D$19<Допущения!$D$58,0,((D$19-Допущения!$D$58+1)/(36-Допущения!$D$58+1))^Допущения!$D$67) -> 0 | E21: =Допущения!$D$63*IF(E$19<Допущения!$D$58,0,((E$19-Допущения!$D$58+1)/(36-Допущения!$D$58+1))^Допущения!$D$67) -> 0 | F21: =Допущения!$D$63*IF(F$19<Допущения!$D$58,0,((F$19-Допущения!$D$58+1)/(36-Допущения!$D$58+1))^Допущения!$D$67) -> 0 | G21: =Допущения!$D$63*IF(G$19<Допущения!$D$58,0,((G$19-Допущения!$D$58+1)/(36-Допущения!$D$58+1))^Допущения!$D$67) -> 0 | H21: =Допущения!$D$63*IF(H$19<Допущения!$D$58,0,((H$19-Допущения!$D$58+1)/(36-Допущения!$D$58+1))^Допущения!$D$67) -> 0 | I21: =Допущения!$D$63*IF(I$19<Допущения!$D$58,0,((I$19-Допущения!$D$58+1)/(36-Допущения!$D$58+1))^Допущения!$D$67) -> 10.129914 | J21: =Допущения!$D$63*IF(J$19<Допущения!$D$58,0,((J$19-Допущения!$D$58+1)/(36-Допущения!$D$58+1))^Допущения!$D$67) -> 23.27243 | ... AL21: =Допущения!$D$63*IF(AL$19<Допущения!$D$58,0,((AL$19-Допущения!$D$58+1)/(36-Допущения!$D$58+1))^Допущения!$D$67) -> 600 | AM21: =SUM(C21:N21) -> 281.58206 | AN21: =SUM(O21:Z21) -> 2541.5805 | AO21: =SUM(AA21:AL21) -> 5660.1006 | AP21: =SUM(C21:AL21) -> 8483.2632
A22: gross | B22: Валовая выручка программ (вся, вкл. долю НГУ) | C22: =C20*Допущения!$D$60+C21*Допущения!$D$62 -> 0 | D22: =D20*Допущения!$D$60+D21*Допущения!$D$62 -> 0 | E22: =E20*Допущения!$D$60+E21*Допущения!$D$62 -> 0 | F22: =F20*Допущения!$D$60+F21*Допущения!$D$62 -> 0 | G22: =G20*Допущения!$D$60+G21*Допущения!$D$62 -> 0 | H22: =H20*Допущения!$D$60+H21*Допущения!$D$62 -> 0 | I22: =I20*Допущения!$D$60+I21*Допущения!$D$62 -> 27350.767 | J22: =J20*Допущения!$D$60+J21*Допущения!$D$62 -> 62835.562 | ... AL22: =AL20*Допущения!$D$60+AL21*Допущения!$D$62 -> 1620000 | AM22: =SUM(C22:N22) -> 760271.57 | AN22: =SUM(O22:Z22) -> 6862267.4 | AO22: =SUM(AA22:AL22) -> 15282272 | AP22: =SUM(C22:AL22) -> 22904811
A23: rev | B23: Выручка владельца (его доля) | C23: =C22*Допущения!$D$59 -> 0 | D23: =D22*Допущения!$D$59 -> 0 | E23: =E22*Допущения!$D$59 -> 0 | F23: =F22*Допущения!$D$59 -> 0 | G23: =G22*Допущения!$D$59 -> 0 | H23: =H22*Допущения!$D$59 -> 0 | I23: =I22*Допущения!$D$59 -> 13675.383 | J23: =J22*Допущения!$D$59 -> 31417.781 | ... AL23: =AL22*Допущения!$D$59 -> 810000 | AM23: =SUM(C23:N23) -> 380135.78 | AN23: =SUM(O23:Z23) -> 3431133.7 | AO23: =SUM(AA23:AL23) -> 7641135.8 | AP23: =SUM(C23:AL23) -> 11452405
A24: contrib | B24: Маржинальный доход (доля − налог) | C24: =C23*(1-Допущения!$D$14) -> 0 | D24: =D23*(1-Допущения!$D$14) -> 0 | E24: =E23*(1-Допущения!$D$14) -> 0 | F24: =F23*(1-Допущения!$D$14) -> 0 | G24: =G23*(1-Допущения!$D$14) -> 0 | H24: =H23*(1-Допущения!$D$14) -> 0 | I24: =I23*(1-Допущения!$D$14) -> 12854.86 | J24: =J23*(1-Допущения!$D$14) -> 29532.714 | ... AL24: =AL23*(1-Допущения!$D$14) -> 761400 | AM24: =SUM(C24:N24) -> 357327.64 | AN24: =SUM(O24:Z24) -> 3225265.7 | AO24: =SUM(AA24:AL24) -> 7182667.7 | AP24: =SUM(C24:AL24) -> 10765261
A25: acq | B25: Маркетинг и продажи | C25: =C22*Допущения!$D$64 -> 0 | D25: =D22*Допущения!$D$64 -> 0 | E25: =E22*Допущения!$D$64 -> 0 | F25: =F22*Допущения!$D$64 -> 0 | G25: =G22*Допущения!$D$64 -> 0 | H25: =H22*Допущения!$D$64 -> 0 | I25: =I22*Допущения!$D$64 -> 6837.6917 | J25: =J22*Допущения!$D$64 -> 15708.89 | ... AL25: =AL22*Допущения!$D$64 -> 405000 | AM25: =SUM(C25:N25) -> 190067.89 | AN25: =SUM(O25:Z25) -> 1715566.9 | AO25: =SUM(AA25:AL25) -> 3820567.9 | AP25: =SUM(C25:AL25) -> 5726202.7
A26: fixed | B26: Постоянные расходы (команда) | C26: =IF(C$19>=2,Допущения!$D$65,0) -> 0 | D26: =IF(D$19>=2,Допущения!$D$65,0) -> 170000 | E26: =IF(E$19>=2,Допущения!$D$65,0) -> 170000 | F26: =IF(F$19>=2,Допущения!$D$65,0) -> 170000 | G26: =IF(G$19>=2,Допущения!$D$65,0) -> 170000 | H26: =IF(H$19>=2,Допущения!$D$65,0) -> 170000 | I26: =IF(I$19>=2,Допущения!$D$65,0) -> 170000 | J26: =IF(J$19>=2,Допущения!$D$65,0) -> 170000 | ... AL26: =IF(AL$19>=2,Допущения!$D$65,0) -> 170000 | AM26: =SUM(C26:N26) -> 1870000 | AN26: =SUM(O26:Z26) -> 2040000 | AO26: =SUM(AA26:AL26) -> 2040000 | AP26: =SUM(C26:AL26) -> 5950000
A27: op | B27: Операционная прибыль (маржинальный доход − постоянные − привлечение) | C27: =C24-C26-C25 -> 0 | D27: =D24-D26-D25 -> -170000 | E27: =E24-E26-E25 -> -170000 | F27: =F24-F26-F25 -> -170000 | G27: =G24-G26-G25 -> -170000 | H27: =H24-H26-H25 -> -170000 | I27: =I24-I26-I25 -> -163982.83 | J27: =J24-J26-J25 -> -156176.18 | ... AL27: =AL24-AL26-AL25 -> 186400 | AM27: =SUM(C27:N27) -> -1702740.3 | AN27: =SUM(O27:Z27) -> -530301.17 | AO27: =SUM(AA27:AL27) -> 1322099.8 | AP27: =SUM(C27:AL27) -> -910941.67
A28: capex | B28: CAPEX и вложения в оборотку | C28: =IF(AND(C$19>=MAX(1,Допущения!$D$58-4),C$19<Допущения!$D$58),Допущения!$D$66/(Допущения!$D$58-MAX(1,Допущения!$D$58-4)),0) -> 0 | D28: =IF(AND(D$19>=MAX(1,Допущения!$D$58-4),D$19<Допущения!$D$58),Допущения!$D$66/(Допущения!$D$58-MAX(1,Допущения!$D$58-4)),0) -> 0 | E28: =IF(AND(E$19>=MAX(1,Допущения!$D$58-4),E$19<Допущения!$D$58),Допущения!$D$66/(Допущения!$D$58-MAX(1,Допущения!$D$58-4)),0) -> 250000 | F28: =IF(AND(F$19>=MAX(1,Допущения!$D$58-4),F$19<Допущения!$D$58),Допущения!$D$66/(Допущения!$D$58-MAX(1,Допущения!$D$58-4)),0) -> 250000 | G28: =IF(AND(G$19>=MAX(1,Допущения!$D$58-4),G$19<Допущения!$D$58),Допущения!$D$66/(Допущения!$D$58-MAX(1,Допущения!$D$58-4)),0) -> 250000 | H28: =IF(AND(H$19>=MAX(1,Допущения!$D$58-4),H$19<Допущения!$D$58),Допущения!$D$66/(Допущения!$D$58-MAX(1,Допущения!$D$58-4)),0) -> 250000 | I28: =IF(AND(I$19>=MAX(1,Допущения!$D$58-4),I$19<Допущения!$D$58),Допущения!$D$66/(Допущения!$D$58-MAX(1,Допущения!$D$58-4)),0) -> 0 | J28: =IF(AND(J$19>=MAX(1,Допущения!$D$58-4),J$19<Допущения!$D$58),Допущения!$D$66/(Допущения!$D$58-MAX(1,Допущения!$D$58-4)),0) -> 0 | ... AL28: =IF(AND(AL$19>=MAX(1,Допущения!$D$58-4),AL$19<Допущения!$D$58),Допущения!$D$66/(Допущения!$D$58-MAX(1,Допущения!$D$58-4)),0) -> 0 | AM28: =SUM(C28:N28) -> 1000000 | AN28: =SUM(O28:Z28) -> 0 | AO28: =SUM(AA28:AL28) -> 0 | AP28: =SUM(C28:AL28) -> 1000000
A29: cf | B29: Денежный поток | C29: =C27-C28 -> 0 | D29: =D27-D28 -> -170000 | E29: =E27-E28 -> -420000 | F29: =F27-F28 -> -420000 | G29: =G27-G28 -> -420000 | H29: =H27-H28 -> -420000 | I29: =I27-I28 -> -163982.83 | J29: =J27-J28 -> -156176.18 | ... AL29: =AL27-AL28 -> 186400 | AM29: =SUM(C29:N29) -> -2702740.3 | AN29: =SUM(O29:Z29) -> -530301.17 | AO29: =SUM(AA29:AL29) -> 1322099.8 | AP29: =SUM(C29:AL29) -> -1910941.7
A30: cum | B30: Накопленный денежный поток | C30: =0+C29 -> 0 | D30: =C30+D29 -> -170000 | E30: =D30+E29 -> -590000 | F30: =E30+F29 -> -1010000 | G30: =F30+G29 -> -1430000 | H30: =G30+H29 -> -1850000 | I30: =H30+I29 -> -2013982.8 | J30: =I30+J29 -> -2170159 | K30: =J30+K29 -> -2317671.7 | ... AL30: =AK30+AL29 -> -1910941.7 | AM30: =N30 -> -2702740.3 | AN30: =Z30 -> -3233041.4 | AO30: =AL30 -> -1910941.7
A31: be_flag | B31: служебно: месяц устойчивой опер. прибыли | C31: =IF(AND(C27>0,COUNTIF(C27:AL27,"<=0")=0),C$19,99) -> 99 | D31: =IF(AND(D27>0,COUNTIF(D27:AL27,"<=0")=0),D$19,99) -> 99 | E31: =IF(AND(E27>0,COUNTIF(E27:AL27,"<=0")=0),E$19,99) -> 99 | F31: =IF(AND(F27>0,COUNTIF(F27:AL27,"<=0")=0),F$19,99) -> 99 | G31: =IF(AND(G27>0,COUNTIF(G27:AL27,"<=0")=0),G$19,99) -> 99 | H31: =IF(AND(H27>0,COUNTIF(H27:AL27,"<=0")=0),H$19,99) -> 99 | I31: =IF(AND(I27>0,COUNTIF(I27:AL27,"<=0")=0),I$19,99) -> 99 | J31: =IF(AND(J27>0,COUNTIF(J27:AL27,"<=0")=0),J$19,99) -> 99 | K31: =IF(AND(K27>0,COUNTIF(K27:AL27,"<=0")=0),K$19,99) -> 99 | L31: =IF(AND(L27>0,COUNTIF(L27:AL27,"<=0")=0),L$19,99) -> 99 | M31: =IF(AND(M27>0,COUNTIF(M27:AL27,"<=0")=0),M$19,99) -> 99 | N31: =IF(AND(N27>0,COUNTIF(N27:AL27,"<=0")=0),N$19,99) -> 99 | O31: =IF(AND(O27>0,COUNTIF(O27:AL27,"<=0")=0),O$19,99) -> 99 | P31: =IF(AND(P27>0,COUNTIF(P27:AL27,"<=0")=0),P$19,99) -> 99 | Q31: =IF(AND(Q27>0,COUNTIF(Q27:AL27,"<=0")=0),Q$19,99) -> 99 | R31: =IF(AND(R27>0,COUNTIF(R27:AL27,"<=0")=0),R$19,99) -> 99 | S31: =IF(AND(S27>0,COUNTIF(S27:AL27,"<=0")=0),S$19,99) -> 99 | T31: =IF(AND(T27>0,COUNTIF(T27:AL27,"<=0")=0),T$19,99) -> 99 | U31: =IF(AND(U27>0,COUNTIF(U27:AL27,"<=0")=0),U$19,99) -> 99 | V31: =IF(AND(V27>0,COUNTIF(V27:AL27,"<=0")=0),V$19,99) -> 99 | W31: =IF(AND(W27>0,COUNTIF(W27:AL27,"<=0")=0),W$19,99) -> 99 | X31: =IF(AND(X27>0,COUNTIF(X27:AL27,"<=0")=0),X$19,99) -> 99 | Y31: =IF(AND(Y27>0,COUNTIF(Y27:AL27,"<=0")=0),Y$19,99) -> 23 | Z31: =IF(AND(Z27>0,COUNTIF(Z27:AL27,"<=0")=0),Z$19,99) -> 24 | AA31: =IF(AND(AA27>0,COUNTIF(AA27:AL27,"<=0")=0),AA$19,99) -> 25 | AB31: =IF(AND(AB27>0,COUNTIF(AB27:AL27,"<=0")=0),AB$19,99) -> 26 | AC31: =IF(AND(AC27>0,COUNTIF(AC27:AL27,"<=0")=0),AC$19,99) -> 27 | AD31: =IF(AND(AD27>0,COUNTIF(AD27:AL27,"<=0")=0),AD$19,99) -> 28 | AE31: =IF(AND(AE27>0,COUNTIF(AE27:AL27,"<=0")=0),AE$19,99) -> 29 | AF31: =IF(AND(AF27>0,COUNTIF(AF27:AL27,"<=0")=0),AF$19,99) -> 30 | AG31: =IF(AND(AG27>0,COUNTIF(AG27:AL27,"<=0")=0),AG$19,99) -> 31 | AH31: =IF(AND(AH27>0,COUNTIF(AH27:AL27,"<=0")=0),AH$19,99) -> 32 | AI31: =IF(AND(AI27>0,COUNTIF(AI27:AL27,"<=0")=0),AI$19,99) -> 33 | AJ31: =IF(AND(AJ27>0,COUNTIF(AJ27:AL27,"<=0")=0),AJ$19,99) -> 34 | AK31: =IF(AND(AK27>0,COUNTIF(AK27:AL27,"<=0")=0),AK$19,99) -> 35 | AL31: =IF(AND(AL27>0,COUNTIF(AL27:AL27,"<=0")=0),AL$19,99) -> 36
A32: pb_flag | B32: служебно: месяц окупаемости | C32: =IF(AND(C30>=0,COUNTIF(C30:AL30,"<0")=0),C$19,99) -> 99 | D32: =IF(AND(D30>=0,COUNTIF(D30:AL30,"<0")=0),D$19,99) -> 99 | E32: =IF(AND(E30>=0,COUNTIF(E30:AL30,"<0")=0),E$19,99) -> 99 | F32: =IF(AND(F30>=0,COUNTIF(F30:AL30,"<0")=0),F$19,99) -> 99 | G32: =IF(AND(G30>=0,COUNTIF(G30:AL30,"<0")=0),G$19,99) -> 99 | H32: =IF(AND(H30>=0,COUNTIF(H30:AL30,"<0")=0),H$19,99) -> 99 | I32: =IF(AND(I30>=0,COUNTIF(I30:AL30,"<0")=0),I$19,99) -> 99 | J32: =IF(AND(J30>=0,COUNTIF(J30:AL30,"<0")=0),J$19,99) -> 99 | K32: =IF(AND(K30>=0,COUNTIF(K30:AL30,"<0")=0),K$19,99) -> 99 | L32: =IF(AND(L30>=0,COUNTIF(L30:AL30,"<0")=0),L$19,99) -> 99 | M32: =IF(AND(M30>=0,COUNTIF(M30:AL30,"<0")=0),M$19,99) -> 99 | N32: =IF(AND(N30>=0,COUNTIF(N30:AL30,"<0")=0),N$19,99) -> 99 | O32: =IF(AND(O30>=0,COUNTIF(O30:AL30,"<0")=0),O$19,99) -> 99 | P32: =IF(AND(P30>=0,COUNTIF(P30:AL30,"<0")=0),P$19,99) -> 99 | Q32: =IF(AND(Q30>=0,COUNTIF(Q30:AL30,"<0")=0),Q$19,99) -> 99 | R32: =IF(AND(R30>=0,COUNTIF(R30:AL30,"<0")=0),R$19,99) -> 99 | S32: =IF(AND(S30>=0,COUNTIF(S30:AL30,"<0")=0),S$19,99) -> 99 | T32: =IF(AND(T30>=0,COUNTIF(T30:AL30,"<0")=0),T$19,99) -> 99 | U32: =IF(AND(U30>=0,COUNTIF(U30:AL30,"<0")=0),U$19,99) -> 99 | V32: =IF(AND(V30>=0,COUNTIF(V30:AL30,"<0")=0),V$19,99) -> 99 | W32: =IF(AND(W30>=0,COUNTIF(W30:AL30,"<0")=0),W$19,99) -> 99 | X32: =IF(AND(X30>=0,COUNTIF(X30:AL30,"<0")=0),X$19,99) -> 99 | Y32: =IF(AND(Y30>=0,COUNTIF(Y30:AL30,"<0")=0),Y$19,99) -> 99 | Z32: =IF(AND(Z30>=0,COUNTIF(Z30:AL30,"<0")=0),Z$19,99) -> 99 | AA32: =IF(AND(AA30>=0,COUNTIF(AA30:AL30,"<0")=0),AA$19,99) -> 99 | AB32: =IF(AND(AB30>=0,COUNTIF(AB30:AL30,"<0")=0),AB$19,99) -> 99 | AC32: =IF(AND(AC30>=0,COUNTIF(AC30:AL30,"<0")=0),AC$19,99) -> 99 | AD32: =IF(AND(AD30>=0,COUNTIF(AD30:AL30,"<0")=0),AD$19,99) -> 99 | AE32: =IF(AND(AE30>=0,COUNTIF(AE30:AL30,"<0")=0),AE$19,99) -> 99 | AF32: =IF(AND(AF30>=0,COUNTIF(AF30:AL30,"<0")=0),AF$19,99) -> 99 | AG32: =IF(AND(AG30>=0,COUNTIF(AG30:AL30,"<0")=0),AG$19,99) -> 99 | AH32: =IF(AND(AH30>=0,COUNTIF(AH30:AL30,"<0")=0),AH$19,99) -> 99 | AI32: =IF(AND(AI30>=0,COUNTIF(AI30:AL30,"<0")=0),AI$19,99) -> 99 | AJ32: =IF(AND(AJ30>=0,COUNTIF(AJ30:AL30,"<0")=0),AJ$19,99) -> 99 | AK32: =IF(AND(AK30>=0,COUNTIF(AK30:AL30,"<0")=0),AK$19,99) -> 99 | AL32: =IF(AND(AL30>=0,COUNTIF(AL30:AL30,"<0")=0),AL$19,99) -> 99
A34: Сценарий: Оптимистичный | B34: Месяц → | C34: 1 | D34: 2 | E34: 3 | F34: 4 | G34: 5 | H34: 6 | I34: 7 | J34: 8 | K34: 9 | L34: 10 | M34: 11 | N34: 12 | O34: 13 | P34: 14 | Q34: 15 | R34: 16 | S34: 17 | T34: 18 | U34: 19 | V34: 20 | W34: 21 | X34: 22 | Y34: 23 | Z34: 24 | AA34: 25 | AB34: 26 | AC34: 27 | AD34: 28 | AE34: 29 | AF34: 30 | AG34: 31 | AH34: 32 | AI34: 33 | AJ34: 34 | AK34: 35 | AL34: 36 | AM34: Год 1 | AN34: Год 2 | AO34: Год 3 | AP34: Итого 36 мес
A35: n_pro | B35: Продажи медработникам, шт | C35: =Допущения!$E$61*IF(C$34<Допущения!$E$58,0,((C$34-Допущения!$E$58+1)/(36-Допущения!$E$58+1))^Допущения!$E$67) -> 0 | D35: =Допущения!$E$61*IF(D$34<Допущения!$E$58,0,((D$34-Допущения!$E$58+1)/(36-Допущения!$E$58+1))^Допущения!$E$67) -> 0 | E35: =Допущения!$E$61*IF(E$34<Допущения!$E$58,0,((E$34-Допущения!$E$58+1)/(36-Допущения!$E$58+1))^Допущения!$E$67) -> 0 | F35: =Допущения!$E$61*IF(F$34<Допущения!$E$58,0,((F$34-Допущения!$E$58+1)/(36-Допущения!$E$58+1))^Допущения!$E$67) -> 0 | G35: =Допущения!$E$61*IF(G$34<Допущения!$E$58,0,((G$34-Допущения!$E$58+1)/(36-Допущения!$E$58+1))^Допущения!$E$67) -> 15.625 | H35: =Допущения!$E$61*IF(H$34<Допущения!$E$58,0,((H$34-Допущения!$E$58+1)/(36-Допущения!$E$58+1))^Допущения!$E$67) -> 31.25 | I35: =Допущения!$E$61*IF(I$34<Допущения!$E$58,0,((I$34-Допущения!$E$58+1)/(36-Допущения!$E$58+1))^Допущения!$E$67) -> 46.875 | J35: =Допущения!$E$61*IF(J$34<Допущения!$E$58,0,((J$34-Допущения!$E$58+1)/(36-Допущения!$E$58+1))^Допущения!$E$67) -> 62.5 | ... AL35: =Допущения!$E$61*IF(AL$34<Допущения!$E$58,0,((AL$34-Допущения!$E$58+1)/(36-Допущения!$E$58+1))^Допущения!$E$67) -> 500 | AM35: =SUM(C35:N35) -> 562.5 | AN35: =SUM(O35:Z35) -> 2718.75 | AO35: =SUM(AA35:AL35) -> 4968.75 | AP35: =SUM(C35:AL35) -> 8250
A36: n_ped | B36: Продажи педагогам, шт | C36: =Допущения!$E$63*IF(C$34<Допущения!$E$58,0,((C$34-Допущения!$E$58+1)/(36-Допущения!$E$58+1))^Допущения!$E$67) -> 0 | D36: =Допущения!$E$63*IF(D$34<Допущения!$E$58,0,((D$34-Допущения!$E$58+1)/(36-Допущения!$E$58+1))^Допущения!$E$67) -> 0 | E36: =Допущения!$E$63*IF(E$34<Допущения!$E$58,0,((E$34-Допущения!$E$58+1)/(36-Допущения!$E$58+1))^Допущения!$E$67) -> 0 | F36: =Допущения!$E$63*IF(F$34<Допущения!$E$58,0,((F$34-Допущения!$E$58+1)/(36-Допущения!$E$58+1))^Допущения!$E$67) -> 0 | G36: =Допущения!$E$63*IF(G$34<Допущения!$E$58,0,((G$34-Допущения!$E$58+1)/(36-Допущения!$E$58+1))^Допущения!$E$67) -> 46.875 | H36: =Допущения!$E$63*IF(H$34<Допущения!$E$58,0,((H$34-Допущения!$E$58+1)/(36-Допущения!$E$58+1))^Допущения!$E$67) -> 93.75 | I36: =Допущения!$E$63*IF(I$34<Допущения!$E$58,0,((I$34-Допущения!$E$58+1)/(36-Допущения!$E$58+1))^Допущения!$E$67) -> 140.625 | J36: =Допущения!$E$63*IF(J$34<Допущения!$E$58,0,((J$34-Допущения!$E$58+1)/(36-Допущения!$E$58+1))^Допущения!$E$67) -> 187.5 | ... AL36: =Допущения!$E$63*IF(AL$34<Допущения!$E$58,0,((AL$34-Допущения!$E$58+1)/(36-Допущения!$E$58+1))^Допущения!$E$67) -> 1500 | AM36: =SUM(C36:N36) -> 1687.5 | AN36: =SUM(O36:Z36) -> 8156.25 | AO36: =SUM(AA36:AL36) -> 14906.25 | AP36: =SUM(C36:AL36) -> 24750
A37: gross | B37: Валовая выручка программ (вся, вкл. долю НГУ) | C37: =C35*Допущения!$E$60+C36*Допущения!$E$62 -> 0 | D37: =D35*Допущения!$E$60+D36*Допущения!$E$62 -> 0 | E37: =E35*Допущения!$E$60+E36*Допущения!$E$62 -> 0 | F37: =F35*Допущения!$E$60+F36*Допущения!$E$62 -> 0 | G37: =G35*Допущения!$E$60+G36*Допущения!$E$62 -> 168750 | H37: =H35*Допущения!$E$60+H36*Допущения!$E$62 -> 337500 | I37: =I35*Допущения!$E$60+I36*Допущения!$E$62 -> 506250 | J37: =J35*Допущения!$E$60+J36*Допущения!$E$62 -> 675000 | ... AL37: =AL35*Допущения!$E$60+AL36*Допущения!$E$62 -> 5400000 | AM37: =SUM(C37:N37) -> 6075000 | AN37: =SUM(O37:Z37) -> 29362500 | AO37: =SUM(AA37:AL37) -> 53662500 | AP37: =SUM(C37:AL37) -> 89100000
A38: rev | B38: Выручка владельца (его доля) | C38: =C37*Допущения!$E$59 -> 0 | D38: =D37*Допущения!$E$59 -> 0 | E38: =E37*Допущения!$E$59 -> 0 | F38: =F37*Допущения!$E$59 -> 0 | G38: =G37*Допущения!$E$59 -> 101250 | H38: =H37*Допущения!$E$59 -> 202500 | I38: =I37*Допущения!$E$59 -> 303750 | J38: =J37*Допущения!$E$59 -> 405000 | ... AL38: =AL37*Допущения!$E$59 -> 3240000 | AM38: =SUM(C38:N38) -> 3645000 | AN38: =SUM(O38:Z38) -> 17617500 | AO38: =SUM(AA38:AL38) -> 32197500 | AP38: =SUM(C38:AL38) -> 53460000
A39: contrib | B39: Маржинальный доход (доля − налог) | C39: =C38*(1-Допущения!$E$14) -> 0 | D39: =D38*(1-Допущения!$E$14) -> 0 | E39: =E38*(1-Допущения!$E$14) -> 0 | F39: =F38*(1-Допущения!$E$14) -> 0 | G39: =G38*(1-Допущения!$E$14) -> 95175 | H39: =H38*(1-Допущения!$E$14) -> 190350 | I39: =I38*(1-Допущения!$E$14) -> 285525 | J39: =J38*(1-Допущения!$E$14) -> 380700 | ... AL39: =AL38*(1-Допущения!$E$14) -> 3045600 | AM39: =SUM(C39:N39) -> 3426300 | AN39: =SUM(O39:Z39) -> 16560450 | AO39: =SUM(AA39:AL39) -> 30265650 | AP39: =SUM(C39:AL39) -> 50252400
A40: acq | B40: Маркетинг и продажи | C40: =C37*Допущения!$E$64 -> 0 | D40: =D37*Допущения!$E$64 -> 0 | E40: =E37*Допущения!$E$64 -> 0 | F40: =F37*Допущения!$E$64 -> 0 | G40: =G37*Допущения!$E$64 -> 25312.5 | H40: =H37*Допущения!$E$64 -> 50625 | I40: =I37*Допущения!$E$64 -> 75937.5 | J40: =J37*Допущения!$E$64 -> 101250 | ... AL40: =AL37*Допущения!$E$64 -> 810000 | AM40: =SUM(C40:N40) -> 911250 | AN40: =SUM(O40:Z40) -> 4404375 | AO40: =SUM(AA40:AL40) -> 8049375 | AP40: =SUM(C40:AL40) -> 13365000
A41: fixed | B41: Постоянные расходы (команда) | C41: =IF(C$34>=2,Допущения!$E$65,0) -> 0 | D41: =IF(D$34>=2,Допущения!$E$65,0) -> 150000 | E41: =IF(E$34>=2,Допущения!$E$65,0) -> 150000 | F41: =IF(F$34>=2,Допущения!$E$65,0) -> 150000 | G41: =IF(G$34>=2,Допущения!$E$65,0) -> 150000 | H41: =IF(H$34>=2,Допущения!$E$65,0) -> 150000 | I41: =IF(I$34>=2,Допущения!$E$65,0) -> 150000 | J41: =IF(J$34>=2,Допущения!$E$65,0) -> 150000 | ... AL41: =IF(AL$34>=2,Допущения!$E$65,0) -> 150000 | AM41: =SUM(C41:N41) -> 1650000 | AN41: =SUM(O41:Z41) -> 1800000 | AO41: =SUM(AA41:AL41) -> 1800000 | AP41: =SUM(C41:AL41) -> 5250000
A42: op | B42: Операционная прибыль (маржинальный доход − постоянные − привлечение) | C42: =C39-C41-C40 -> 0 | D42: =D39-D41-D40 -> -150000 | E42: =E39-E41-E40 -> -150000 | F42: =F39-F41-F40 -> -150000 | G42: =G39-G41-G40 -> -80137.5 | H42: =H39-H41-H40 -> -10275 | I42: =I39-I41-I40 -> 59587.5 | J42: =J39-J41-J40 -> 129450 | ... AL42: =AL39-AL41-AL40 -> 2085600 | AM42: =SUM(C42:N42) -> 865050 | AN42: =SUM(O42:Z42) -> 10356075 | AO42: =SUM(AA42:AL42) -> 20416275 | AP42: =SUM(C42:AL42) -> 31637400
A43: capex | B43: CAPEX и вложения в оборотку | C43: =IF(AND(C$34>=MAX(1,Допущения!$E$58-4),C$34<Допущения!$E$58),Допущения!$E$66/(Допущения!$E$58-MAX(1,Допущения!$E$58-4)),0) -> 175000 | D43: =IF(AND(D$34>=MAX(1,Допущения!$E$58-4),D$34<Допущения!$E$58),Допущения!$E$66/(Допущения!$E$58-MAX(1,Допущения!$E$58-4)),0) -> 175000 | E43: =IF(AND(E$34>=MAX(1,Допущения!$E$58-4),E$34<Допущения!$E$58),Допущения!$E$66/(Допущения!$E$58-MAX(1,Допущения!$E$58-4)),0) -> 175000 | F43: =IF(AND(F$34>=MAX(1,Допущения!$E$58-4),F$34<Допущения!$E$58),Допущения!$E$66/(Допущения!$E$58-MAX(1,Допущения!$E$58-4)),0) -> 175000 | G43: =IF(AND(G$34>=MAX(1,Допущения!$E$58-4),G$34<Допущения!$E$58),Допущения!$E$66/(Допущения!$E$58-MAX(1,Допущения!$E$58-4)),0) -> 0 | H43: =IF(AND(H$34>=MAX(1,Допущения!$E$58-4),H$34<Допущения!$E$58),Допущения!$E$66/(Допущения!$E$58-MAX(1,Допущения!$E$58-4)),0) -> 0 | I43: =IF(AND(I$34>=MAX(1,Допущения!$E$58-4),I$34<Допущения!$E$58),Допущения!$E$66/(Допущения!$E$58-MAX(1,Допущения!$E$58-4)),0) -> 0 | J43: =IF(AND(J$34>=MAX(1,Допущения!$E$58-4),J$34<Допущения!$E$58),Допущения!$E$66/(Допущения!$E$58-MAX(1,Допущения!$E$58-4)),0) -> 0 | ... AL43: =IF(AND(AL$34>=MAX(1,Допущения!$E$58-4),AL$34<Допущения!$E$58),Допущения!$E$66/(Допущения!$E$58-MAX(1,Допущения!$E$58-4)),0) -> 0 | AM43: =SUM(C43:N43) -> 700000 | AN43: =SUM(O43:Z43) -> 0 | AO43: =SUM(AA43:AL43) -> 0 | AP43: =SUM(C43:AL43) -> 700000
A44: cf | B44: Денежный поток | C44: =C42-C43 -> -175000 | D44: =D42-D43 -> -325000 | E44: =E42-E43 -> -325000 | F44: =F42-F43 -> -325000 | G44: =G42-G43 -> -80137.5 | H44: =H42-H43 -> -10275 | I44: =I42-I43 -> 59587.5 | J44: =J42-J43 -> 129450 | ... AL44: =AL42-AL43 -> 2085600 | AM44: =SUM(C44:N44) -> 165050 | AN44: =SUM(O44:Z44) -> 10356075 | AO44: =SUM(AA44:AL44) -> 20416275 | AP44: =SUM(C44:AL44) -> 30937400
A45: cum | B45: Накопленный денежный поток | C45: =0+C44 -> -175000 | D45: =C45+D44 -> -500000 | E45: =D45+E44 -> -825000 | F45: =E45+F44 -> -1150000 | G45: =F45+G44 -> -1230137.5 | H45: =G45+H44 -> -1240412.5 | I45: =H45+I44 -> -1180825 | J45: =I45+J44 -> -1051375 | K45: =J45+K44 -> -852062.5 | ... AL45: =AK45+AL44 -> 30937400 | AM45: =N45 -> 165050 | AN45: =Z45 -> 10521125 | AO45: =AL45 -> 30937400
A46: be_flag | B46: служебно: месяц устойчивой опер. прибыли | C46: =IF(AND(C42>0,COUNTIF(C42:AL42,"<=0")=0),C$34,99) -> 99 | D46: =IF(AND(D42>0,COUNTIF(D42:AL42,"<=0")=0),D$34,99) -> 99 | E46: =IF(AND(E42>0,COUNTIF(E42:AL42,"<=0")=0),E$34,99) -> 99 | F46: =IF(AND(F42>0,COUNTIF(F42:AL42,"<=0")=0),F$34,99) -> 99 | G46: =IF(AND(G42>0,COUNTIF(G42:AL42,"<=0")=0),G$34,99) -> 99 | H46: =IF(AND(H42>0,COUNTIF(H42:AL42,"<=0")=0),H$34,99) -> 99 | I46: =IF(AND(I42>0,COUNTIF(I42:AL42,"<=0")=0),I$34,99) -> 7 | J46: =IF(AND(J42>0,COUNTIF(J42:AL42,"<=0")=0),J$34,99) -> 8 | K46: =IF(AND(K42>0,COUNTIF(K42:AL42,"<=0")=0),K$34,99) -> 9 | L46: =IF(AND(L42>0,COUNTIF(L42:AL42,"<=0")=0),L$34,99) -> 10 | M46: =IF(AND(M42>0,COUNTIF(M42:AL42,"<=0")=0),M$34,99) -> 11 | N46: =IF(AND(N42>0,COUNTIF(N42:AL42,"<=0")=0),N$34,99) -> 12 | O46: =IF(AND(O42>0,COUNTIF(O42:AL42,"<=0")=0),O$34,99) -> 13 | P46: =IF(AND(P42>0,COUNTIF(P42:AL42,"<=0")=0),P$34,99) -> 14 | Q46: =IF(AND(Q42>0,COUNTIF(Q42:AL42,"<=0")=0),Q$34,99) -> 15 | R46: =IF(AND(R42>0,COUNTIF(R42:AL42,"<=0")=0),R$34,99) -> 16 | S46: =IF(AND(S42>0,COUNTIF(S42:AL42,"<=0")=0),S$34,99) -> 17 | T46: =IF(AND(T42>0,COUNTIF(T42:AL42,"<=0")=0),T$34,99) -> 18 | U46: =IF(AND(U42>0,COUNTIF(U42:AL42,"<=0")=0),U$34,99) -> 19 | V46: =IF(AND(V42>0,COUNTIF(V42:AL42,"<=0")=0),V$34,99) -> 20 | W46: =IF(AND(W42>0,COUNTIF(W42:AL42,"<=0")=0),W$34,99) -> 21 | X46: =IF(AND(X42>0,COUNTIF(X42:AL42,"<=0")=0),X$34,99) -> 22 | Y46: =IF(AND(Y42>0,COUNTIF(Y42:AL42,"<=0")=0),Y$34,99) -> 23 | Z46: =IF(AND(Z42>0,COUNTIF(Z42:AL42,"<=0")=0),Z$34,99) -> 24 | AA46: =IF(AND(AA42>0,COUNTIF(AA42:AL42,"<=0")=0),AA$34,99) -> 25 | AB46: =IF(AND(AB42>0,COUNTIF(AB42:AL42,"<=0")=0),AB$34,99) -> 26 | AC46: =IF(AND(AC42>0,COUNTIF(AC42:AL42,"<=0")=0),AC$34,99) -> 27 | AD46: =IF(AND(AD42>0,COUNTIF(AD42:AL42,"<=0")=0),AD$34,99) -> 28 | AE46: =IF(AND(AE42>0,COUNTIF(AE42:AL42,"<=0")=0),AE$34,99) -> 29 | AF46: =IF(AND(AF42>0,COUNTIF(AF42:AL42,"<=0")=0),AF$34,99) -> 30 | AG46: =IF(AND(AG42>0,COUNTIF(AG42:AL42,"<=0")=0),AG$34,99) -> 31 | AH46: =IF(AND(AH42>0,COUNTIF(AH42:AL42,"<=0")=0),AH$34,99) -> 32 | AI46: =IF(AND(AI42>0,COUNTIF(AI42:AL42,"<=0")=0),AI$34,99) -> 33 | AJ46: =IF(AND(AJ42>0,COUNTIF(AJ42:AL42,"<=0")=0),AJ$34,99) -> 34 | AK46: =IF(AND(AK42>0,COUNTIF(AK42:AL42,"<=0")=0),AK$34,99) -> 35 | AL46: =IF(AND(AL42>0,COUNTIF(AL42:AL42,"<=0")=0),AL$34,99) -> 36
